Workbook

Sheet All Responses
A1: Submission Timestamp | B1: Email Address | C1: Workflow Status | D1: Post-Processing Status | E1: Have all Recruiting Requirements been met? | F1: Date Requested | G1: Requester Name | H1: Requester Email | I1: Hire Date | J1: New Hire or Rehire | K1: Employee Type | L1: Hourly or Salary | M1: Temporary ID | N1: First Name | O1: Middle Name | P1: Last Name | Q1: Preferred Name | R1: Position / Job Title | S1: Site Name | T1: Job Site Number | U1: Reporting Manager Name | V1: Reporting Manager Email | W1: E-Business Card | X1: 30-60-90 | Y1: ADP Manager Access | Z1: Cost Sheet | AA1: Leader Access | AB1: Trip Reports Access | AC1: JR | AD1: JONAS Purchasing Software | AE1: JONAS Field Time/Field Project Access | AF1: JONAS EBI Access | AG1: Incidents | AH1: SiteDocs Training Login | AI1: CAA | AJ1: Transform | AK1: Net Promoter Score | AL1: Fleetio / Vehicle | AM1: Credit Card | AN1: Google Account | AO1: Delivery App | AP1: Mobile Phone | AQ1: Computer | AR1: SiteDocs Tablet | AS1: Is the new User getting a previous user assigned computer? | AT1: Reassigned Computer - Previous User's Name | AU1: Is the new User getting a previous user assigned phone? | AV1: Reassigned Phone - Previous User's Name | AW1: Phone Number | AX1: Cost Sheet - Job Site(s) to be assigned | AY1: Delivery Module - Job Site(s) to be assigned | AZ1: JONAS Purchasing - Job Number(s) to be assigned | BA1: JONAS Field Time/Field Project - Job Number(s) to be Assigned | BB1: JONAS EBI - Job Number(s) to be Assigned | BC1: Vehicle Assigned | BD1: Fleetio Access Required | BE1: Additional Notes/Comments | BF1: Signer Name | BG1: Request Date | BH1: BOSS User Account | BI1: Additional System/Equipment Access Needed? | BJ1: Email Requested | BK1: Date Required By | BL1: SiteDocs | BM1: ADP Supervisor Access | BN1: Additional Credit/ Purchasing Accounts | BO1: Request ID | BP1: HR - Email Address Requested | BQ1: HR - SiteDocs Worker ID | BR1: HR - DSS Username | BS1: HR - DSS Password | BT1: HR - Employee assigned to WIS module? | BU1: HR - SiteDocs Training Username | BV1: HR - SiteDocs Training Password | BW1: HR - Date of Submission | BX1: Final Status | BY1: Approval Notes | BZ1: IT - BOSS User Account | CA1: IT - Cost Sheet | CB1: IT - Leader Access | CC1: IT - Trip Reports Access | CD1: IT - Incidents | CE1: IT - CAA | CF1: IT - Transform | CG1: IT - Net Promoter Score | CH1: IT - E-Business Card | CI1: IT - Delivery App | CJ1: IT - Google Account Email | CK1: IT - Google Account Password | CL1: IT - Phone Number | CM1: IT - Phone Voicemail Password | CN1: IT - Computer Model | CO1: IT - Computer Serial Number | CP1: IT - Completion Timestamp | CQ1: Fleetio - Status | CR1: Fleetio - Asset Number | CS1: Fleetio - Vehicle Make | CT1: Fleetio - Vehicle Model | CU1: Fleetio - License Plate | CV1: Fleetio - Timestamp | CW1: Credit Card - Limit | CX1: Credit Card - Currency | CY1: Credit Card - Per | CZ1: Credit Card - Spend Dynamics Username | DA1: Credit Card - Spend Dynamics Password | DB1: Amazon - Username / Number | DC1: Amazon - Password / PIN | DD1: Staples - Username / Number | DE1: Staples - Password / PIN | DF1: HomeDepot - Card Number | DG1: HomeDepot - PIN | DH1: Credit Card - Status | DI1: Credit Card - Timestamp | DJ1: Business Card - Status | DK1: Business Card - Timestamp | DL1: 30-60-90 - Status | DM1: 30-60-90 - Timestamp | DN1: ADP Manager Access - Status | DO1: ADP Manager Access - Timestamp | DP1: ADP Supervisor Access | DQ1: ADP Supervisor Access - Status | DR1: ADP Supervisor Access - Timestamp | DS1: SiteDocs Tablet - Status | DT1: SiteDocs Tablet - Timestamp | DU1: SiteDocs - Status | DV1: SiteDocs - Timestamp | DW1: JR - Status | DX1: JR - Timestamp | DY1: JONAS - Status | DZ1: JONAS - Timestamp | EA1: Final Approver Name | EB1: Final Approval Comments | EC1: Final Denial Reason | ED1: Final Approval Timestamp
F2: 45863 | G2: z | H2: z | I2: 45856 | N2: z | O2: z | P2: z | Q2: z | R2: z | S2: z | T2: z | U2: z | V2: z | AT2: z | AV2: z | AW2: z | AX2: z | AY2: z | AZ2: z | BA2: z, z, z | BB2: z | BE2: z | BF2: z | BG2: 45863
F3: 45863 | G3: z | H3: Vishal.srikanth@team-group.com | I3: 45856 | N3: z | O3: z | P3: z | Q3: z | R3: z | S3: z | T3: z | U3: z | V3: z | AT3: z | AV3: z | AW3: z | AX3: z | AY3: z | AZ3: z | BA3: z, z, z | BB3: z | BE3: z | BF3: z | BG3: 45863
E4: Yes | F4: 45862 | G4: Vish | H4: Vishal.srikanth@team-group.com | I4: 45866 | J4: New Hire | K4: Direct Hire | L4: Hourly | N4: x | O4: y | P4: z | Q4: V | R4: ss | S4: sss | T4: 123 | U4: vs | V4: Vishal.srikanth@team-group.com | W4: Required | X4: Required | Y4: Required | Z4: Required | AA4: Required | AB4: Required | AC4: Required | AD4: Required | AE4: Required | AF4: Required | AG4: Required | AI4: Required | AJ4: Required | AK4: Required | AL4: Required | AM4: Required | AN4: Required | AO4: Required | AP4: Required | AQ4: Required | AR4: Required | AS4: Yes | AT4: vs | AU4: Yes | AV4: vs | AW4: 123 | AX4: vs, vs, vs, vs, vs | AY4: vs | AZ4: vs | BA4: vs, vs, vs, sv, vs, vs | BB4: vs | BC4: Yes | BD4: Yes | BE4: vs | BF4: Vish | BG4: 45862
E5: Yes | F5: 45863 | G5: Vish | H5: Vishal.srikanth@team-group.com | I5: 45902 | J5: New Hire | K5: Direct Hire | L5: Salary | N5: John | O5: JD | P5: Doe | Q5: JD | R5: VP | S5: Form Cambridge | T5: 123 | U5: VS | V5: Vishal.srikanth@team-group.com | W5: Required | X5: Required | Y5: Required | Z5: Required | AA5: Required | AB5: Required | AC5: Required | AD5: Required | AE5: Required | AF5: Required | AG5: Required | AI5: Required | AJ5: Required | AK5: Required | AL5: Required | AM5: Required | AN5: Required | AO5: Required | AP5: Required | AQ5: Required | AR5: Required | BE5: None | BF5: Vish | BG5: 45863
E6: Yes | F6: 45863 | G6: Vish | H6: Vishal.srikanth@team-group.com | I6: 45874 | J6: New Hire | K6: Direct Hire | L6: Salary | N6: John | O6: JD | P6: Doe | Q6: JD | R6: VP | S6: Form Cambridge | T6: 123 | U6: VS | V6: Vishal.srikanth@team-group.com | W6: Required | X6: Required | Y6: Required | Z6: Required | AA6: Required | AB6: Required | AC6: Required | AD6: Required | AE6: Required | AF6: Required | AG6: Required | AI6: Required | AJ6: Required | AK6: Required | AL6: Required | AM6: Required | AN6: Required | AO6: Required | AP6: Required | AQ6: Required | AR6: Required | BE6: none | BF6: Vish | BG6: 45863
E7: Yes | F7: 45863 | G7: Vish | H7: Vishal.srikanth@team-group.com | I7: 45874 | J7: New Hire | K7: Direct Hire | L7: Salary | M7: 250725006 | N7: John | O7: JD | P7: Doe | Q7: JD | R7: VP | S7: Form Cambridge | T7: 123 | U7: VS | V7: Vishal.srikanth@team-group.com | W7: Required | X7: Required | Y7: Required | Z7: Required | AA7: Required | AB7: Required | AC7: Required | AD7: Required | AE7: Required | AF7: Required | AG7: Required | AI7: Required | AJ7: Required | AK7: Required | AL7: Required | AM7: Required | AN7: Required | AO7: Required | AP7: Required | AQ7: Required | AR7: Required | BE7: none | BF7: Vish | BG7: 45863
E8: Yes | F8: 45863 | G8: Vish | H8: Vishal.srikanth@team-group.com | I8: 45874 | J8: New Hire | K8: Direct Hire | L8: Salary | M8: 250725007 | N8: John | O8: JD | P8: Doe | Q8: JD | R8: VP | S8: Form Cambridge | T8: 123 | U8: VS | V8: Vishal.srikanth@team-group.com | W8: Required | X8: Required | Y8: Required | Z8: Required | AA8: Required | AB8: Required | AC8: Required | AD8: Required | AE8: Required | AF8: Required | AG8: Required | AI8: Required | AJ8: Required | AK8: Required | AL8: Required | AM8: Required | AN8: Required | AO8: Required | AP8: Required | AQ8: Required | AR8: Required | AS8: Yes | AT8: vs | AU8: Yes | AV8: usnm | AW8: 123 | AX8: 123 | AY8: 123 | AZ8: 123, 123, 12 | BA8: 123 | BB8: 123 | BC8: Yes | BD8: Yes | BE8: none | BF8: Vish | BG8: 45863
E9: Yes | F9: 45865 | G9: Vish | H9: Vishal.srikanth@team-group.com | I9: 45874 | J9: New Hire | K9: Direct Hire | L9: Hourly | M9: 250727008 | N9: John | O9: JD | P9: Doe | Q9: JD | R9: VP | S9: Form Cambridge | T9: 123 | U9: VS | V9: Vishal.srikanth@team-group.com | W9: Required | X9: Required | Y9: Required | Z9: Required | AA9: Required | AB9: Required | AC9: Required | AD9: Required | AE9: Required | AF9: Required | AG9: Required | AI9: Required | AJ9: Required | AK9: Required | AL9: Required | AM9: Required | AN9: Required | AO9: Required | AP9: Required | AQ9: Required | AR9: Required | AS9: Yes | AT9: vs | AU9: Yes | AV9: usnm | AW9: 123 | AX9: 123, 123, 123 | AY9: 123, 123 | AZ9: 123 | BB9: 123 | BC9: No | BD9: Yes | BE9: none | BF9: Vish | BG9: 45865
E10: Yes | F10: 45865 | G10: Vish | H10: Vishal.srikanth@team-group.com | I10: 45874 | J10: New Hire | K10: Direct Hire | L10: Hourly | M10: 250727009 | N10: John | O10: JD | P10: Doe | Q10: JD | R10: VP | S10: Form Cambridge | T10: 123 | U10: VS | V10: Vishal.srikanth@team-group.com | W10: Required | X10: Required | Y10: Required | Z10: Required | AD10: Required | AE10: Not Required | BE10: none | BF10: Vish | BG10: 45865
E11: Yes | F11: 45866 | G11: Vish | H11: Vishal.srikanth@team-group.com | M11: 250727010 | N11: John | O11: JD | P11: Doe | Q11: JD | R11: VP | S11: Form Cambridge | T11: 123 | U11: VS | V11: Vishal.srikanth@team-group.com | AF11: Required | AP11: Required | AQ11: Required | AS11: Yes | AT11: vs | AU11: Yes | AV11: usnm | AW11: 123 | BB11: 123, 123 | BE11: none | BF11: Vish | BG11: 45866
E12: Yes | F12: 45865 | G12: Vish | H12: Vishal.srikanth@team-group.com | I12: 45874 | J12: New Hire | K12: Direct Hire | L12: Hourly | M12: 250727011 | N12: John | O12: JD | P12: Doe | Q12: JD | R12: VP | S12: Form Cambridge | T12: 123 | U12: VS | V12: Vishal.srikanth@team-group.com | W12: Required | AD12: Required | AO12: Required | AP12: Required | AQ12: Required | AS12: Yes | AT12: usnm | AU12: Yes | AV12: usnm | AW12: 123 | AY12: 123, 123, 123, 123 | AZ12: 123 | BE12: none | BF12: Vish | BG12: 45865
E13: Yes | F13: 45865 | G13: Vish | H13: Vishal.srikanth@team-group.com | I13: 45874 | J13: New Hire | K13: Direct Hire | L13: Hourly | M13: 250727012 | N13: John | O13: JD | P13: Doe | Q13: JD | R13: VP | S13: Form Cambridge | T13: 123 | U13: VS | V13: Vishal.srikanth@team-group.com | W13: Required | AD13: Required | AO13: Required | AP13: Required | AQ13: Required | AS13: Yes | AT13: usnm | AU13: Yes | AV13: usnm | AW13: 123 | AY13: 123, 123, 123, 123 | AZ13: 123 | BE13: none | BF13: Vish | BG13: 45865
E14: Yes | G14: Vish | H14: Vishal.srikanth@team-group.com | M14: 250727013 | N14: John | O14: JD | P14: Doe | Q14: JD | R14: VP | S14: Form Cambridge | T14: 123 | U14: VS | V14: Vishal.srikanth@team-group.com | AD14: Required | AZ14: 123 | BF14: Vish | BG14: 45866
E15: Yes | F15: 45866 | G15: Vish | H15: Vishal.srikanth@team-group.com | M15: 250727014 | N15: John | O15: JD | P15: Doe | Q15: JD | R15: VP | S15: Form Cambridge | T15: 123 | U15: VS | V15: Vishal.srikanth@team-group.com | AF15: Required | BB15: 123 | BF15: Vish | BG15: 45865
E16: Yes | F16: 45865 | G16: Vish | H16: Vishal.srikanth@team-group.com | I16: 45867 | J16: New Hire | K16: Direct Hire | L16: Hourly | M16: 250727015 | N16: John | O16: JD | P16: Doe | Q16: JD | AN16: Required | BF16: Vish | BG16: 45867
E17: Yes | F17: 45866 | G17: Vish | H17: Vishal.srikanth@team-group.com | I17: 45867 | J17: New Hire | K17: Direct Hire | L17: Hourly | M17: 250727016 | N17: John | O17: JD | P17: Doe | Q17: JD | R17: VP | S17: Form Cambridge | T17: 123 | U17: VS | V17: Vishal.srikanth@team-group.com | BF17: Vish | BG17: 45865
E18: Yes | G18: Vish | H18: Vishal.srikanth@team-group.com | J18: New Hire | K18: Direct Hire | L18: Hourly | M18: 250727017 | W18: Required | X18: Required | Y18: Required | Z18: Required | AA18: Required | AB18: Required | AC18: Required | AD18: Required | AE18: Required | AF18: Required | AG18: Required | AI18: Required | AJ18: Required | AK18: Required | AL18: Required | AM18: Required | AN18: Required | AO18: Required | AP18: Required | AQ18: Required | AR18: Required | AS18: Yes | AU18: Yes | BC18: Yes | BD18: Yes
E19: Yes | G19: Vish | H19: Vishal.srikanth@team-group.com | J19: New Hire | K19: Direct Hire | L19: Hourly | M19: 250728018 | W19: Required | X19: Required | Y19: Required | Z19: Required | AA19: Required | AB19: Required | AC19: Required | AD19: Required | AE19: Required | AF19: Required | AG19: Required | AI19: Required | AJ19: Required | AK19: Required | AL19: Required | AM19: Required | AN19: Required | AO19: Required | AP19: Required | AQ19: Required | AR19: Required | AS19: Yes | AU19: Yes | BC19: Yes | BD19: Yes | BF19: Vish | BG19: 45866
E20: Yes | F20: 45866 | G20: Vish | H20: Vishal.srikanth@team-group.com | I20: 45874 | J20: New Hire | K20: Direct Hire | L20: Hourly | M20: 250728019 | N20: John | O20: JD | P20: Doe | Q20: JD | R20: VP | S20: Form Cambridge | T20: 123 | U20: VS | V20: Vishal.srikanth@team-group.com | W20: Required | X20: Not Required | Y20: Required | Z20: Required | AA20: Not Required | AB20: Not Required | AC20: Required | AD20: Not Required | AE20: Not Required | AF20: Required | AL20: Required | AM20: Not Required | AN20: Not Required | AO20: Not Required | AP20: Required | AQ20: Required | AR20: Not Required | AS20: Yes | AT20: usnm | AU20: Yes | AV20: usnm | AW20: 123 | AX20: 123, 123 | BB20: 123, 123, 123, 123, 123 | BC20: Yes | BD20: Yes | BE20: none | BF20: Vish | BG20: 45866
E21: Yes | F21: 45866 | G21: Vish | H21: Vishal.srikanth@team-group.com | J21: New Hire | K21: Direct Hire | L21: Salary | M21: 250728020 | N21: John | O21: JD | P21: Doe | Q21: JD | R21: VP | S21: Form Cambridge | T21: 123 | U21: VS | V21: Vishal.srikanth@team-group.com | X21: Required | Y21: Required | AB21: Required | AF21: Required | AL21: Required | AN21: Required | BB21: 123, 123, 123 | BC21: Yes | BD21: Yes | BF21: Vish | BG21: 45866
E22: Yes | F22: 45866 | G22: Vish | H22: Vishal.srikanth@team-group.com | I22: 45866 | J22: New Hire | K22: Direct Hire | L22: Salary | M22: 250728021 | N22: John | O22: JD | P22: Doe | Q22: JD | R22: VP | S22: Form Cambridge | T22: 123 | U22: VS | V22: Vishal.srikanth@team-group.com | AB22: Required | AO22: Required | AY22: 123, 123, 123 | BF22: Vish | BG22: 45866 | BO22: REQ-1753710025359
E23: Yes | F23: 45866 | G23: Vish | H23: Vishal.srikanth@team-group.com | I23: 45874 | J23: New Hire | K23: Direct Hire | L23: Salary | M23: 250728022 | N23: John | O23: JD | P23: Doe | Q23: JD | R23: VP | S23: Form Cambridge | T23: 123 | U23: VS | V23: Vishal.srikanth@team-group.com | AF23: Required | BB23: 123 | BF23: Vish | BG23: 45866 | BO23: REQ-1753710374600
E24: Yes | F24: 45866 | G24: Vish | H24: Vishal.srikanth@team-group.com | I24: 45866 | J24: New Hire | K24: Direct Hire | L24: Salary | M24: 250728023 | N24: John | O24: JD | P24: Doe | Q24: JD | R24: VP | S24: Form Cambridge | BF24: Vish | BG24: 45866 | BO24: REQ-1753710733135
E25: Yes | F25: 45866 | G25: Vish | H25: Vishal.srikanth@team-group.com | I25: 45874 | J25: New Hire | K25: Direct Hire | L25: Salary | M25: 250728024 | N25: John | O25: JD | P25: Doe | Q25: JD | BF25: Vish | BG25: 45866 | BO25: REQ-1753711057797 | BP25: test@gmail.com | BQ25: 123 | BW25: 45866 | BY25: test
E26: Yes | F26: 45866 | G26: Vish | H26: Vishal.srikanth@team-group.com | I26: 45874 | J26: New Hire | K26: Direct Hire | L26: Hourly | M26: 250728025 | N26: John | BG26: 45866 | BO26: REQ-1753712267593 | BP26: test@gmail.com | BQ26: 123 | BW26: 45866 | BY26: test
E27: Yes | F27: 45866 | G27: Vish | H27: Vishal.srikanth@team-group.com | I27: 45866 | J27: New Hire | K27: Direct Hire | L27: Salary | M27: 250728026 | N27: John | O27: JD | P27: Doe | Q27: JD | R27: VP | S27: Form Cambridge | BF27: Vish | BO27: REQ-1753712881052 | BP27: test@gmail.com | BQ27: 123 | BW27: 45866
E28: Yes | F28: 45866 | M28: 250728027 | BO28: REQ-1753712890623 | BP28: test@gmail.com | BQ28: 123 | BW28: 45866
E29: Yes | F29: 45866 | G29: Vish | M29: 250728028 | BO29: REQ-1753712892388 | BP29: test@gmail.com | BQ29: 123 | BW29: 45866 | BY29: test
E30: Yes | F30: 45866 | M30: 250728029 | BO30: REQ-1753713540080
E31: Yes | F31: 45866 | G31: Vish | M31: 250728030 | BO31: REQ-1753713541006
E32: Yes | F32: 45866 | G32: Vish | H32: Vishal.srikanth@team-group.com | I32: 45866 | J32: New Hire | K32: Direct Hire | L32: Hourly | M32: 250728031 | N32: John | O32: JD | P32: Doe | Q32: JD | U32: VS | V32: Vishal.srikanth@team-group.com | BF32: Vish | BG32: 45866 | BO32: REQ-1753713613796 | BP32: test@gmail.com | BQ32: 123 | BW32: 45866 | BX32: Approved
E33: Yes | F33: 45866 | G33: Vish | H33: Vishal.srikanth@team-group.com | I33: 45866 | J33: New Hire | K33: Direct Hire | L33: Hourly | M33: 250728032 | N33: John | O33: JD | P33: Doe | Q33: JD | R33: VP | S33: Form Cambridge | T33: 123 | U33: VS | V33: Vishal.srikanth@team-group.com | AP33: Required | AU33: Yes | AV33: usnm | AW33: 123 | BF33: Vish | BG33: 45866 | BO33: REQ-1753714423582 | BP33: test@gmail.com | BQ33: 123 | BW33: 45866 | BX33: Approved | BY33: test
E34: Yes | F34: 45866 | G34: Vish | H34: Vishal.srikanth@team-group.com | I34: 45875 | J34: New Hire | K34: Direct Hire | L34: Salary | M34: 250728033 | N34: John | O34: JD | P34: Doe | Q34: JD | R34: VP | S34: Form Cambridge | T34: 123 | U34: VS | V34: Vishal.srikanth@team-group.com | W34: Required | Z34: Required | AP34: Required | AQ34: Required | AS34: Yes | AT34: usnm | AU34: Yes | AV34: usnm | AW34: 123 | AX34: 123, 123 | BF34: Vish | BG34: 45866 | BO34: REQ-1753714741932
E35: Yes | F35: 45866 | G35: Jane Doe | H35: Vishal.srikanth@team-group.com | I35: 45873 | J35: New Hire | K35: Direct Hire | L35: Salary | M35: 250728034 | N35: John | O35: JD | P35: Doe | Q35: JD | R35: VP | S35: Form Cambridge | T35: 123 | U35: Jane Doe | V35: Vishal.srikanth@team-group.com | W35: Required | X35: Required | Y35: Required | Z35: Required | AA35: Required | AB35: Required | AC35: Required | AD35: Required | AE35: Required | AF35: Required | AG35: Required | AI35: Required | AJ35: Required | AK35: Required | AL35: Required | AM35: Required | AN35: Required | AO35: Required | AP35: Required | AQ35: Required | AR35: Required | AS35: Yes | AT35: usnm | AU35: Yes | AV35: usnm | AW35: 123 | AX35: 123 | AY35: 123 | AZ35: 123, 123, 123, 123 | BB35: 123 | BC35: Yes | BD35: Yes | BE35: none | BF35: Jane Doe | BG35: 45866 | BO35: REQ-1753716743848
E36: Yes | F36: 45866 | G36: Jane Doe | H36: Vishal.srikanth@team-group.com | I36: 45866 | J36: New Hire | K36: Direct Hire | L36: Hourly | M36: 250728035 | N36: John | O36: JD | P36: Doe | Q36: JD | R36: VP | S36: Form Cambridge | T36: 123 | U36: Jane Doe | V36: Vishal.srikanth@team-group.com | W36: Required | Z36: Required | AC36: Required | AE36: Required | AO36: Required | AP36: Required | AQ36: Required | AS36: Yes | AT36: usnm | AU36: Yes | AV36: usnm | AW36: 123 | AX36: 123 | AY36: 123 | BA36: 123 | BF36: Vish | BH36: Required | BI36: Yes | BJ36: john.doe@company.com | BO36: REQ-1753718542202 | BQ36: 123 | BR36: 123 | BS36: 123 | BT36: Yes | BW36: 45866
E37: Yes | F37: 45866 | G37: Jane Doe | H37: Vishal.srikanth@team-group.com | I37: 45866 | J37: New Hire | K37: Direct Hire | L37: Hourly | M37: 250728036 | N37: John | O37: JD | P37: Doe | Q37: JD | R37: VP | S37: Form Cambridge | T37: 123 | U37: Jane Doe | V37: Vishal.srikanth@team-group.com | BF37: Jane Doe | BG37: 45866 | BI37: No | BJ37: john.doe@company.com | BO37: REQ-1753719218294 | BQ37: 123 | BR37: 123 | BS37: 123 | BT37: Yes | BW37: 45866 | BX37: Denied | BY37: test
E38: Yes | F38: 45866 | G38: Jane Doe | H38: Vishal.srikanth@team-group.com | I38: 45874 | J38: New Hire | K38: Direct Hire | L38: Hourly | M38: 250728037 | N38: John | O38: JD | P38: Doe | Q38: JD | R38: VP | S38: Form Cambridge | T38: 123 | U38: Jane Doe | V38: Vishal.srikanth@team-group.com | W38: Required | X38: Required | Y38: Required | Z38: Required | AA38: Required | AB38: Required | AC38: Required | AD38: Required | AE38: Required | AF38: Required | AG38: Required | AI38: Required | AJ38: Required | AK38: Required | AL38: Required | AM38: Required | AN38: Required | AO38: Required | AP38: Required | AQ38: Required | AR38: Required | AS38: Yes | AT38: usnm | AU38: Yes | AV38: usnm | AW38: 123 | AX38: 123, 123, 123, 123 | AY38: 123 | BA38: 123 | BB38: 123 | BC38: Yes | BD38: Yes | BE38: none | BF38: Jane Doe | BG38: 45866 | BH38: Required | BI38: Yes | BJ38: john.doe@company.com | BO38: REQ-1753720221560
E39: Yes | F39: 45866 | G39: Jane Doe | H39: Vishal.srikanth@team-group.com | I39: 45874 | J39: New Hire | K39: Direct Hire | L39: Hourly | M39: 250728038 | N39: John | O39: JD | P39: Doe | Q39: JD | R39: VP | S39: Form Cambridge | T39: 123 | U39: VS | V39: Vishal.srikanth@team-group.com | BF39: Jane Doe | BG39: 45866 | BI39: No | BJ39: john.doe@company.com | BO39: REQ-1753726357468 | BQ39: 123 | BR39: 123 | BS39: 123 | BT39: Yes | BW39: 45866
E40: Yes | F40: 45866 | G40: Jane Doe | H40: Vishal.srikanth@team-group.com | I40: 45866 | J40: New Hire | K40: Direct Hire | L40: Hourly | M40: 250728039 | N40: John | O40: JD | P40: Doe | Q40: JD | R40: VP | S40: Form Cambridge | T40: 123 | U40: Jane Doe | V40: Vishal.srikanth@team-group.com | BF40: Jane Doe | BG40: 45866 | BI40: No | BJ40: john.doe@company.com | BO40: REQ-1753726497095
E41: Yes | F41: 45866 | G41: Jane Doe | H41: Vishal.srikanth@team-group.com | I41: 45866 | J41: New Hire | K41: Direct Hire | L41: Hourly | M41: 250728040 | N41: John | O41: JD | P41: Doe | Q41: JD | R41: VP | S41: Form Cambridge | T41: 123 | U41: Jane Doe | V41: Vishal.srikanth@team-group.com | BF41: Jane Doe | BG41: 45866 | BI41: No | BJ41: john.doe@company.com | BO41: REQ-1753726960455
E42: Yes | F42: 45866 | G42: Jane Doe | H42: Vishal.srikanth@team-group.com | I42: 45874 | J42: New Hire | K42: Direct Hire | L42: Hourly | M42: 250728041 | N42: John | O42: JD | P42: Doe | Q42: JD | R42: VP | S42: Form Cambridge | T42: 123 | U42: Jane Doe | V42: Vishal.srikanth@team-group.com | BF42: Jane Doe | BG42: 45866 | BI42: No | BJ42: john.doe@company.com | BO42: REQ-1753727139982 | BQ42: 123 | BR42: 123 | BS42: 123 | BT42: Yes | BW42: 45866 | BX42: Approved
E43: Yes | F43: 45866 | G43: Jane Doe | H43: Vishal.srikanth@team-group.com | I43: 45866 | J43: New Hire | K43: Direct Hire | L43: Salary | M43: 250728042 | N43: John | O43: JD | P43: Doe | Q43: JD | R43: VP | S43: Form Cambridge | T43: 123 | U43: Jane Doe | V43: Vishal.srikanth@team-group.com | W43: Required | X43: Required | Y43: Required | Z43: Required | AA43: Required | AB43: Required | AC43: Required | AD43: Required | AE43: Required | AF43: Required | AG43: Required | AI43: Required | AJ43: Required | AK43: Required | AL43: Required | AM43: Required | AN43: Required | AO43: Required | AP43: Required | AQ43: Required | AR43: Required | AS43: Yes | AT43: usnm | AU43: Yes | AV43: usnm | AW43: 123 | AX43: 123 | AY43: 123 | AZ43: 123 | BB43: 123 | BC43: Yes | BD43: Yes | BE43: none | BF43: Jane Doe | BG43: 45866 | BH43: Required | BI43: No | BJ43: john.doe@company.com | BO43: REQ-1753729756939 | BQ43: 123 | BR43: 123 | BS43: 123 | BT43: Yes | BW43: 45866 | BX43: Approved | BZ43: Complete | CA43: Complete | CB43: Complete | CC43: Complete | CD43: Complete | CE43: Complete | CF43: Complete | CG43: Complete | CI43: Complete | CJ43: email | CK43: pswrd | CL43: 123 | CM43: pswrd | CN43: Chrome
E44: Yes | F44: 45866 | G44: Jane Doe | H44: Vishal.srikanth@team-group.com | I44: 45875 | J44: New Hire | K44: Direct Hire | L44: Hourly | M44: 250728043 | N44: John | O44: JD | P44: Doe | Q44: JD | R44: VP | S44: Form Cambridge | T44: 123 | U44: Jane Doe | V44: Vishal.srikanth@team-group.com | Z44: Required | AA44: Required | AB44: Required | AC44: Required | AG44: Required | AI44: Required | AJ44: Required | AK44: Required | AL44: Required | AM44: Required | AN44: Required | AO44: Required | AP44: Required | AQ44: Required | AR44: Required | AS44: Yes | AT44: usnm | AU44: Yes | AV44: usnm | AW44: 123 | AX44: 123 | AY44: 123 | BC44: Yes | BD44: Yes | BF44: Jane Doe | BG44: 45866 | BH44: Required | BI44: Yes | BJ44: john.doe@company.com | BO44: REQ-1753730666707 | BQ44: 123 | BR44: 123 | BS44: 123 | BT44: Yes | BW44: 45866 | BX44: Approved
E45: Yes | F45: 45866 | G45: Jane Doe | H45: Vishal.srikanth@team-group.com | I45: 45866 | J45: New Hire | K45: Direct Hire | L45: Hourly | M45: 250728044 | N45: John | O45: JD | P45: Doe | Q45: JD | R45: VP | S45: Form Cambridge | T45: 123 | U45: Jane Doe | V45: Vishal.srikanth@team-group.com | Z45: Required | AP45: Required | AX45: 123 | BF45: Jane Doe | BG45: 45866 | BH45: Required | BI45: Yes | BJ45: john.doe@company.com | BO45: REQ-1753730963528 | BQ45: 123 | BR45: 123 | BS45: 123 | BT45: Yes | BW45: 45866 | BX45: Approved | BZ45: Complete | CA45: Complete | CJ45: email | CK45: pswrd | CL45: 123 | CM45: pswrd
E46: Yes | F46: 45866 | G46: Jane Doe | H46: Vishal.srikanth@team-group.com | I46: 45866 | J46: New Hire | K46: Direct Hire | L46: Hourly | M46: 250728045 | N46: John | O46: JD | P46: Doe | Q46: JD | R46: VP | S46: Form Cambridge | T46: 123 | U46: Jane Doe | V46: Vishal.srikanth@team-group.com | W46: Required | X46: Required | Y46: Required | Z46: Required | AA46: Required | AB46: Required | AC46: Required | AD46: Required | AE46: Required | AF46: Required | AG46: Required | AI46: Required | AJ46: Required | AK46: Required | AL46: Required | AM46: Required | AN46: Required | AO46: Required | AP46: Required | AQ46: Required | AR46: Required | AS46: Yes | AT46: usnm | AU46: Yes | AV46: usnm | AW46: 123 | AX46: 123 | AY46: 123 | AZ46: 123, 123, 123, 123 | BB46: 123 | BC46: Yes | BD46: Yes | BF46: Jane Doe | BG46: 45866 | BH46: Required | BI46: Yes | BJ46: john.doe@company.com | BO46: REQ-1753731968142 | BQ46: 123 | BR46: 123 | BS46: 123 | BT46: Yes | BW46: 45866 | BX46: Completed | BZ46: Complete | CA46: Complete | CB46: Complete | CC46: Complete | CD46: Complete | CE46: Complete | CF46: Complete | CG46: Complete | CI46: Complete | CJ46: email | CK46: pswrd | CL46: 123 | CM46: pswrd | CN46: Chrome | EA46: First Last | ED46: 45866.661
E47: Yes | F47: 45866 | G47: Jane Doe | H47: Vishal.srikanth@team-group.com | I47: 45866 | J47: New Hire | K47: Direct Hire | L47: Hourly | M47: 250728046 | N47: John | O47: JD | P47: Doe | Q47: JD | R47: VP | S47: Form Cambridge | T47: 123 | U47: VS | V47: Vishal.srikanth@team-group.com | Z47: Required | AA47: Required | AB47: Required | AC47: Required | AG47: Required | AI47: Required | AJ47: Required | AK47: Required | AO47: Required | AP47: Required | AQ47: Required | AR47: Required | AS47: Yes | AT47: usnm | AU47: Yes | AV47: usnm | AW47: 123 | AX47: 123 | AY47: 123 | BF47: Jane Doe | BG47: 45866 | BH47: Required | BI47: Yes | BJ47: john.doe@company.com | BO47: REQ-1753733411452 | BQ47: 123 | BR47: 123 | BS47: 123 | BT47: Yes | BW47: 45866 | BX47: Completed | BZ47: Complete | CA47: Complete | CB47: Complete | CC47: Complete | CD47: Complete | CE47: Complete | CF47: Complete | CG47: Complete | CI47: Complete | CJ47: email | CK47: pswrd | CL47: 123 | CM47: pswrd | CN47: Chrome | EA47: First Last | ED47: 45866.683
E48: Yes | F48: 45867 | G48: Daniel Binns | H48: dbinns@robinsonsolutions.com | I48: 45873 | J48: New Hire | K48: Direct Hire | L48: Hourly | M48: 250729047 | N48: John | O48: James | P48: Doe | Q48: James | R48: Cleaner | S48: Bluebird | T48: UC122 | U48: Binns | V48: dbinns@robinsonsolutions.com | BF48: Binns | BG48: 45867 | BI48: No | BJ48: john.doe@company.com | BO48: REQ-1753797394629 | BQ48: 55555 | BR48: ddddd | BS48: dddddddd | BT48: Yes | BW48: 45867 | BX48: Approved
E49: Yes | F49: 45867 | G49: Daniel Binns | H49: dbinns@robinsonsolutions.com | I49: 45867 | J49: New Hire | K49: Direct Hire | L49: Salary | M49: 250729048 | N49: DANIEL | P49: BINNS | R49: Cleaner | S49: Bluebird | T49: UC122 | U49: Binns | V49: dbinns@robinsonsolutions.com | W49: Required | X49: Required | Y49: Required | Z49: Required | AA49: Required | AB49: Required | AC49: Required | AD49: Not Required | AE49: Not Required | AF49: Not Required | AG49: Required | AI49: Required | AJ49: Required | AK49: Required | AL49: Required | AM49: Required | AN49: Required | AO49: Required | AP49: Required | AQ49: Required | AR49: Required | AS49: No | AU49: No | AX49: 555 | AY49: 555 | BC49: Yes | BD49: Yes | BF49: Binns | BG49: 45867 | BH49: Required | BI49: No | BJ49: daniel.binns@company.com | BO49: REQ-1753798014866 | BQ49: 55555 | BR49: ddddd | BS49: dddddddd | BT49: Yes | BW49: 45867
E50: Yes | F50: 45867 | G50: Vish | H50: Vishal.srikanth@team-group.com | I50: 45867 | J50: New Hire | K50: Direct Hire | L50: Hourly | M50: 250729049 | N50: John | O50: JD | P50: Doe | Q50: JD | R50: VP | S50: Form Cambridge | T50: 123 | U50: Jane Doe | V50: Vishal.srikanth@team-group.com | W50: Required | X50: Required | Y50: Required | Z50: Required | AA50: Required | AB50: Required | AC50: Required | AD50: Required | AE50: Required | AF50: Required | AG50: Required | AH50: Required | AI50: Required | AJ50: Required | AK50: Required | AL50: Required | AM50: Required | AN50: Required | AO50: Required | AP50: Required | AQ50: Required | AR50: Required | AS50: Yes | AT50: usnm | AU50: Yes | AV50: usnm | AW50: 123 | AX50: 123 | AY50: 123 | AZ50: 123 | BB50: 123 | BC50: Yes | BD50: Yes | BF50: Vish | BH50: Required | BI50: Yes | BJ50: john.doe@team-group.com | BK50: 45875 | BL50: Required | BO50: REQ-1753804784414 | BQ50: 123 | BR50: 123 | BS50: 123 | BT50: Yes | BW50: 45867.501 | BX50: Completed | BZ50: Complete | CA50: Complete | CB50: Complete | CC50: Complete | CD50: Complete | CE50: Complete | CF50: Complete | CG50: Complete | CI50: Complete | CJ50: email | CK50: pswrd | CL50: 123 | CM50: pswrd | CN50: Chrome | EA50: First Last | ED50: 45867.505
E51: Yes | F51: 45867 | G51: Jane Doe | H51: Vishal.srikanth@team-group.com | I51: 45867 | J51: New Hire | K51: Direct Hire | L51: Hourly | M51: 250729050 | N51: John | O51: JD | P51: Doe | Q51: JD | R51: VP | U51: VS | V51: Vishal.srikanth@team-group.com | W51: Required | X51: Required | Y51: Required | Z51: Required | AA51: Required | AB51: Required | AC51: Required | AD51: Required | AE51: Required | AF51: Required | AG51: Required | AH51: Required | AI51: Required | AJ51: Required | AK51: Required | AL51: Required | AM51: Required | AN51: Required | AO51: Required | AP51: Required | AQ51: Required | AR51: Required | AS51: Yes | AT51: usnm | AU51: Yes | AV51: usnm | AW51: 123 | AX51: 123 | AY51: 123 | AZ51: 123 | BA51: 123 | BB51: 123 | BF51: Vish | BH51: Required | BI51: Yes | BJ51: john.doe@team-group.com | BK51: 45875 | BL51: Required | BO51: REQ-1753806417438 | BQ51: 123 | BR51: 123 | BS51: 123 | BT51: Yes | BW51: 45867.524 | BX51: Completed | BZ51: Complete | CA51: Complete | CB51: Complete | CC51: Complete | CD51: Complete | CE51: Complete | CF51: Complete | CG51: Complete | CI51: Complete | CJ51: email | CK51: pswrd | CL51: 123 | CM51: pswrd | CN51: Chrome | CP51: 45867.526 | EA51: First Last | ED51: 45867.527
A52: 45867.534 | E52: Yes | F52: 45867 | G52: Vish | H52: Vishal.srikanth@team-group.com | I52: 45875 | J52: New Hire | K52: Direct Hire | L52: Salary | M52: 250729051 | N52: John | O52: JD | P52: Doe | Q52: JD | R52: VP | S52: Form Cambridge | T52: 123 | U52: VS | V52: Vishal.srikanth@team-group.com | Y52: Required | Z52: Required | AA52: Required | AB52: Required | AG52: Required | AH52: Required | AI52: Required | AJ52: Required | AK52: Required | AM52: Required | AN52: Required | AO52: Required | AP52: Required | AQ52: Required | AX52: 123 | AY52: 123 | BF52: Jane Doe | BH52: Required | BI52: Yes | BJ52: john.doe@team-group.com | BK52: 45875 | BL52: Required | BO52: REQ-1753807726057 | BQ52: 123 | BR52: 123 | BS52: 123 | BT52: Yes | BW52: 45867.537 | BX52: Denied | BZ52: Complete | CA52: Complete | CB52: Complete | CC52: Complete | CD52: Complete | CE52: Complete | CF52: Complete | CG52: Complete | CI52: Complete | CJ52: email | CK52: pswrd | CL52: 123 | CM52: pswrd | CN52: Chrome | CO52: abc123 | CP52: 45867.536 | EA52: First Last | ED52: 45867.538
A53: 45867.544 | E53: Yes | F53: 45867 | G53: Jane Doe | H53: Vishal.srikanth@team-group.com | I53: 45867 | J53: New Hire | K53: Direct Hire | L53: Hourly | M53: 250729052 | N53: John | O53: JD | P53: Doe | Q53: JD | R53: VP | S53: Form Cambridge | T53: 123 | U53: VS | V53: Vishal.srikanth@team-group.com | BF53: Vish | BI53: No | BK53: 45867 | BO53: REQ-1753808626079
A54: 45867.549 | E54: Yes | F54: 45867 | G54: Jane Doe | H54: Vishal.srikanth@team-group.com | I54: 45867 | J54: New Hire | K54: Direct Hire | L54: Hourly | M54: 250729053 | N54: John | O54: JD | P54: Doe | Q54: JD | R54: VP | S54: Form Cambridge | T54: 123 | U54: VS | V54: Vishal.srikanth@team-group.com | BF54: Jane Doe | BI54: No | BK54: 45867 | BO54: REQ-1753809015718
A55: 45867.555 | C55: Sent Back to Requester | E55: Yes | F55: 45867 | G55: Jane Doe | H55: Vishal.srikanth@team-group.com | I55: 45867 | J55: New Hire | K55: Direct Hire | L55: Hourly | M55: 250729054 | N55: John | O55: JD | P55: Doe | Q55: JD | R55: VP | S55: Form Cambridge | T55: 123 | U55: VS | V55: Vishal.srikanth@team-group.com | BF55: Jane Doe | BI55: No | BK55: 45875 | BO55: REQ-1753809589591 | BQ55: 123 | BR55: 123 | BS55: 123 | BT55: Yes | BW55: 45867.556 | BX55: Pending | BY55: test | CP55: 45867.558
A56: 45867.585 | C56: Pending HR Setup | E56: Yes | F56: 45867 | G56: Jane Doe | H56: Vishal.srikanth@team-group.com | I56: 45867 | J56: New Hire | K56: Direct Hire | L56: Hourly | M56: 250729055 | N56: John | O56: JD | P56: Doe | Q56: JD | R56: VP | S56: Edmonton | T56: TEST4 | U56: Jane Doe | V56: Vishal.srikanth@team-group.com | Z56: Required | AA56: Required | AB56: Required | AC56: Required | AD56: Required | AE56: Required | AF56: Required | AG56: Required | AH56: Required | AI56: Required | AJ56: Required | AK56: Required | AL56: Required | AM56: Required | AN56: Required | AO56: Required | AP56: Required | AQ56: Required | AR56: Required | AS56: Yes | AT56: usnm | AU56: Yes | AV56: usnm | AW56: 123 | AX56: Bluebird, BMW, Edmonton | AY56: Bluebird, BMW, Edmonton | AZ56: TEST1, TEST2 | BA56: TEST2, TEST3 | BB56: TEST2, TEST1 | BF56: Jane Doe | BH56: Required | BI56: Yes | BK56: 45874 | BL56: Required | BO56: REQ-1753812102690
A57: 45867.588 | C57: Pending HR Setup | E57: Yes | F57: 45867 | G57: Jane Doe | H57: Vishal.srikanth@team-group.com | I57: 45874 | J57: New Hire | K57: Direct Hire | L57: Hourly | M57: 250729056 | N57: John | O57: JD | P57: Doe | Q57: JD | R57: VP | S57: BMW | T57: TEST2 | U57: VS | V57: Vishal.srikanth@team-group.com | BF57: Jane Doe | BI57: No | BK57: 45867 | BO57: REQ-1753812436274
A58: 45867.593 | C58: Pending HR Setup | E58: Yes | F58: 45867 | G58: Jane Doe | H58: Vishal.srikanth@team-group.com | I58: 45874 | J58: New Hire | K58: Direct Hire | L58: Salary | M58: 250729057 | N58: John | O58: JD | P58: Doe | Q58: JD | R58: VP | S58: BMW | T58: TEST2 | U58: VS | V58: Vishal.srikanth@team-group.com | AD58: Required | AQ58: Required | AS58: Yes | AT58: usnm | AZ58: TEST1, TEST2, TEST3 | BF58: Vish | BI58: No | BJ58: john.doe@team-group.com | BK58: 45874 | BO58: REQ-1753812843208
A59: 45867.6 | C59: Pending HR Setup | E59: Yes | F59: 45867 | G59: Jane Doe | H59: Vishal.srikanth@team-group.com | I59: 45874 | J59: New Hire | K59: Direct Hire | L59: Hourly | M59: 250729058 | N59: John | O59: JD | P59: Doe | Q59: JD | R59: VP | S59: Bluebird | T59: TEST1 | U59: VS | V59: Vishal.srikanth@team-group.com | BF59: Vish | BI59: No | BO59: REQ-1753813433425
A60: 45867.609 | C60: Pending IT Setup | E60: Yes | F60: 45867 | G60: Vish | H60: Vishal.srikanth@team-group.com | I60: 45874 | J60: New Hire | K60: Direct Hire | L60: Hourly | M60: 250729059 | N60: John | O60: JD | P60: Doe | Q60: JD | R60: VP | S60: Bluebird | T60: TEST1 | U60: VS | V60: Vishal.srikanth@team-group.com | BF60: Vish | BI60: No | BK60: 45867 | BO60: REQ-1753814199489 | BQ60: 123 | BR60: JD250805BB | BS60: 123 | BT60: Yes | BW60: 45867.611
A61: 45867.623 | C61: Completed | E61: Yes | F61: 45867 | G61: Vish | H61: Vishal.srikanth@team-group.com | J61: New Hire | K61: Direct Hire | L61: Hourly | M61: 250729060 | N61: John | O61: JD | P61: Doe | Q61: JD | R61: VP | S61: Decostar | T61: TEST3 | U61: VS | V61: Vishal.srikanth@team-group.com | AN61: Required | AP61: Required | AQ61: Required | AS61: Yes | AT61: usnm | AU61: Yes | AV61: usnm | AW61: 123 | BF61: Vish | BI61: Yes | BK61: 45873 | BO61: REQ-1753815392768 | BQ61: 123 | BR61: JD691231STAR | BS61: 123 | BT61: Yes | BW61: 45867.624 | BX61: Completed | CL61: 123 | CM61: pswrd | CN61: Chrome | CO61: abc123 | CP61: 45867.625 | EA61: First Last | ED61: 45867.625
A62: 45867.63 | C62: Pending HR Setup | E62: Yes | F62: 45867 | G62: Vish | H62: Vishal.srikanth@team-group.com | J62: New Hire | K62: Direct Hire | L62: Hourly | M62: 250729061 | N62: John | O62: JD | P62: Doe | Q62: JD | R62: VP | S62: Etobicote | T62: TEST5 | U62: Jane Doe | V62: Vishal.srikanth@team-group.com | BF62: Vish | BI62: No | BK62: 45874 | BO62: REQ-1753816058655
C63: Completed | E63: Yes | F63: 45867 | G63: Vish | H63: Vishal.srikanth@team-group.com | I63: 45875 | J63: New Hire | K63: Direct Hire | L63: Hourly | M63: 250729062 | N63: John | O63: z | P63: Doe | Q63: JZ | R63: VP | S63: Etobicote | T63: TEST5 | U63: Jane Doe | V63: Vishal.srikanth@team-group.com | BF63: Vish | BI63: No | BK63: 45867 | BO63: REQ-1753816586422 | BQ63: 123 | BR63: JD250806ECP | BS63: 123 | BT63: Yes | BW63: 45867.637 | BX63: Completed | CP63: 45867.639 | EA63: First Last | ED63: 45867.639
A64: 45867.659 | C64: Completed | E64: Yes | F64: 45867 | G64: Vish | H64: Vishal.srikanth@team-group.com | I64: 45876 | J64: New Hire | K64: Direct Hire | L64: Hourly | M64: 250729063 | N64: John | O64: JD | P64: Doe | Q64: JD | R64: VP | S64: Decostar | T64: TEST3 | U64: Jane Doe | V64: Vishal.srikanth@team-group.com | W64: Required | X64: Required | Y64: Required | Z64: Required | AA64: Required | AB64: Required | AC64: Required | AD64: Required | AE64: Required | AF64: Required | AG64: Required | AH64: Required | AI64: Required | AJ64: Required | AK64: Required | AL64: Required | AM64: Required | AN64: Required | AO64: Required | AP64: Required | AQ64: Required | AR64: Required | AS64: Yes | AT64: usnm | AU64: Yes | AV64: usnm | AW64: 123 | AX64: Bluebird, Decostar, Etobicote | AY64: Bluebird, Decostar, Etobicote | AZ64: TEST1, TEST3, TEST5 | BA64: TEST1, TEST3, TEST5 | BB64: TEST1, TEST3, TEST5 | BE64: none | BF64: Vish | BH64: Required | BI64: Yes | BJ64: john.doe@company.com | BK64: 45875 | BL64: Required | BO64: REQ-1753818551130 | BQ64: 123 | BR64: JD250807STAR | BS64: pswrd | BT64: Yes | BU64: usrnm | BV64: pswrd | BW64: 45867.66 | BX64: Completed | BZ64: Complete | CA64: Complete | CB64: Complete | CC64: Complete | CD64: Complete | CE64: Complete | CF64: Complete | CG64: Complete | CI64: Complete | CJ64: email | CK64: pswrd | CL64: 123 | CM64: pswrd | CN64: Chrome | CO64: abc123 | CP64: 45867.662 | EA64: First Last | ED64: 45867.662
A65: 45867.672 | C65: Completed | E65: Yes | F65: 45867 | G65: Vish | H65: Vishal.srikanth@team-group.com | I65: 45875 | J65: New Hire | K65: Direct Hire | L65: Salary | M65: 250729064 | N65: John | O65: JD | P65: Doe | Q65: JD | R65: VP | S65: Etobicote | T65: TEST5 | U65: Jane Doe | V65: Vishal.srikanth@team-group.com | W65: Required | X65: Required | Y65: Required | Z65: Required | AA65: Required | AB65: Required | AC65: Required | AD65: Required | AE65: Required | AF65: Required | AG65: Required | AH65: Required | AI65: Required | AJ65: Required | AK65: Required | AL65: Required | AM65: Required | AN65: Required | AO65: Required | AP65: Required | AQ65: Required | AR65: Required | AS65: Yes | AT65: usnm | AU65: Yes | AV65: usnm | AW65: 123 | AX65: Bluebird | AY65: BMW | AZ65: TEST3 | BA65: TEST4 | BB65: TEST5 | BE65: none | BF65: Vish | BH65: Required | BI65: No | BJ65: john.doe@team-group.com | BK65: 45874 | BL65: Required | BO65: REQ-1753819668750 | BQ65: 123 | BR65: JD250806ECP | BS65: pswrd | BT65: Yes | BU65: usrnm | BV65: pswrd | BW65: 45867.673 | BX65: Completed | BZ65: Complete | CA65: Complete | CB65: Complete | CC65: Complete | CD65: Complete | CE65: Complete | CF65: Complete | CG65: Complete | CI65: Complete | CL65: 123 | CM65: pswrd | CN65: Chrome | CO65: abc123 | CP65: 45867.674 | EA65: First Last | ED65: 45867.675
A66: 45867.682 | C66: Completed | E66: Yes | F66: 45867 | G66: Vish | H66: Vishal.srikanth@team-group.com | I66: 45875 | J66: New Hire | K66: Direct Hire | L66: Salary | M66: 250729065 | N66: John | O66: JD | P66: Doe | Q66: JD | R66: VP | S66: Etobicote | T66: TEST5 | U66: VS | V66: Vishal.srikanth@team-group.com | W66: Required | X66: Required | Y66: Required | Z66: Required | AF66: Required | AN66: Required | AP66: Required | AQ66: Required | AS66: Yes | AT66: usnm | AU66: Yes | AV66: usnm | AW66: 123 | AX66: Bluebird | BB66: TEST2 | BE66: none | BF66: Vish | BH66: Required | BI66: No | BJ66: john.doe@team-group.com | BK66: 45874 | BO66: REQ-1753820546753 | BQ66: 123 | BR66: JD250806ECP | BS66: pswrd | BT66: Yes | BW66: 45867.683 | BX66: Completed | BZ66: Complete | CA66: Complete | CL66: 123 | CM66: pswrd | CN66: Chrome | CO66: abc123 | CP66: 45867.684 | EA66: First Last | EB66: Notes | ED66: 45867.684
A67: 45867.702 | C67: Completed | E67: Yes | F67: 45867 | G67: Vish | H67: Vishal.srikanth@team-group.com | I67: 45875 | J67: New Hire | K67: Direct Hire | L67: Hourly | M67: 250729066 | N67: John | O67: JD | P67: Doe | Q67: JD | R67: VP | S67: Edmonton | T67: TEST4 | U67: Jane Doe | Z67: Required | AA67: Required | AK67: Required | AN67: Required | AO67: Required | AQ67: Required | AS67: Yes | AT67: usnm | AX67: Bluebird, Decostar, Edmonton | AY67: Edmonton | BE67: none | BF67: Vish | BH67: Required | BI67: Yes | BJ67: john.doe@company.com | BK67: 45874 | BO67: REQ-1753822251923 | BQ67: 123 | BR67: JD250806EDM | BS67: pswrd | BT67: Yes | BW67: 45867.704 | BX67: Completed | BZ67: Complete | CA67: Complete | CB67: Complete | CG67: Complete | CI67: Complete | CN67: Chrome | CO67: abc123 | CP67: 45867.709 | EA67: First Last | EB67: Notes | ED67: 45867.71
C68: Completed | E68: Yes | F68: 45868 | G68: Vish | H68: Vishal.srikanth@team-group.com | I68: 45876 | J68: New Hire | K68: Agency | L68: Salary | M68: 250730001 | N68: John | O68: JD | P68: Doe | Q68: JD | R68: VP | S68: Bluebird | T68: TEST1 | U68: Jane Doe | V68: Vishal.srikanth@team-group.com | W68: Required | X68: Required | Y68: Required | Z68: Required | AA68: Required | AB68: Required | AC68: Required | AD68: Required | AE68: Required | AF68: Required | AG68: Required | AH68: Required | AI68: Required | AJ68: Required | AK68: Required | AL68: Required | AM68: Required | AN68: Required | AO68: Required | AP68: Required | AQ68: Required | AR68: Required | AS68: Yes | AT68: usnm | AU68: Yes | AV68: usnm | AW68: 123 | AX68: Bluebird | AY68: Bluebird | AZ68: TEST2, TEST3 | BA68: TEST2, TEST3 | BB68: TEST1 | BE68: none | BF68: Vish | BH68: Required | BI68: No | BJ68: john.doe@team-group.com | BK68: 45874 | BL68: Required | BO68: REQ-1753891707261 | BQ68: 123 | BR68: JD20250807BB | BS68: pswrd | BT68: Yes | BU68: usrnm | BV68: pswrd | BW68: 45868.507 | BX68: Completed | BZ68: Complete | CA68: Complete | CB68: Complete | CC68: Complete | CD68: Complete | CE68: Complete | CF68: Complete | CG68: Complete | CI68: Complete | CL68: 123 | CM68: pswrd | CN68: Chrome | CO68: abc123 | CP68: 45868.511 | CQ68: Complete | CR68: numbr | CS68: make | CT68: model | CU68: ab12c3 | DH68: Complete | DI68: 45868.509 | DJ68: Complete | DK68: 45868.509 | DL68: Complete | DM68: 45868.509 | DN68: Complete | DO68: 45868.51 | EA68: First Last | EB68: Good | ED68: 45868.513
C69: Pending IT Setup | E69: Yes | F69: 45868 | G69: Vish | H69: Vishal.srikanth@team-group.com | I69: 45876 | J69: New Hire | K69: Direct Hire | L69: Salary | M69: 250730002 | N69: John | O69: JD | P69: Doe | Q69: JD | R69: VP | S69: Bluebird | T69: TEST1 | U69: Jane Doe | V69: Vishal.srikanth@team-group.com | W69: Required | X69: Required | Z69: Required | AA69: Required | AC69: Required | AF69: Required | AG69: Required | AL69: Required | AM69: Required | AN69: Required | AQ69: Required | AS69: Yes | AT69: usnm | AX69: Bluebird | BB69: TEST1 | BE69: none | BF69: Vish | BH69: Required | BI69: No | BJ69: john.doe@team-group.com | BK69: 45874 | BO69: REQ-1753893370440 | BQ69: 123 | BR69: JD20250807BB | BS69: pswrd | BT69: Yes | BW69: 45868.526 | CQ69: Complete | CR69: numbr | CS69: make | CT69: model | CU69: ab12c3 | DH69: Complete | DI69: 45868.526 | DJ69: Complete | DK69: 45868.527 | DL69: Complete | DM69: 45868.527
C70: Completed | E70: Yes | F70: 45868 | G70: Vish | H70: Vishal.srikanth@team-group.com | I70: 45875 | J70: New Hire | K70: Direct Hire | L70: Salary | M70: 250730003 | N70: John | O70: JD | P70: Doe | Q70: JD | R70: VP | S70: Edmonton | T70: TEST4 | U70: Jane Doe | V70: Vishal.srikanth@team-group.com | W70: Required | Y70: Required | AC70: Required | AE70: Required | AL70: Required | AN70: Required | AP70: Required | BA70: TEST2 | BE70: none | BF70: Vish | BI70: No | BJ70: john.doe@team-group.com | BK70: 45874 | BO70: REQ-1753894039801 | BQ70: 123 | BR70: JD20250806EDM | BS70: pswrd | BT70: Yes | BW70: 45868.533 | BX70: Completed | CL70: 123 | CM70: pswrd | CP70: 45868.535 | CQ70: Complete | CR70: numbr | CS70: make | CT70: model | CU70: ab12c3 | DJ70: Complete | DK70: 45868.535 | DN70: Complete | DO70: 45868.535 | EA70: First Last | ED70: 45868.536
C71: Completed | E71: Yes | F71: 45868 | G71: Vish | H71: Vishal.srikanth@team-group.com | I71: 45877 | J71: New Hire | K71: Agency | L71: Salary | M71: 250730004 | N71: John | O71: JD | P71: Doe | Q71: JD | R71: VP | S71: Edmonton | T71: TEST4 | U71: Jane Doe | V71: Vishal.srikanth@team-group.com | W71: Required | X71: Required | Y71: Required | Z71: Required | AA71: Required | AB71: Required | AC71: Required | AD71: Required | AE71: Required | AF71: Required | AG71: Required | AH71: Required | AI71: Required | AJ71: Required | AK71: Required | AL71: Required | AM71: Required | AN71: Required | AO71: Required | AP71: Required | AQ71: Required | AR71: Required | AS71: Yes | AT71: usnm | AU71: Yes | AV71: usnm | AW71: 123 | AX71: Bluebird | AY71: BMW | AZ71: TEST3 | BA71: TEST4 | BB71: TEST5 | BE71: none | BF71: Vish | BH71: Required | BI71: No | BJ71: john.doe@team-group.com | BK71: 45874 | BL71: Required | BO71: REQ-1753895117922 | BQ71: 123 | BR71: JD20250808EDM | BS71: pswrd | BT71: Yes | BU71: usrnm | BV71: pswrd | BW71: 45868.546 | BX71: Completed | BZ71: Complete | CA71: Complete | CB71: Complete | CC71: Complete | CD71: Complete | CE71: Complete | CF71: Complete | CG71: Complete | CI71: Complete | CL71: 123 | CM71: pswrd | CN71: Chrome | CO71: abc123 | CP71: 45868.547 | CQ71: Complete | CR71: numbr | CS71: make | CT71: model | CU71: ab12c3 | DH71: Complete | DI71: 45868.547 | DJ71: Complete | DK71: 45868.547 | DL71: Complete | DM71: 45868.547 | DN71: Complete | DO71: 45868.547 | DW71: Complete | DX71: 45868.547 | EA71: First Last | EB71: notes | ED71: 45868.549
C72: Completed | E72: Yes | F72: 45868 | G72: Vish | H72: Vishal.srikanth@team-group.com | I72: 45874 | J72: New Hire | K72: Direct Hire | L72: Salary | M72: 250730005 | N72: John | O72: JD | P72: Doe | Q72: JD | R72: VP | S72: Bluebird | T72: TEST1 | U72: Jane Doe | V72: Vishal.srikanth@team-group.com | W72: Required | X72: Required | Y72: Required | Z72: Required | AA72: Required | AB72: Required | AC72: Required | AD72: Required | AE72: Required | AF72: Required | AG72: Required | AH72: Required | AI72: Required | AJ72: Required | AK72: Required | AL72: Required | AM72: Required | AN72: Required | AO72: Required | AP72: Required | AQ72: Required | AR72: Required | AS72: Yes | AT72: usnm | AU72: Yes | AV72: usnm | AW72: 123 | AX72: Bluebird | AY72: Bluebird | AZ72: TEST1 | BA72: TEST1 | BB72: TEST1 | BE72: none | BF72: Vish | BH72: Required | BI72: No | BJ72: john.doe@team-group.com | BK72: 45874 | BL72: Required | BO72: REQ-1753903915218 | BQ72: 123 | BR72: JD20250805BB | BS72: pswrd | BT72: Yes | BU72: usrnm | BV72: pswrd | BW72: 45868.648 | BX72: Completed | BZ72: Complete | CA72: Complete | CB72: Complete | CC72: Complete | CD72: Complete | CE72: Complete | CF72: Complete | CG72: Complete | CI72: Complete | CL72: 123 | CM72: pswrd | CN72: Chrome | CO72: abc123 | CP72: 45868.651 | CQ72: Complete | CR72: numbr | CS72: make | CT72: model | CU72: ab12c3 | DH72: Complete | DI72: 45868.649 | DJ72: Complete | DK72: 45868.65 | DL72: Complete | DM72: 45868.65 | DN72: Complete | DO72: 45868.65 | DW72: Complete | DX72: 45868.65 | EA72: First Last | EB72: nice | ED72: 45868.652
C73: Pending HR Setup | E73: Yes | F73: 45869 | G73: Daniel Binns | H73: dbinns@robinsonsolutions.com | I73: 45869 | J73: New Hire | K73: Direct Hire | L73: Salary | M73: 250731001 | N73: DANIEL | P73: BINNS | Q73: Dan | R73: Cleaner | S73: Bluebird | T73: TEST1 | U73: Binns | V73: dbinns@robinsonsolutions.com | W73: Required | X73: Required | Z73: Required | AN73: Required | AX73: Bluebird, BMW | BF73: Binns | BI73: No | BJ73: daniel.binns@team-group.com | BK73: 45873 | BO73: REQ-1753981527725
C74: Pending HR Setup | E74: Yes | F74: 45874 | G74: Vish | H74: Vishal.srikanth@team-group.com | M74: 250805001 | BI74: No | BK74: 45896 | BO74: REQ-1754409331657
C75: Completed | E75: Yes | F75: 45874 | G75: Jane Doe | H75: Vishal.srikanth@team-group.com | I75: 45881 | J75: New Hire | K75: Direct Hire | L75: Salary | M75: 250805002 | N75: John | O75: JD | P75: Doe | Q75: JD | R75: VP | S75: Bluebird | T75: TEST1 | U75: VS | V75: Vishal.srikanth@team-group.com | W75: Required | X75: Required | Y75: Required | Z75: Required | AA75: Required | AB75: Required | AC75: Required | AD75: Required | AE75: Required | AF75: Required | AG75: Required | AH75: Required | AI75: Required | AJ75: Required | AK75: Required | AL75: Required | AM75: Required | AN75: Required | AO75: Required | AP75: Required | AQ75: Required | AR75: Required | AS75: Yes | AT75: usnm | AU75: Yes | AV75: usnm | AW75: 123 | AX75: BMW | AY75: Bluebird, BMW, Edmonton | AZ75: TEST2 | BA75: TEST2 | BB75: TEST2 | BE75: none | BF75: Jane Doe | BH75: Required | BI75: No | BJ75: john.doe@team-group.com | BK75: 45880 | BL75: Required | BO75: REQ-1754410261724 | BQ75: 123 | BR75: JD20250812BB | BS75: pswrd | BT75: Yes | BU75: usrnm | BV75: pswrd | BW75: 45874.509 | BX75: Completed | BZ75: Complete | CA75: Complete | CB75: Complete | CC75: Complete | CD75: Complete | CE75: Complete | CF75: Complete | CG75: Complete | CI75: Complete | CL75: 123 | CM75: pswrd | CN75: Chrome | CO75: abc123 | CP75: 45874.512 | CQ75: Complete | CR75: numbr | CS75: make | CT75: model | CU75: ab12c3 | DH75: Complete | DI75: 45874.511 | DJ75: Complete | DK75: 45874.511 | DL75: Complete | DM75: 45874.511 | DN75: Complete | DO75: 45874.511 | DW75: Complete | DX75: 45874.511 | EA75: First Last | EB75: i felt like it | EC75: i felt like it | ED75: 45874.514
C76: Denied at Final Review | E76: Yes | G76: Vish | H76: Vishal.srikanth@team-group.com | I76: 45881 | L76: Hourly | M76: 250805003 | N76: John | P76: Doe | S76: BMW | T76: TEST2 | W76: Yes | X76: Yes | Y76: No | Z76: Yes | AA76: No | AB76: Yes | AC76: No | AD76: Yes | AE76: Yes | AF76: Yes | AG76: No | AH76: No | AI76: No | AJ76: No | AK76: No | AL76: No | AM76: No | AN76: Yes | AO76: No | AP76: No | AQ76: No | AR76: No | AX76: Bluebird | AZ76: TEST1, TEST2 | BA76: TEST3 | BB76: TEST4 | BF76: Vish | BH76: No | BI76: Yes | BJ76: john.doe@company.com | BK76: 45880 | BL76: No | BO76: REQ-1754412471221 | BQ76: 123 | BR76: JD20250812BMW | BS76: pswrd | BT76: Yes | BW76: 45874.534 | BX76: Denied | CP76: 45874.535 | EA76: First Last | EC76: test | ED76: 45874.536
C77: Pending Final HR Approval | E77: Yes | F77: 45874 | G77: Vish | H77: Vishal.srikanth@team-group.com | I77: 45884 | J77: New Hire | K77: Direct Hire | L77: Hourly | M77: 250805004 | N77: John | O77: JD | P77: Doe | Q77: JD | R77: VP | S77: Bluebird | T77: TEST1 | U77: VS | V77: Vishal.srikanth@team-group.com | W77: No | X77: No | Y77: No | Z77: No | AA77: No | AB77: No | AC77: No | AD77: No | AE77: No | AF77: No | AG77: No | AH77: No | AI77: No | AJ77: No | AK77: No | AL77: No | AM77: No | AN77: No | AO77: No | AP77: No | AQ77: No | AR77: Yes | BF77: Vish | BH77: No | BI77: Yes | BK77: 45883 | BL77: No | BO77: REQ-1754415405650 | BQ77: 123 | BR77: JD20250815BB | BS77: pswrd | BT77: Yes | BW77: 45874.568 | CP77: 45874.569 | DS77: Complete | DT77: 45874.569
C78: Pending Final HR Approval | E78: Yes | F78: 45874 | G78: Vish | H78: Vishal.srikanth@team-group.com | I78: 45882 | J78: New Hire | K78: Direct Hire | L78: Salary | M78: 250805005 | N78: John | O78: JD | P78: Doe | S78: Bluebird | T78: TEST1 | U78: Jane Doe | V78: Vishal.srikanth@team-group.com | W78: No | X78: No | Y78: No | Z78: No | AA78: No | AB78: No | AC78: No | AD78: No | AE78: No | AF78: No | AG78: No | AH78: No | AI78: No | AJ78: No | AK78: No | AL78: No | AM78: No | AN78: Yes | AO78: No | AP78: No | AQ78: Yes | AR78: Yes | AS78: Yes | AT78: usnm | BF78: Vish | BH78: No | BI78: No | BJ78: john.doe@team-group.com | BK78: 45880 | BL78: No | BO78: REQ-1754418821693 | BQ78: 123 | BR78: JD20250813BB | BS78: pswrd | BT78: Yes | BW78: 45874.607 | CP78: 45874.61 | DS78: Complete | DT78: 45874.61
C79: Completed | E79: Yes | F79: 45874 | G79: Vish | H79: Vishal.srikanth@team-group.com | I79: 45889 | J79: New Hire | K79: Direct Hire | L79: Hourly | M79: 250805006 | N79: John | O79: JD | P79: Doe | Q79: JD | R79: VP | S79: Decostar | T79: TEST3 | U79: Jane Doe | V79: Vishal.srikanth@team-group.com | W79: No | X79: No | Y79: No | Z79: No | AA79: No | AB79: No | AC79: No | AD79: No | AE79: No | AF79: No | AG79: No | AH79: No | AI79: No | AJ79: No | AK79: No | AL79: No | AM79: Yes | AN79: Yes | AO79: No | AP79: Yes | AQ79: No | AR79: Yes | AU79: Yes | AV79: usnm | AW79: 123 | BF79: Vish | BH79: No | BI79: Yes | BJ79: john.doe@company.com | BK79: 45880 | BL79: No | BO79: REQ-1754420317324 | BQ79: 123 | BR79: JD20250820STAR | BS79: pswrd | BT79: Yes | BW79: 45874.625 | BX79: Completed | CJ79: email | CK79: pswrd | CL79: 123 | CM79: pswrd | CP79: 45874.625 | DH79: Complete | DI79: 45874.626 | DS79: Complete | DT79: 45874.626 | EA79: System - Auto-approved (Hourly) | ED79: 45874.626
C80: Completed | E80: Yes | F80: 45874 | G80: Vish | H80: Vishal.srikanth@team-group.com | I80: 45883 | J80: New Hire | K80: Direct Hire | L80: Hourly | M80: 250805007 | N80: John | O80: JD | P80: Doe | R80: VP | S80: Decostar | T80: TEST3 | U80: Jane Doe | V80: Vishal.srikanth@team-group.com | W80: No | X80: No | Y80: No | Z80: No | AA80: No | AB80: No | AC80: No | AD80: No | AE80: No | AF80: No | AG80: No | AH80: No | AI80: No | AJ80: No | AK80: No | AL80: No | AM80: No | AN80: No | AO80: No | AP80: No | AQ80: No | AR80: No | BF80: Vish | BH80: No | BI80: No | BK80: 45880 | BL80: No | BO80: REQ-1754422595110 | BQ80: 123 | BR80: JD20250814STAR | BS80: pswrd | BT80: Yes | BW80: 45874.652 | BX80: Completed | CP80: 45874.652 | EA80: System - Auto-approved (Hourly) | ED80: 45874.652
C81: Completed | E81: Yes | F81: 45875 | G81: Vish | H81: Vishal.srikanth@team-group.com | I81: 45904 | J81: New Hire | K81: Direct Hire | L81: Hourly | M81: 250806001 | N81: John | P81: Doe | R81: VP | S81: Chrysler Windsor Paintshop | T81: TW049 | U81: Jane Doe | V81: Vishal.srikanth@team-group.com | W81: No | X81: No | Y81: No | Z81: No | AA81: No | AB81: No | AC81: No | AD81: No | AE81: No | AF81: No | AG81: No | AH81: No | AI81: No | AJ81: No | AK81: No | AL81: No | AM81: Yes | AN81: No | AO81: No | AP81: No | AQ81: No | AR81: No | BF81: Vish | BH81: No | BI81: Yes | BK81: 45895 | BL81: No | BO81: REQ-1754490210421 | BQ81: 123 | BR81: JD20250904CWP | BS81: pswrd | BT81: Yes | BW81: 45875.434 | BX81: Completed | CP81: 45875.434 | DH81: Complete | DI81: 45875.434 | EA81: System - Auto-approved (Hourly) | ED81: 45875.434
A82: 45875.457 | C82: Completed | E82: Yes | F82: 45875 | G82: Vish | H82: Vishal.srikanth@team-group.com | I82: 45894 | J82: New Hire | K82: Direct Hire | L82: Hourly | M82: 250806002 | N82: John | O82: JD | P82: Doe | R82: VP | S82: Cost Variance - RSI | T82: 171 | U82: VS | V82: Vishal.srikanth@team-group.com | W82: No | X82: No | Y82: No | Z82: No | AA82: No | AB82: No | AC82: No | AD82: No | AE82: No | AF82: No | AG82: No | AH82: No | AI82: No | AJ82: No | AK82: No | AL82: No | AM82: No | AN82: No | AO82: No | AP82: No | AQ82: No | AR82: No | BF82: Vish | BH82: No | BI82: No | BK82: 45891 | BL82: No | BO82: REQ-1754492263330 | BQ82: 123 | BR82: JD20250825CVR | BS82: pswrd | BT82: Yes | BW82: 45875.458 | BX82: Completed | CP82: 45875.465 | EA82: System - Auto-approved (Hourly) | ED82: 45875.465
A83: 45875.468 | C83: Completed | E83: Yes | F83: 45875 | G83: Vish | H83: Vishal.srikanth@team-group.com | I83: 45896 | J83: New Hire | K83: Direct Hire | L83: Hourly | M83: 250806003 | N83: John | O83: z | P83: Doe | Q83: JZ | R83: VP | S83: Finance | T83: 44 | U83: Jane Doe | V83: Vishal.srikanth@team-group.com | W83: Yes | X83: Yes | Y83: Yes | Z83: Yes | AA83: Yes | AB83: Yes | AC83: Yes | AD83: Yes | AE83: Yes | AF83: Yes | AG83: Yes | AH83: Yes | AI83: Yes | AJ83: Yes | AK83: Yes | AL83: Yes | AM83: Yes | AN83: Yes | AO83: Yes | AP83: Yes | AQ83: Yes | AR83: Yes | AS83: No | AU83: No | AX83: Corporate Groups | AY83: Controls | AZ83: 120 | BA83: 44 | BB83: 147 | BE83: NONE | BF83: Vish | BH83: Yes | BI83: Yes | BJ83: john.doe@company.com | BK83: 45894 | BL83: Yes | BO83: REQ-1754493260126 | BQ83: 123 | BR83: JD20250827F | BS83: pswrd | BT83: Yes | BW83: 45875.469 | BX83: Completed | BZ83: Complete | CA83: Complete | CB83: Complete | CC83: Complete | CD83: Complete | CE83: Complete | CF83: Complete | CG83: Complete | CI83: Complete | CJ83: email | CK83: pswrd | CL83: 123 | CM83: pswrd | CN83: Chrome | CO83: abc123 | CP83: 45875.471 | CQ83: Complete | CR83: numbr | CS83: make | CT83: model | CU83: ab12c3 | DH83: Complete | DI83: 45875.471 | DJ83: Complete | DK83: 45875.471 | DL83: Complete | DM83: 45875.471 | DN83: Complete | DO83: 45875.471 | DS83: Complete | DT83: 45875.471 | DW83: Complete | DX83: 45875.471 | EA83: System - Auto-approved (Hourly) | ED83: 45875.471
A84: 45875.501 | C84: Completed | E84: Yes | F84: 45875 | G84: Vish | H84: Vishal.srikanth@team-group.com | I84: 45889 | J84: New Hire | K84: Direct Hire | L84: Hourly | M84: 250806004 | N84: John | O84: JD | P84: Doe | Q84: JD | R84: VP | S84: GM Oshawa Assembly | T84: 135 | U84: Jane Doe | V84: Vishal.srikanth@team-group.com | W84: No | X84: No | Y84: No | Z84: No | AA84: Yes | AB84: No | AC84: Yes | AD84: No | AE84: No | AF84: No | AG84: No | AH84: No | AI84: No | AJ84: No | AK84: No | AL84: No | AM84: Yes | AN84: Yes | AO84: No | AP84: No | AQ84: Yes | AR84: No | AS84: No | BE84: none | BF84: Vish | BH84: Yes | BI84: Yes | BJ84: john.doe@company.com | BK84: 45888 | BL84: No | BO84: REQ-1754496076458 | BQ84: 123 | BR84: JD20250820GOA | BS84: pswrd | BT84: Yes | BW84: 45875.502 | BX84: Completed | BZ84: Complete | CB84: Complete | CJ84: email | CK84: pswrd | CN84: Chrome | CO84: abc123 | CP84: 45875.503 | DH84: Complete | DI84: 45875.503 | DW84: Complete | DX84: 45875.503 | EA84: First Last | ED84: 45875.504
A85: 45876.505 | C85: Completed | E85: Yes | F85: 45876 | G85: Vish | H85: Vishal.srikanth@team-group.com | I85: 45877 | J85: New Hire | K85: Direct Hire | L85: Hourly | M85: 250807001 | N85: John | O85: JD | P85: Doe | Q85: JD | R85: VP | S85: Decostar Industries | T85: 132 | U85: Jane Doe | V85: Vishal.srikanth@team-group.com | W85: Yes | X85: Yes | Y85: Yes | Z85: Yes | AA85: Yes | AB85: Yes | AC85: Yes | AD85: Yes | AE85: Yes | AF85: Yes | AG85: Yes | AH85: Yes | AI85: Yes | AJ85: Yes | AK85: Yes | AL85: Yes | AM85: Yes | AN85: Yes | AO85: Yes | AP85: Yes | AQ85: Yes | AR85: Yes | AS85: Yes | AT85: usnm | AU85: Yes | AV85: usnm | AW85: 123 | AX85: Corporate Groups | AY85: Accounts Receivable | AZ85: 194 | BA85: 171 | BB85: 132 | BE85: none | BF85: Vish | BH85: Yes | BI85: Yes | BJ85: john.doe@company.com | BK85: 45877 | BL85: Yes | BO85: REQ-1754582830696 | BQ85: 123 | BR85: JD20250808DI | BS85: pswrd | BT85: Yes | BW85: 45876.511 | BX85: Completed | BZ85: Complete | CA85: Complete | CB85: Complete | CC85: Complete | CD85: Complete | CE85: Complete | CF85: Complete | CG85: Complete | CI85: Complete | CJ85: email | CK85: pswrd | CL85: 123 | CM85: pswrd | CN85: Chrome | CO85: abc123 | CP85: 45876.512 | CQ85: Complete | CR85: numbr | CS85: make | CT85: model | CU85: ab12c3 | DH85: Complete | DI85: 45876.512 | DJ85: Complete | DK85: 45876.512 | DL85: Complete | DM85: 45876.512 | DN85: Complete | DO85: 45876.512 | DS85: Complete | DT85: 45876.512 | DW85: Complete | DX85: 45876.512 | EA85: First Last | ED85: 45876.513
A86: 45876.559 | C86: Completed | E86: Yes | F86: 45876 | G86: Vish | H86: Vishal.srikanth@team-group.com | I86: 45881 | J86: New Hire | K86: Direct Hire | L86: Salary | M86: 250807002 | N86: John | O86: JD | P86: Doe | Q86: JD | R86: VP | S86: BMW Spartanburg Assembly | T86: 120 | U86: Jane Doe | V86: Vishal.srikanth@team-group.com | W86: Yes | X86: Yes | Y86: Yes | Z86: Yes | AA86: Yes | AB86: Yes | AC86: Yes | AD86: Yes | AE86: Yes | AF86: Yes | AG86: Yes | AH86: Yes | AI86: Yes | AJ86: Yes | AK86: Yes | AL86: Yes | AM86: Yes | AN86: Yes | AO86: Yes | AP86: Yes | AQ86: Yes | AR86: Yes | AS86: Yes | AT86: usnm | AU86: Yes | AV86: usnm | AW86: 123 | AX86: Canadian Operations, China Operations | AY86: Cost Variance - RSI | BA86: 172 | BB86: 132 | BE86: none | BF86: Vish | BH86: Yes | BI86: No | BJ86: john.doe@team-group.com | BK86: 45880 | BL86: Yes | BO86: REQ-1754587492781 | BQ86: 123 | BR86: JD20250812BSA | BS86: pswrd | BT86: Yes | BW86: 45876.57 | BX86: Completed | BZ86: Complete | CA86: Complete | CB86: Complete | CC86: Complete | CD86: Complete | CE86: Complete | CF86: Complete | CG86: Complete | CI86: Complete | CJ86: email | CK86: pswrd | CL86: 123 | CM86: pswrd | CN86: Chrome | CO86: abc123 | CP86: 45876.576 | CQ86: Complete | CR86: numbr | CS86: make | CT86: model | CU86: ab12c3 | DH86: Complete | DI86: 45876.577 | DJ86: Complete | DK86: 45876.577 | DL86: Complete | DM86: 45876.579 | DN86: Complete | DO86: 45876.579 | DS86: Complete | DT86: 45876.579 | DW86: Complete | DX86: 45876.579 | EA86: First Last | EB86: this is correct | ED86: 45876.586
C87: Pending HR Setup | E87: Yes | F87: 45877 | G87: Vish | H87: Vishal.srikanth@team-group.com | I87: 45880 | J87: New Hire | K87: Direct Hire | L87: Salary | M87: 250808001 | N87: John | O87: JS | P87: Smith | Q87: JZ | R87: VP | S87: Burns MacDonald | T87: TC014 | U87: Jane Doe | V87: Vishal.srikanth@team-group.com | W87: Yes | X87: Yes | Y87: Yes | Z87: Yes | AA87: Yes | AB87: Yes | AC87: Yes | AD87: Yes | AE87: Yes | AF87: Yes | AG87: Yes | AI87: Yes | AJ87: Yes | AK87: Yes | AL87: Yes | AM87: Yes | AN87: Yes | AO87: Yes | AP87: Yes | AQ87: Yes | AS87: Yes | AT87: usnm | AU87: Yes | AV87: usnm | AW87: 123 | AX87: Atlantic Automotive Benton Harbour | AY87: Atlantic Automotive Benton Harbour | AZ87: TC002 | BA87: TC002 | BB87: TC015 | BE87: none | BF87: Vish | BH87: Yes | BI87: No | BJ87: john.smith@team-group.com | BK87: 45880 | BL87: Yes | BM87: Yes | BO87: REQ-1754663028369 | DP87: Yes
C88: Pending HR Setup | E88: Yes | F88: 45877 | G88: Vish | H88: Vishal.srikanth@team-group.com | I88: 45880 | J88: New Hire | K88: Direct Hire | L88: Salary | M88: 250808002 | N88: John | O88: JS | P88: Smith | Q88: JZ | R88: VP | S88: Caterpillar Wuxi | T88: TC600 | U88: Jane Doe | V88: Vishal.srikanth@team-group.com | W88: Yes | X88: Yes | Y88: Yes | Z88: Yes | AA88: Yes | AB88: Yes | AC88: Yes | AD88: Yes | AE88: Yes | AF88: Yes | AG88: Yes | AI88: Yes | AJ88: Yes | AK88: Yes | AL88: Yes | AM88: Yes | AN88: Yes | AO88: Yes | AP88: Yes | AQ88: Yes | AS88: No | AU88: No | AX88: Adelie Foods | AY88: Atlantic Packaging | AZ88: TC009 | BA88: TC005 | BB88: TC015 | BE88: none | BF88: Vish | BH88: Yes | BI88: No | BJ88: john.smith@team-group.com | BK88: 45880 | BL88: Yes | BM88: Yes | BO88: REQ-1754664501091 | DP88: Yes
C89: Pending HR Setup | E89: Yes | F89: 45877 | G89: Vish | H89: Vishal.srikanth@team-group.com | I89: 45891 | J89: New Hire | K89: Direct Hire | L89: Salary | M89: 250808003 | N89: John | O89: JS | P89: Smith | Q89: JZ | R89: VP | S89: Caterpillar Wuxi | T89: TC600 | U89: Jane Doe | V89: Vishal.srikanth@team-group.com | W89: Yes | X89: Yes | Y89: No | Z89: No | AA89: No | AB89: No | AC89: Yes | AD89: No | AE89: No | AF89: No | AG89: No | AI89: No | AJ89: No | AK89: No | AL89: No | AM89: No | AN89: Yes | AO89: Yes | AP89: No | AQ89: Yes | AS89: No | AY89: Adelie Foods | BF89: Vish | BH89: No | BI89: No | BJ89: john.smith@team-group.com | BK89: 45889 | BL89: Yes | BM89: No | BO89: REQ-1754666225792 | DP89: No
C90: Pending HR Setup | E90: Yes | F90: 45877 | G90: Vish | H90: Vishal.srikanth@team-group.com | I90: 45890 | J90: New Hire | K90: Direct Hire | L90: Salary | M90: 250808004 | N90: John | O90: JD | P90: Doe | Q90: JD | R90: VP | S90: Burns MacDonald | T90: TC014 | U90: Jane Doe | V90: Vishal.srikanth@team-group.com | W90: Yes | X90: Yes | Y90: No | Z90: No | AA90: No | AB90: No | AC90: Yes | AD90: No | AE90: No | AF90: No | AG90: No | AI90: No | AJ90: No | AK90: No | AL90: No | AM90: No | AN90: Yes | AO90: No | AP90: No | AQ90: Yes | AS90: Yes | AT90: usnm | BF90: Vish | BH90: No | BI90: No | BJ90: john.doe@team-group.com | BK90: 45888 | BL90: Yes | BM90: No | BO90: REQ-1754666726275 | DP90: No
C91: Pending HR Setup | E91: Yes | F91: 45877 | G91: Vish | H91: Vishal.srikanth@team-group.com | I91: 45896 | J91: New Hire | K91: Agency | L91: Salary | M91: 250808005 | N91: John | O91: JS | P91: Smith | Q91: JZ | R91: VP | S91: International Springfield | T91: TW169 | U91: Jane Doe | V91: Vishal.srikanth@team-group.com | W91: Yes | X91: Yes | Y91: No | Z91: No | AA91: No | AB91: No | AC91: Yes | AD91: No | AE91: No | AF91: No | AG91: No | AI91: No | AJ91: No | AK91: No | AL91: No | AM91: No | AN91: Yes | AO91: No | AP91: Yes | AQ91: No | AU91: No | BF91: Vish | BH91: No | BI91: No | BJ91: john.smith@team-group.com | BK91: 45895 | BL91: No | BM91: No | BO91: REQ-1754667089964 | DP91: No
C92: Pending HR Setup | E92: Yes | F92: 45877 | G92: Vish | H92: Vishal.srikanth@team-group.com | I92: 45897 | J92: New Hire | K92: Direct Hire | L92: Salary | M92: 250808006 | N92: John | O92: JD | P92: Doe | Q92: JD | R92: VP | S92: Caterpillar Wuxi | T92: TC600 | U92: Jane Doe | V92: Vishal.srikanth@team-group.com | W92: Yes | X92: Yes | Y92: No | Z92: No | AA92: No | AB92: No | AC92: Yes | AD92: No | AE92: No | AF92: No | AG92: No | AI92: No | AJ92: No | AK92: No | AL92: No | AM92: No | AN92: Yes | AO92: No | AP92: Yes | AQ92: No | AU92: No | BF92: Vish | BH92: No | BI92: No | BJ92: john.doe@team-group.com | BK92: 45896 | BL92: Yes | BM92: Yes | BO92: REQ-1754667253798 | DP92: Yes
C93: Completed | E93: Yes | F93: 45877 | G93: Vish | H93: Vishal.srikanth@team-group.com | I93: 45896 | J93: New Hire | K93: Direct Hire | L93: Salary | M93: 250808007 | N93: John | O93: JD | P93: Doe | Q93: JD | R93: VP | S93: Burns MacDonald | T93: TC014 | U93: Jane Doe | V93: Vishal.srikanth@team-group.com | W93: Yes | X93: Yes | Y93: No | Z93: No | AA93: No | AB93: No | AC93: Yes | AD93: No | AE93: No | AF93: No | AG93: No | AI93: No | AJ93: No | AK93: No | AL93: No | AM93: No | AN93: Yes | AO93: No | AP93: Yes | AQ93: No | AU93: No | BF93: Vish | BH93: No | BI93: No | BJ93: john.doe@team-group.com | BK93: 45895 | BL93: Yes | BM93: Yes | BO93: REQ-1754667551704 | BQ93: 123 | BR93: JD20250827BM | BS93: pswrd | BT93: Yes | BU93: usrnm | BV93: pswrd | BW93: 45877.487 | BX93: Completed | CH93: Complete | CJ93: email | CK93: pswrd | CL93: 123 | CM93: pswrd | CP93: 45877.488 | DL93: Complete | DM93: 45877.488 | DP93: Yes | DQ93: Complete | DR93: 45877.488 | DU93: Complete | DV93: 45877.488 | DW93: Complete | DX93: 45877.488 | EA93: First Last | ED93: 45877.49
C94: Pending IT Setup | E94: Yes | F94: 45877 | G94: Vish | H94: Vishal.srikanth@team-group.com | I94: 45877 | J94: New Hire | K94: Direct Hire | L94: Salary | M94: 250808008 | N94: John | O94: JD | P94: Doe | Q94: JD | R94: VP | S94: ArcelorMittal | T94: TC001 | U94: Jane Doe | V94: Vishal.srikanth@team-group.com | W94: No | X94: No | Y94: No | Z94: No | AA94: No | AB94: No | AC94: No | AD94: No | AE94: No | AF94: No | AG94: No | AI94: No | AJ94: No | AK94: No | AL94: No | AM94: Yes | AN94: Yes | AO94: No | AP94: No | AQ94: No | BF94: Vish | BH94: No | BI94: No | BJ94: john.doe@team-group.com | BK94: 45877 | BL94: No | BM94: No | BN94: Amazon, Staples, HomeDepot (physical card) | BO94: REQ-1754669859300 | BR94: JD20250808A | BS94: pswrd | BT94: Yes | BW94: 45877.513 | CJ94: email | CK94: pswrd | CP94: 45877.514 | DP94: No
C95: Pending IT Setup | E95: Yes | F95: 45877 | G95: Vish | H95: Vishal.srikanth@team-group.com | I95: 45898 | J95: New Hire | K95: Direct Hire | L95: Salary | M95: 250808009 | N95: John | O95: JS | P95: Smith | Q95: JZ | R95: VP | S95: Chrysler Brampton Paintshop | T95: TF176 | U95: Jane Doe | W95: No | X95: No | Y95: No | Z95: No | AA95: No | AB95: No | AC95: No | AD95: No | AE95: No | AF95: No | AG95: No | AI95: No | AJ95: No | AK95: No | AL95: No | AM95: Yes | AN95: Yes | AO95: No | AP95: No | AQ95: No | BF95: Vish | BH95: No | BI95: No | BJ95: john.smith@team-group.com | BK95: 45895 | BL95: No | BM95: No | BN95: HomeDepot (physical card), Amazon | BO95: REQ-1754669900527 | BR95: JS20250829CBP | BS95: pswrd | BT95: Yes | BW95: 45877.513 | CJ95: email | CK95: pswrd | CP95: 45877.514 | DP95: No
C96: Completed | E96: Yes | F96: 45877 | G96: Vish | H96: Vishal.srikanth@team-group.com | I96: 45897 | J96: New Hire | K96: Direct Hire | L96: Salary | M96: 250808010 | N96: John | O96: JD | P96: Doe | Q96: JD | R96: VP | S96: Chrysler Brampton GSO | T96: TC800 | W96: Yes | X96: No | Y96: No | Z96: No | AA96: No | AB96: No | AC96: No | AD96: No | AE96: No | AF96: No | AG96: No | AI96: No | AJ96: No | AK96: No | AL96: No | AM96: Yes | AN96: Yes | AO96: No | AP96: No | AQ96: No | BF96: Vish | BH96: No | BI96: No | BJ96: john.doe@team-group.com | BK96: 45889 | BL96: No | BM96: No | BN96: Staples, HomeDepot (physical card), Amazon | BO96: REQ-1754671332597 | BR96: JD20250828CBG | BS96: pswrd | BT96: Yes | BW96: 45877.53 | BX96: Completed | CH96: Complete | CJ96: email | CK96: pswrd | CP96: 45877.539 | CW96: 500 | CX96: CAD | CY96: Day | CZ96: usrnm | DA96: pswrd | DB96: abc123 | DC96: 1234 | DD96: abc123 | DE96: 1234 | DF96: 12345678910 | DG96: 1234 | DH96: Complete | DP96: No | EA96: First Last | ED96: 45877.547
C97: Completed | E97: Yes | F97: 45877 | G97: Vish | H97: Vishal.srikanth@team-group.com | I97: 45896 | J97: New Hire | K97: Direct Hire | L97: Salary | M97: 250808011 | S97: Toyota Burnaston | T97: UP168 | U97: Jane Doe | V97: Vishal.srikanth@team-group.com | W97: Yes | X97: No | Y97: No | Z97: No | AA97: No | AB97: No | AC97: No | AD97: No | AE97: No | AF97: No | AG97: No | AI97: No | AJ97: No | AK97: No | AL97: No | AM97: Yes | AN97: Yes | AO97: No | AP97: No | AQ97: No | BF97: Vish | BH97: No | BI97: No | BJ97: john.doe@company.com | BK97: 45888 | BL97: Yes | BM97: No | BN97: Amazon, Staples, HomeDepot (physical card) | BO97: REQ-1754673008873 | BQ97: 123 | BR97: XX20250827TB | BS97: pswrd | BT97: Yes | BU97: usrnm | BV97: pswrd | BW97: 45877.55 | BX97: Completed | CH97: Complete | CJ97: email | CK97: pswrd | CP97: 45877.558 | CW97: 500 | CX97: CAD | CY97: Week | CZ97: usrnm | DA97: pswrd | DB97: abc123 | DC97: 1234 | DD97: abc123 | DE97: 1234 | DF97: 12345678910 | DG97: 1234 | DH97: Complete | DP97: No | DU97: Complete | DV97: 45877.551 | EA97: First Last | ED97: 45877.559
C98: Completed | E98: Yes | F98: 45880 | G98: Vish | H98: Vishal.srikanth@team-group.com | I98: 45888 | J98: New Hire | K98: Direct Hire | L98: Hourly | M98: 250811001 | N98: John | O98: JD | P98: Doe | Q98: JD | R98: VP | S98: GM Oshawa PPS | T98: TW010 | U98: Jane Doe | V98: Vishal.srikanth@team-group.com | W98: No | X98: No | Y98: No | Z98: No | AA98: No | AB98: No | AC98: No | AD98: No | AE98: No | AF98: No | AG98: No | AI98: No | AJ98: No | AK98: No | AL98: Yes | AM98: Yes | AN98: No | AO98: No | AP98: No | AQ98: No | BF98: Vish | BH98: No | BI98: Yes | BK98: 45887 | BL98: No | BM98: No | BN98: Staples, Amazon | BO98: REQ-1754941971487 | BR98: JD20250819GOP | BS98: pswrd | BT98: Yes | BW98: 45880.662 | BX98: Completed | CP98: 45880.663 | CQ98: Complete | CR98: numbr | CS98: make | CT98: model | CU98: ab12c3 | CW98: 500 | CX98: CAD | CY98: Day | CZ98: usrnm | DA98: pswrd | DB98: abc123 | DC98: 1234 | DD98: abc123 | DE98: 1234 | DH98: Complete | DP98: No | EA98: System - Auto-approved (Hourly) | ED98: 45880.663
C99: Pending HR Setup | E99: Yes | L99: Salary | M99: 250811002 | N99: Angie | O99: O | P99: O'Plasty | R99: VP | S99: ArcelorMittal | T99: TC001 | W99: No | X99: No | Y99: No | Z99: Yes | AA99: No | AB99: No | AC99: No | AD99: No | AE99: No | AF99: No | AG99: No | AI99: No | AJ99: No | AK99: No | AL99: No | AM99: Yes | AN99: Yes | AO99: No | AP99: No | AQ99: No | AX99: ArcelorMittal | BF99: Vish | BH99: Yes | BI99: No | BJ99: angie.o'plasty@team-group.com | BK99: 45880 | BL99: No | BM99: No | BN99: Amazon, Staples, HomeDepot (physical card) | BO99: REQ-1754944362129 | DP99: No
C100: Completed | E100: Yes | G100: Vish | H100: Vishal.srikanth@team-group.com | L100: Salary | M100: 250811003 | N100: Angie | O100: O | P100: O'Plasty | R100: VP | S100: ArcelorMittal | T100: TC001 | W100: No | X100: No | Y100: No | Z100: Yes | AA100: No | AB100: No | AC100: No | AD100: No | AE100: No | AF100: No | AG100: No | AI100: No | AJ100: No | AK100: No | AL100: No | AM100: Yes | AN100: Yes | AO100: No | AP100: No | AQ100: No | AX100: ArcelorMittal | BF100: Vish | BH100: Yes | BI100: No | BJ100: angie.o'plasty@team-group.com | BK100: 45880 | BL100: No | BM100: No | BN100: Amazon, Staples, HomeDepot (physical card) | BO100: REQ-1754944516482 | BR100: AO19691231A | BS100: pswrd | BT100: Yes | BW100: 45880.692 | BX100: Completed | BZ100: Complete | CA100: Complete | CJ100: email | CK100: pswrd | CP100: 45880.692 | CW100: 500 | CX100: CAD | CY100: Day | CZ100: usrnm | DA100: pswrd | DB100: abc123 | DC100: 1234 | DD100: abc123 | DE100: 1234 | DF100: 12345678910 | DG100: 1234 | DH100: Complete | DP100: No | EA100: First Last | ED100: 45880.694
...

Sheet Sheet5

Sheet Tasks
A1: Task ID | B1: Workflow ID | C1: Task Type | D1: Status | E1: Assigned To | F1: Started At | G1: Completed At | H1: Data | I1: Metadata | J1: External Ticket ID | K1: External System | L1: Last Synced At

Sheet Workflows
A1: Workflow ID | B1: Workflow Type | C1: Status | D1: Initiated By | E1: Initiated At | F1: Completed At | G1: Metadata
A2: WF-NEWHIRE-1764104102576 | B2: NewHire | C2: Complete | D2: hr@team-group.com | E2: 45986.663 | F2: 45986.663 | G2: {"First Name":"Test","Last Name":"Employee","Requester Email":"test@team-group.com","Department":"IT","Reporting Manager":"Manager Name","Credit Card":"Yes","Fleetio / Vehicle":"Yes","JR":"Yes","30-60-90":"Yes","ADP Supervisor Access":"No","ADP Manager Access":"No","JONAS":"No","SiteDocs":"No"}

Sheet Employee Directory
A1: Employee ID | B1: First Name | C1: Middle Name | D1: Last Name | E1: Preferred Name | F1: Position / Job Title | G1: Email Address | H1: Phone Number | I1: Hourly or Salary | J1: Hire Date | K1: Site Name | L1: Site Number | M1: Reporting Manager Name | N1: Reporting Manager Email | O1: Google Account | P1: Business Card | Q1: 30-60-90 | R1: ADP Manager Access | S1: BOSS User Account | T1: Cost Sheet | U1: Leader Access | V1: Trip Reports Access | W1: JR | X1: JONAS Purchasing | Y1: JONAS Field Time | Z1: JOANS EBI | AA1: Incidents | AB1: SiteDocs Training | AC1: CAA | AD1: Fleetio / Vehicle | AE1: Credit Card | AF1: Delivery App | AG1: Mobile Phone | AH1: Computer | AI1: SiteDocs Tablet
A2: =IFERROR(__xludf.DUMMYFUNCTION("FILTER('All Responses'!M:M, 'All Responses'!C:C = ""Completed"")"),2.5072906E8) -> 250729060 | B2: =IFERROR(__xludf.DUMMYFUNCTION("FILTER('All Responses'!N:N, 'All Responses'!C:C = ""Completed"")"),"John") -> John | C2: =IFERROR(__xludf.DUMMYFUNCTION("FILTER('All Responses'!O:O, 'All Responses'!C:C = ""Completed"")"),"JD") -> JD | D2: =IFERROR(__xludf.DUMMYFUNCTION("FILTER('All Responses'!P:P, 'All Responses'!C:C = ""Completed"")"),"Doe") -> Doe | E2: =IFERROR(__xludf.DUMMYFUNCTION("FILTER('All Responses'!Q:Q, 'All Responses'!C:C = ""Completed"")"),"JD") -> JD | F2: =IFERROR(__xludf.DUMMYFUNCTION("FILTER('All Responses'!R:R, 'All Responses'!C:C = ""Completed"")"),"VP") -> VP | G2: =IFERROR(__xludf.DUMMYFUNCTION("FILTER('All Responses'!CJ:CJ, 'All Responses'!C:C = ""Completed"")"),"") | H2: =IFERROR(__xludf.DUMMYFUNCTION("FILTER('All Responses'!CL:CL, 'All Responses'!C:C = ""Completed"")"),123.0) -> 123 | I2: =IFERROR(__xludf.DUMMYFUNCTION("FILTER('All Responses'!L:L, 'All Responses'!C:C = ""Completed"")"),"Hourly") -> Hourly | J2: =IFERROR(__xludf.DUMMYFUNCTION("FILTER('All Responses'!I:I, 'All Responses'!C:C = ""Completed"")"),"") | K2: =IFERROR(__xludf.DUMMYFUNCTION("FILTER('All Responses'!S:S, 'All Responses'!C:C = ""Completed"")"),"Decostar") -> Decostar | L2: =IFERROR(__xludf.DUMMYFUNCTION("FILTER('All Responses'!T:T, 'All Responses'!C:C = ""Completed"")"),"TEST3") -> TEST3 | M2: =IFERROR(__xludf.DUMMYFUNCTION("FILTER('All Responses'!U:U, 'All Responses'!C:C = ""Completed"")"),"VS") -> VS | N2: =IFERROR(__xludf.DUMMYFUNCTION("FILTER('All Responses'!V:V, 'All Responses'!C:C = ""Completed"")"),"Vishal.srikanth@team-group.com") -> Vishal.srikanth@team-group.com | O2: =IFERROR(__xludf.DUMMYFUNCTION("FILTER('All Responses'!AN:AN, 'All Responses'!C:C = ""Completed"")"),"Required") -> Required | P2: =IFERROR(__xludf.DUMMYFUNCTION("FILTER('All Responses'!W:W, 'All Responses'!C:C = ""Completed"")"),"") | Q2: =IFERROR(__xludf.DUMMYFUNCTION("FILTER('All Responses'!X:X, 'All Responses'!C:C = ""Completed"")"),"") | R2: =IFERROR(__xludf.DUMMYFUNCTION("FILTER('All Responses'!Y:Y, 'All Responses'!C:C = ""Completed"")"),"") | S2: =IFERROR(__xludf.DUMMYFUNCTION("FILTER('All Responses'!BH:BH, 'All Responses'!C:C = ""Completed"")"),"") | T2: =IFERROR(__xludf.DUMMYFUNCTION("FILTER('All Responses'!Z:Z, 'All Responses'!C:C = ""Completed"")"),"") | U2: =IFERROR(__xludf.DUMMYFUNCTION("FILTER('All Responses'!AA:AA, 'All Responses'!C:C = ""Completed"")"),"") | V2: =IFERROR(__xludf.DUMMYFUNCTION("FILTER('All Responses'!AB:AB, 'All Responses'!C:C = ""Completed"")"),"") | W2: =IFERROR(__xludf.DUMMYFUNCTION("FILTER('All Responses'!AC:AC, 'All Responses'!C:C = ""Completed"")"),"") | X2: =IFERROR(__xludf.DUMMYFUNCTION("FILTER('All Responses'!AD:AD, 'All Responses'!C:C = ""Completed"")"),"") | Y2: =IFERROR(__xludf.DUMMYFUNCTION("FILTER('All Responses'!AE:AE, 'All Responses'!C:C = ""Completed"")"),"") | Z2: =IFERROR(__xludf.DUMMYFUNCTION("FILTER('All Responses'!AF:AF, 'All Responses'!C:C = ""Completed"")"),"") | AA2: =IFERROR(__xludf.DUMMYFUNCTION("FILTER('All Responses'!AG:AG, 'All Responses'!C:C = ""Completed"")"),"") | AB2: =IFERROR(__xludf.DUMMYFUNCTION("FILTER('All Responses'!AH:AH, 'All Responses'!C:C = ""Completed"")"),"") | AC2: =IFERROR(__xludf.DUMMYFUNCTION("FILTER('All Responses'!AI:AI, 'All Responses'!C:C = ""Completed"")"),"") | AD2: =IFERROR(__xludf.DUMMYFUNCTION("FILTER('All Responses'!AL:AL, 'All Responses'!C:C = ""Completed"")"),"") | AE2: =IFERROR(__xludf.DUMMYFUNCTION("FILTER('All Responses'!AM:AM, 'All Responses'!C:C = ""Completed"")"),"") | AF2: =IFERROR(__xludf.DUMMYFUNCTION("FILTER('All Responses'!AO:AO, 'All Responses'!C:C = ""Completed"")"),"") | AG2: =IFERROR(__xludf.DUMMYFUNCTION("FILTER('All Responses'!AP:AP, 'All Responses'!C:C = ""Completed"")"),"Required") -> Required | AH2: =IFERROR(__xludf.DUMMYFUNCTION("FILTER('All Responses'!AQ:AQ, 'All Responses'!C:C = ""Completed"")"),"Required") -> Required | AI2: =IFERROR(__xludf.DUMMYFUNCTION("FILTER('All Responses'!AR:AR, 'All Responses'!C:C = ""Completed"")"),"")
A3: =IFERROR(__xludf.DUMMYFUNCTION("""COMPUTED_VALUE"""),2.50729062E8) -> 250729062 | B3: =IFERROR(__xludf.DUMMYFUNCTION("""COMPUTED_VALUE"""),"John") -> John | C3: =IFERROR(__xludf.DUMMYFUNCTION("""COMPUTED_VALUE"""),"z") -> z | D3: =IFERROR(__xludf.DUMMYFUNCTION("""COMPUTED_VALUE"""),"Doe") -> Doe | E3: =IFERROR(__xludf.DUMMYFUNCTION("""COMPUTED_VALUE"""),"JZ") -> JZ | F3: =IFERROR(__xludf.DUMMYFUNCTION("""COMPUTED_VALUE"""),"VP") -> VP | I3: =IFERROR(__xludf.DUMMYFUNCTION("""COMPUTED_VALUE"""),"Hourly") -> Hourly | J3: =IFERROR(__xludf.DUMMYFUNCTION("""COMPUTED_VALUE"""),45875.0) -> 45875 | K3: =IFERROR(__xludf.DUMMYFUNCTION("""COMPUTED_VALUE"""),"Etobicote") -> Etobicote | L3: =IFERROR(__xludf.DUMMYFUNCTION("""COMPUTED_VALUE"""),"TEST5") -> TEST5 | M3: =IFERROR(__xludf.DUMMYFUNCTION("""COMPUTED_VALUE"""),"Jane Doe") -> Jane Doe | N3: =IFERROR(__xludf.DUMMYFUNCTION("""COMPUTED_VALUE"""),"Vishal.srikanth@team-group.com") -> Vishal.srikanth@team-group.com
A4: =IFERROR(__xludf.DUMMYFUNCTION("""COMPUTED_VALUE"""),2.50729063E8) -> 250729063 | B4: =IFERROR(__xludf.DUMMYFUNCTION("""COMPUTED_VALUE"""),"John") -> John | C4: =IFERROR(__xludf.DUMMYFUNCTION("""COMPUTED_VALUE"""),"JD") -> JD | D4: =IFERROR(__xludf.DUMMYFUNCTION("""COMPUTED_VALUE"""),"Doe") -> Doe | E4: =IFERROR(__xludf.DUMMYFUNCTION("""COMPUTED_VALUE"""),"JD") -> JD | F4: =IFERROR(__xludf.DUMMYFUNCTION("""COMPUTED_VALUE"""),"VP") -> VP | G4: =IFERROR(__xludf.DUMMYFUNCTION("""COMPUTED_VALUE"""),"email") -> email | H4: =IFERROR(__xludf.DUMMYFUNCTION("""COMPUTED_VALUE"""),123.0) -> 123 | I4: =IFERROR(__xludf.DUMMYFUNCTION("""COMPUTED_VALUE"""),"Hourly") -> Hourly | J4: =IFERROR(__xludf.DUMMYFUNCTION("""COMPUTED_VALUE"""),45876.0) -> 45876 | K4: =IFERROR(__xludf.DUMMYFUNCTION("""COMPUTED_VALUE"""),"Decostar") -> Decostar | L4: =IFERROR(__xludf.DUMMYFUNCTION("""COMPUTED_VALUE"""),"TEST3") -> TEST3 | M4: =IFERROR(__xludf.DUMMYFUNCTION("""COMPUTED_VALUE"""),"Jane Doe") -> Jane Doe | N4: =IFERROR(__xludf.DUMMYFUNCTION("""COMPUTED_VALUE"""),"Vishal.srikanth@team-group.com") -> Vishal.srikanth@team-group.com | O4: =IFERROR(__xludf.DUMMYFUNCTION("""COMPUTED_VALUE"""),"Required") -> Required | P4: =IFERROR(__xludf.DUMMYFUNCTION("""COMPUTED_VALUE"""),"Required") -> Required | Q4: =IFERROR(__xludf.DUMMYFUNCTION("""COMPUTED_VALUE"""),"Required") -> Required | R4: =IFERROR(__xludf.DUMMYFUNCTION("""COMPUTED_VALUE"""),"Required") -> Required | S4: =IFERROR(__xludf.DUMMYFUNCTION("""COMPUTED_VALUE"""),"Required") -> Required | T4: =IFERROR(__xludf.DUMMYFUNCTION("""COMPUTED_VALUE"""),"Required") -> Required | U4: =IFERROR(__xludf.DUMMYFUNCTION("""COMPUTED_VALUE"""),"Required") -> Required | V4: =IFERROR(__xludf.DUMMYFUNCTION("""COMPUTED_VALUE"""),"Required") -> Required | ... AI4: =IFERROR(__xludf.DUMMYFUNCTION("""COMPUTED_VALUE"""),"Required") -> Required
A5: =IFERROR(__xludf.DUMMYFUNCTION("""COMPUTED_VALUE"""),2.50729064E8) -> 250729064 | B5: =IFERROR(__xludf.DUMMYFUNCTION("""COMPUTED_VALUE"""),"John") -> John | C5: =IFERROR(__xludf.DUMMYFUNCTION("""COMPUTED_VALUE"""),"JD") -> JD | D5: =IFERROR(__xludf.DUMMYFUNCTION("""COMPUTED_VALUE"""),"Doe") -> Doe | E5: =IFERROR(__xludf.DUMMYFUNCTION("""COMPUTED_VALUE"""),"JD") -> JD | F5: =IFERROR(__xludf.DUMMYFUNCTION("""COMPUTED_VALUE"""),"VP") -> VP | H5: =IFERROR(__xludf.DUMMYFUNCTION("""COMPUTED_VALUE"""),123.0) -> 123 | I5: =IFERROR(__xludf.DUMMYFUNCTION("""COMPUTED_VALUE"""),"Salary") -> Salary | J5: =IFERROR(__xludf.DUMMYFUNCTION("""COMPUTED_VALUE"""),45875.0) -> 45875 | K5: =IFERROR(__xludf.DUMMYFUNCTION("""COMPUTED_VALUE"""),"Etobicote") -> Etobicote | L5: =IFERROR(__xludf.DUMMYFUNCTION("""COMPUTED_VALUE"""),"TEST5") -> TEST5 | M5: =IFERROR(__xludf.DUMMYFUNCTION("""COMPUTED_VALUE"""),"Jane Doe") -> Jane Doe | N5: =IFERROR(__xludf.DUMMYFUNCTION("""COMPUTED_VALUE"""),"Vishal.srikanth@team-group.com") -> Vishal.srikanth@team-group.com | O5: =IFERROR(__xludf.DUMMYFUNCTION("""COMPUTED_VALUE"""),"Required") -> Required | P5: =IFERROR(__xludf.DUMMYFUNCTION("""COMPUTED_VALUE"""),"Required") -> Required | Q5: =IFERROR(__xludf.DUMMYFUNCTION("""COMPUTED_VALUE"""),"Required") -> Required | R5: =IFERROR(__xludf.DUMMYFUNCTION("""COMPUTED_VALUE"""),"Required") -> Required | S5: =IFERROR(__xludf.DUMMYFUNCTION("""COMPUTED_VALUE"""),"Required") -> Required | T5: =IFERROR(__xludf.DUMMYFUNCTION("""COMPUTED_VALUE"""),"Required") -> Required | U5: =IFERROR(__xludf.DUMMYFUNCTION("""COMPUTED_VALUE"""),"Required") -> Required | V5: =IFERROR(__xludf.DUMMYFUNCTION("""COMPUTED_VALUE"""),"Required") -> Required | ... AI5: =IFERROR(__xludf.DUMMYFUNCTION("""COMPUTED_VALUE"""),"Required") -> Required
A6: =IFERROR(__xludf.DUMMYFUNCTION("""COMPUTED_VALUE"""),2.50729065E8) -> 250729065 | B6: =IFERROR(__xludf.DUMMYFUNCTION("""COMPUTED_VALUE"""),"John") -> John | C6: =IFERROR(__xludf.DUMMYFUNCTION("""COMPUTED_VALUE"""),"JD") -> JD | D6: =IFERROR(__xludf.DUMMYFUNCTION("""COMPUTED_VALUE"""),"Doe") -> Doe | E6: =IFERROR(__xludf.DUMMYFUNCTION("""COMPUTED_VALUE"""),"JD") -> JD | F6: =IFERROR(__xludf.DUMMYFUNCTION("""COMPUTED_VALUE"""),"VP") -> VP | H6: =IFERROR(__xludf.DUMMYFUNCTION("""COMPUTED_VALUE"""),123.0) -> 123 | I6: =IFERROR(__xludf.DUMMYFUNCTION("""COMPUTED_VALUE"""),"Salary") -> Salary | J6: =IFERROR(__xludf.DUMMYFUNCTION("""COMPUTED_VALUE"""),45875.0) -> 45875 | K6: =IFERROR(__xludf.DUMMYFUNCTION("""COMPUTED_VALUE"""),"Etobicote") -> Etobicote | L6: =IFERROR(__xludf.DUMMYFUNCTION("""COMPUTED_VALUE"""),"TEST5") -> TEST5 | M6: =IFERROR(__xludf.DUMMYFUNCTION("""COMPUTED_VALUE"""),"VS") -> VS | N6: =IFERROR(__xludf.DUMMYFUNCTION("""COMPUTED_VALUE"""),"Vishal.srikanth@team-group.com") -> Vishal.srikanth@team-group.com | O6: =IFERROR(__xludf.DUMMYFUNCTION("""COMPUTED_VALUE"""),"Required") -> Required | P6: =IFERROR(__xludf.DUMMYFUNCTION("""COMPUTED_VALUE"""),"Required") -> Required | Q6: =IFERROR(__xludf.DUMMYFUNCTION("""COMPUTED_VALUE"""),"Required") -> Required | R6: =IFERROR(__xludf.DUMMYFUNCTION("""COMPUTED_VALUE"""),"Required") -> Required | S6: =IFERROR(__xludf.DUMMYFUNCTION("""COMPUTED_VALUE"""),"Required") -> Required | T6: =IFERROR(__xludf.DUMMYFUNCTION("""COMPUTED_VALUE"""),"Required") -> Required | Z6: =IFERROR(__xludf.DUMMYFUNCTION("""COMPUTED_VALUE"""),"Required") -> Required | AG6: =IFERROR(__xludf.DUMMYFUNCTION("""COMPUTED_VALUE"""),"Required") -> Required | AH6: =IFERROR(__xludf.DUMMYFUNCTION("""COMPUTED_VALUE"""),"Required") -> Required
A7: =IFERROR(__xludf.DUMMYFUNCTION("""COMPUTED_VALUE"""),2.50729066E8) -> 250729066 | B7: =IFERROR(__xludf.DUMMYFUNCTION("""COMPUTED_VALUE"""),"John") -> John | C7: =IFERROR(__xludf.DUMMYFUNCTION("""COMPUTED_VALUE"""),"JD") -> JD | D7: =IFERROR(__xludf.DUMMYFUNCTION("""COMPUTED_VALUE"""),"Doe") -> Doe | E7: =IFERROR(__xludf.DUMMYFUNCTION("""COMPUTED_VALUE"""),"JD") -> JD | F7: =IFERROR(__xludf.DUMMYFUNCTION("""COMPUTED_VALUE"""),"VP") -> VP | I7: =IFERROR(__xludf.DUMMYFUNCTION("""COMPUTED_VALUE"""),"Hourly") -> Hourly | J7: =IFERROR(__xludf.DUMMYFUNCTION("""COMPUTED_VALUE"""),45875.0) -> 45875 | K7: =IFERROR(__xludf.DUMMYFUNCTION("""COMPUTED_VALUE"""),"Edmonton") -> Edmonton | L7: =IFERROR(__xludf.DUMMYFUNCTION("""COMPUTED_VALUE"""),"TEST4") -> TEST4 | M7: =IFERROR(__xludf.DUMMYFUNCTION("""COMPUTED_VALUE"""),"Jane Doe") -> Jane Doe | O7: =IFERROR(__xludf.DUMMYFUNCTION("""COMPUTED_VALUE"""),"Required") -> Required | S7: =IFERROR(__xludf.DUMMYFUNCTION("""COMPUTED_VALUE"""),"Required") -> Required | T7: =IFERROR(__xludf.DUMMYFUNCTION("""COMPUTED_VALUE"""),"Required") -> Required | U7: =IFERROR(__xludf.DUMMYFUNCTION("""COMPUTED_VALUE"""),"Required") -> Required | AF7: =IFERROR(__xludf.DUMMYFUNCTION("""COMPUTED_VALUE"""),"Required") -> Required | AH7: =IFERROR(__xludf.DUMMYFUNCTION("""COMPUTED_VALUE"""),"Required") -> Required
A8: =IFERROR(__xludf.DUMMYFUNCTION("""COMPUTED_VALUE"""),2.50730001E8) -> 250730001 | B8: =IFERROR(__xludf.DUMMYFUNCTION("""COMPUTED_VALUE"""),"John") -> John | C8: =IFERROR(__xludf.DUMMYFUNCTION("""COMPUTED_VALUE"""),"JD") -> JD | D8: =IFERROR(__xludf.DUMMYFUNCTION("""COMPUTED_VALUE"""),"Doe") -> Doe | E8: =IFERROR(__xludf.DUMMYFUNCTION("""COMPUTED_VALUE"""),"JD") -> JD | F8: =IFERROR(__xludf.DUMMYFUNCTION("""COMPUTED_VALUE"""),"VP") -> VP | H8: =IFERROR(__xludf.DUMMYFUNCTION("""COMPUTED_VALUE"""),123.0) -> 123 | I8: =IFERROR(__xludf.DUMMYFUNCTION("""COMPUTED_VALUE"""),"Salary") -> Salary | J8: =IFERROR(__xludf.DUMMYFUNCTION("""COMPUTED_VALUE"""),45876.0) -> 45876 | K8: =IFERROR(__xludf.DUMMYFUNCTION("""COMPUTED_VALUE"""),"Bluebird") -> Bluebird | L8: =IFERROR(__xludf.DUMMYFUNCTION("""COMPUTED_VALUE"""),"TEST1") -> TEST1 | M8: =IFERROR(__xludf.DUMMYFUNCTION("""COMPUTED_VALUE"""),"Jane Doe") -> Jane Doe | N8: =IFERROR(__xludf.DUMMYFUNCTION("""COMPUTED_VALUE"""),"Vishal.srikanth@team-group.com") -> Vishal.srikanth@team-group.com | O8: =IFERROR(__xludf.DUMMYFUNCTION("""COMPUTED_VALUE"""),"Required") -> Required | P8: =IFERROR(__xludf.DUMMYFUNCTION("""COMPUTED_VALUE"""),"Required") -> Required | Q8: =IFERROR(__xludf.DUMMYFUNCTION("""COMPUTED_VALUE"""),"Required") -> Required | R8: =IFERROR(__xludf.DUMMYFUNCTION("""COMPUTED_VALUE"""),"Required") -> Required | S8: =IFERROR(__xludf.DUMMYFUNCTION("""COMPUTED_VALUE"""),"Required") -> Required | T8: =IFERROR(__xludf.DUMMYFUNCTION("""COMPUTED_VALUE"""),"Required") -> Required | U8: =IFERROR(__xludf.DUMMYFUNCTION("""COMPUTED_VALUE"""),"Required") -> Required | V8: =IFERROR(__xludf.DUMMYFUNCTION("""COMPUTED_VALUE"""),"Required") -> Required | ... AI8: =IFERROR(__xludf.DUMMYFUNCTION("""COMPUTED_VALUE"""),"Required") -> Required
A9: =IFERROR(__xludf.DUMMYFUNCTION("""COMPUTED_VALUE"""),2.50730003E8) -> 250730003 | B9: =IFERROR(__xludf.DUMMYFUNCTION("""COMPUTED_VALUE"""),"John") -> John | C9: =IFERROR(__xludf.DUMMYFUNCTION("""COMPUTED_VALUE"""),"JD") -> JD | D9: =IFERROR(__xludf.DUMMYFUNCTION("""COMPUTED_VALUE"""),"Doe") -> Doe | E9: =IFERROR(__xludf.DUMMYFUNCTION("""COMPUTED_VALUE"""),"JD") -> JD | F9: =IFERROR(__xludf.DUMMYFUNCTION("""COMPUTED_VALUE"""),"VP") -> VP | H9: =IFERROR(__xludf.DUMMYFUNCTION("""COMPUTED_VALUE"""),123.0) -> 123 | I9: =IFERROR(__xludf.DUMMYFUNCTION("""COMPUTED_VALUE"""),"Salary") -> Salary | J9: =IFERROR(__xludf.DUMMYFUNCTION("""COMPUTED_VALUE"""),45875.0) -> 45875 | K9: =IFERROR(__xludf.DUMMYFUNCTION("""COMPUTED_VALUE"""),"Edmonton") -> Edmonton | L9: =IFERROR(__xludf.DUMMYFUNCTION("""COMPUTED_VALUE"""),"TEST4") -> TEST4 | M9: =IFERROR(__xludf.DUMMYFUNCTION("""COMPUTED_VALUE"""),"Jane Doe") -> Jane Doe | N9: =IFERROR(__xludf.DUMMYFUNCTION("""COMPUTED_VALUE"""),"Vishal.srikanth@team-group.com") -> Vishal.srikanth@team-group.com | O9: =IFERROR(__xludf.DUMMYFUNCTION("""COMPUTED_VALUE"""),"Required") -> Required | P9: =IFERROR(__xludf.DUMMYFUNCTION("""COMPUTED_VALUE"""),"Required") -> Required | R9: =IFERROR(__xludf.DUMMYFUNCTION("""COMPUTED_VALUE"""),"Required") -> Required | W9: =IFERROR(__xludf.DUMMYFUNCTION("""COMPUTED_VALUE"""),"Required") -> Required | Y9: =IFERROR(__xludf.DUMMYFUNCTION("""COMPUTED_VALUE"""),"Required") -> Required | AD9: =IFERROR(__xludf.DUMMYFUNCTION("""COMPUTED_VALUE"""),"Required") -> Required | AG9: =IFERROR(__xludf.DUMMYFUNCTION("""COMPUTED_VALUE"""),"Required") -> Required
A10: =IFERROR(__xludf.DUMMYFUNCTION("""COMPUTED_VALUE"""),2.50730004E8) -> 250730004 | B10: =IFERROR(__xludf.DUMMYFUNCTION("""COMPUTED_VALUE"""),"John") -> John | C10: =IFERROR(__xludf.DUMMYFUNCTION("""COMPUTED_VALUE"""),"JD") -> JD | D10: =IFERROR(__xludf.DUMMYFUNCTION("""COMPUTED_VALUE"""),"Doe") -> Doe | E10: =IFERROR(__xludf.DUMMYFUNCTION("""COMPUTED_VALUE"""),"JD") -> JD | F10: =IFERROR(__xludf.DUMMYFUNCTION("""COMPUTED_VALUE"""),"VP") -> VP | H10: =IFERROR(__xludf.DUMMYFUNCTION("""COMPUTED_VALUE"""),123.0) -> 123 | I10: =IFERROR(__xludf.DUMMYFUNCTION("""COMPUTED_VALUE"""),"Salary") -> Salary | J10: =IFERROR(__xludf.DUMMYFUNCTION("""COMPUTED_VALUE"""),45877.0) -> 45877 | K10: =IFERROR(__xludf.DUMMYFUNCTION("""COMPUTED_VALUE"""),"Edmonton") -> Edmonton | L10: =IFERROR(__xludf.DUMMYFUNCTION("""COMPUTED_VALUE"""),"TEST4") -> TEST4 | M10: =IFERROR(__xludf.DUMMYFUNCTION("""COMPUTED_VALUE"""),"Jane Doe") -> Jane Doe | N10: =IFERROR(__xludf.DUMMYFUNCTION("""COMPUTED_VALUE"""),"Vishal.srikanth@team-group.com") -> Vishal.srikanth@team-group.com | O10: =IFERROR(__xludf.DUMMYFUNCTION("""COMPUTED_VALUE"""),"Required") -> Required | P10: =IFERROR(__xludf.DUMMYFUNCTION("""COMPUTED_VALUE"""),"Required") -> Required | Q10: =IFERROR(__xludf.DUMMYFUNCTION("""COMPUTED_VALUE"""),"Required") -> Required | R10: =IFERROR(__xludf.DUMMYFUNCTION("""COMPUTED_VALUE"""),"Required") -> Required | S10: =IFERROR(__xludf.DUMMYFUNCTION("""COMPUTED_VALUE"""),"Required") -> Required | T10: =IFERROR(__xludf.DUMMYFUNCTION("""COMPUTED_VALUE"""),"Required") -> Required | U10: =IFERROR(__xludf.DUMMYFUNCTION("""COMPUTED_VALUE"""),"Required") -> Required | V10: =IFERROR(__xludf.DUMMYFUNCTION("""COMPUTED_VALUE"""),"Required") -> Required | ... AI10: =IFERROR(__xludf.DUMMYFUNCTION("""COMPUTED_VALUE"""),"Required") -> Required
A11: =IFERROR(__xludf.DUMMYFUNCTION("""COMPUTED_VALUE"""),2.50730005E8) -> 250730005 | B11: =IFERROR(__xludf.DUMMYFUNCTION("""COMPUTED_VALUE"""),"John") -> John | C11: =IFERROR(__xludf.DUMMYFUNCTION("""COMPUTED_VALUE"""),"JD") -> JD | D11: =IFERROR(__xludf.DUMMYFUNCTION("""COMPUTED_VALUE"""),"Doe") -> Doe | E11: =IFERROR(__xludf.DUMMYFUNCTION("""COMPUTED_VALUE"""),"JD") -> JD | F11: =IFERROR(__xludf.DUMMYFUNCTION("""COMPUTED_VALUE"""),"VP") -> VP | H11: =IFERROR(__xludf.DUMMYFUNCTION("""COMPUTED_VALUE"""),123.0) -> 123 | I11: =IFERROR(__xludf.DUMMYFUNCTION("""COMPUTED_VALUE"""),"Salary") -> Salary | J11: =IFERROR(__xludf.DUMMYFUNCTION("""COMPUTED_VALUE"""),45874.0) -> 45874 | K11: =IFERROR(__xludf.DUMMYFUNCTION("""COMPUTED_VALUE"""),"Bluebird") -> Bluebird | L11: =IFERROR(__xludf.DUMMYFUNCTION("""COMPUTED_VALUE"""),"TEST1") -> TEST1 | M11: =IFERROR(__xludf.DUMMYFUNCTION("""COMPUTED_VALUE"""),"Jane Doe") -> Jane Doe | N11: =IFERROR(__xludf.DUMMYFUNCTION("""COMPUTED_VALUE"""),"Vishal.srikanth@team-group.com") -> Vishal.srikanth@team-group.com | O11: =IFERROR(__xludf.DUMMYFUNCTION("""COMPUTED_VALUE"""),"Required") -> Required | P11: =IFERROR(__xludf.DUMMYFUNCTION("""COMPUTED_VALUE"""),"Required") -> Required | Q11: =IFERROR(__xludf.DUMMYFUNCTION("""COMPUTED_VALUE"""),"Required") -> Required | R11: =IFERROR(__xludf.DUMMYFUNCTION("""COMPUTED_VALUE"""),"Required") -> Required | S11: =IFERROR(__xludf.DUMMYFUNCTION("""COMPUTED_VALUE"""),"Required") -> Required | T11: =IFERROR(__xludf.DUMMYFUNCTION("""COMPUTED_VALUE"""),"Required") -> Required | U11: =IFERROR(__xludf.DUMMYFUNCTION("""COMPUTED_VALUE"""),"Required") -> Required | V11: =IFERROR(__xludf.DUMMYFUNCTION("""COMPUTED_VALUE"""),"Required") -> Required | ... AI11: =IFERROR(__xludf.DUMMYFUNCTION("""COMPUTED_VALUE"""),"Required") -> Required
A12: =IFERROR(__xludf.DUMMYFUNCTION("""COMPUTED_VALUE"""),2.50805002E8) -> 250805002 | B12: =IFERROR(__xludf.DUMMYFUNCTION("""COMPUTED_VALUE"""),"John") -> John | C12: =IFERROR(__xludf.DUMMYFUNCTION("""COMPUTED_VALUE"""),"JD") -> JD | D12: =IFERROR(__xludf.DUMMYFUNCTION("""COMPUTED_VALUE"""),"Doe") -> Doe | E12: =IFERROR(__xludf.DUMMYFUNCTION("""COMPUTED_VALUE"""),"JD") -> JD | F12: =IFERROR(__xludf.DUMMYFUNCTION("""COMPUTED_VALUE"""),"VP") -> VP | H12: =IFERROR(__xludf.DUMMYFUNCTION("""COMPUTED_VALUE"""),123.0) -> 123 | I12: =IFERROR(__xludf.DUMMYFUNCTION("""COMPUTED_VALUE"""),"Salary") -> Salary | J12: =IFERROR(__xludf.DUMMYFUNCTION("""COMPUTED_VALUE"""),45881.0) -> 45881 | K12: =IFERROR(__xludf.DUMMYFUNCTION("""COMPUTED_VALUE"""),"Bluebird") -> Bluebird | L12: =IFERROR(__xludf.DUMMYFUNCTION("""COMPUTED_VALUE"""),"TEST1") -> TEST1 | M12: =IFERROR(__xludf.DUMMYFUNCTION("""COMPUTED_VALUE"""),"VS") -> VS | N12: =IFERROR(__xludf.DUMMYFUNCTION("""COMPUTED_VALUE"""),"Vishal.srikanth@team-group.com") -> Vishal.srikanth@team-group.com | O12: =IFERROR(__xludf.DUMMYFUNCTION("""COMPUTED_VALUE"""),"Required") -> Required | P12: =IFERROR(__xludf.DUMMYFUNCTION("""COMPUTED_VALUE"""),"Required") -> Required | Q12: =IFERROR(__xludf.DUMMYFUNCTION("""COMPUTED_VALUE"""),"Required") -> Required | R12: =IFERROR(__xludf.DUMMYFUNCTION("""COMPUTED_VALUE"""),"Required") -> Required | S12: =IFERROR(__xludf.DUMMYFUNCTION("""COMPUTED_VALUE"""),"Required") -> Required | T12: =IFERROR(__xludf.DUMMYFUNCTION("""COMPUTED_VALUE"""),"Required") -> Required | U12: =IFERROR(__xludf.DUMMYFUNCTION("""COMPUTED_VALUE"""),"Required") -> Required | V12: =IFERROR(__xludf.DUMMYFUNCTION("""COMPUTED_VALUE"""),"Required") -> Required | ... AI12: =IFERROR(__xludf.DUMMYFUNCTION("""COMPUTED_VALUE"""),"Required") -> Required
A13: =IFERROR(__xludf.DUMMYFUNCTION("""COMPUTED_VALUE"""),2.50805006E8) -> 250805006 | B13: =IFERROR(__xludf.DUMMYFUNCTION("""COMPUTED_VALUE"""),"John") -> John | C13: =IFERROR(__xludf.DUMMYFUNCTION("""COMPUTED_VALUE"""),"JD") -> JD | D13: =IFERROR(__xludf.DUMMYFUNCTION("""COMPUTED_VALUE"""),"Doe") -> Doe | E13: =IFERROR(__xludf.DUMMYFUNCTION("""COMPUTED_VALUE"""),"JD") -> JD | F13: =IFERROR(__xludf.DUMMYFUNCTION("""COMPUTED_VALUE"""),"VP") -> VP | G13: =IFERROR(__xludf.DUMMYFUNCTION("""COMPUTED_VALUE"""),"email") -> email | H13: =IFERROR(__xludf.DUMMYFUNCTION("""COMPUTED_VALUE"""),123.0) -> 123 | I13: =IFERROR(__xludf.DUMMYFUNCTION("""COMPUTED_VALUE"""),"Hourly") -> Hourly | J13: =IFERROR(__xludf.DUMMYFUNCTION("""COMPUTED_VALUE"""),45889.0) -> 45889 | K13: =IFERROR(__xludf.DUMMYFUNCTION("""COMPUTED_VALUE"""),"Decostar") -> Decostar | L13: =IFERROR(__xludf.DUMMYFUNCTION("""COMPUTED_VALUE"""),"TEST3") -> TEST3 | M13: =IFERROR(__xludf.DUMMYFUNCTION("""COMPUTED_VALUE"""),"Jane Doe") -> Jane Doe | N13: =IFERROR(__xludf.DUMMYFUNCTION("""COMPUTED_VALUE"""),"Vishal.srikanth@team-group.com") -> Vishal.srikanth@team-group.com | O13: =IFERROR(__xludf.DUMMYFUNCTION("""COMPUTED_VALUE"""),"Yes") -> Yes | P13: =IFERROR(__xludf.DUMMYFUNCTION("""COMPUTED_VALUE"""),"No") -> No | Q13: =IFERROR(__xludf.DUMMYFUNCTION("""COMPUTED_VALUE"""),"No") -> No | R13: =IFERROR(__xludf.DUMMYFUNCTION("""COMPUTED_VALUE"""),"No") -> No | S13: =IFERROR(__xludf.DUMMYFUNCTION("""COMPUTED_VALUE"""),"No") -> No | T13: =IFERROR(__xludf.DUMMYFUNCTION("""COMPUTED_VALUE"""),"No") -> No | U13: =IFERROR(__xludf.DUMMYFUNCTION("""COMPUTED_VALUE"""),"No") -> No | V13: =IFERROR(__xludf.DUMMYFUNCTION("""COMPUTED_VALUE"""),"No") -> No | W13: =IFERROR(__xludf.DUMMYFUNCTION("""COMPUTED_VALUE"""),"No") -> No | ... AD13: =IFERROR(__xludf.DUMMYFUNCTION("""COMPUTED_VALUE"""),"No") -> No | AE13: =IFERROR(__xludf.DUMMYFUNCTION("""COMPUTED_VALUE"""),"Yes") -> Yes | AF13: =IFERROR(__xludf.DUMMYFUNCTION("""COMPUTED_VALUE"""),"No") -> No | AG13: =IFERROR(__xludf.DUMMYFUNCTION("""COMPUTED_VALUE"""),"Yes") -> Yes | AH13: =IFERROR(__xludf.DUMMYFUNCTION("""COMPUTED_VALUE"""),"No") -> No | AI13: =IFERROR(__xludf.DUMMYFUNCTION("""COMPUTED_VALUE"""),"Yes") -> Yes
A14: =IFERROR(__xludf.DUMMYFUNCTION("""COMPUTED_VALUE"""),2.50805007E8) -> 250805007 | B14: =IFERROR(__xludf.DUMMYFUNCTION("""COMPUTED_VALUE"""),"John") -> John | C14: =IFERROR(__xludf.DUMMYFUNCTION("""COMPUTED_VALUE"""),"JD") -> JD | D14: =IFERROR(__xludf.DUMMYFUNCTION("""COMPUTED_VALUE"""),"Doe") -> Doe | F14: =IFERROR(__xludf.DUMMYFUNCTION("""COMPUTED_VALUE"""),"VP") -> VP | I14: =IFERROR(__xludf.DUMMYFUNCTION("""COMPUTED_VALUE"""),"Hourly") -> Hourly | J14: =IFERROR(__xludf.DUMMYFUNCTION("""COMPUTED_VALUE"""),45883.0) -> 45883 | K14: =IFERROR(__xludf.DUMMYFUNCTION("""COMPUTED_VALUE"""),"Decostar") -> Decostar | L14: =IFERROR(__xludf.DUMMYFUNCTION("""COMPUTED_VALUE"""),"TEST3") -> TEST3 | M14: =IFERROR(__xludf.DUMMYFUNCTION("""COMPUTED_VALUE"""),"Jane Doe") -> Jane Doe | N14: =IFERROR(__xludf.DUMMYFUNCTION("""COMPUTED_VALUE"""),"Vishal.srikanth@team-group.com") -> Vishal.srikanth@team-group.com | O14: =IFERROR(__xludf.DUMMYFUNCTION("""COMPUTED_VALUE"""),"No") -> No | P14: =IFERROR(__xludf.DUMMYFUNCTION("""COMPUTED_VALUE"""),"No") -> No | Q14: =IFERROR(__xludf.DUMMYFUNCTION("""COMPUTED_VALUE"""),"No") -> No | R14: =IFERROR(__xludf.DUMMYFUNCTION("""COMPUTED_VALUE"""),"No") -> No | S14: =IFERROR(__xludf.DUMMYFUNCTION("""COMPUTED_VALUE"""),"No") -> No | T14: =IFERROR(__xludf.DUMMYFUNCTION("""COMPUTED_VALUE"""),"No") -> No | U14: =IFERROR(__xludf.DUMMYFUNCTION("""COMPUTED_VALUE"""),"No") -> No | V14: =IFERROR(__xludf.DUMMYFUNCTION("""COMPUTED_VALUE"""),"No") -> No | ... AI14: =IFERROR(__xludf.DUMMYFUNCTION("""COMPUTED_VALUE"""),"No") -> No
A15: =IFERROR(__xludf.DUMMYFUNCTION("""COMPUTED_VALUE"""),2.50806001E8) -> 250806001 | B15: =IFERROR(__xludf.DUMMYFUNCTION("""COMPUTED_VALUE"""),"John") -> John | D15: =IFERROR(__xludf.DUMMYFUNCTION("""COMPUTED_VALUE"""),"Doe") -> Doe | F15: =IFERROR(__xludf.DUMMYFUNCTION("""COMPUTED_VALUE"""),"VP") -> VP | I15: =IFERROR(__xludf.DUMMYFUNCTION("""COMPUTED_VALUE"""),"Hourly") -> Hourly | J15: =IFERROR(__xludf.DUMMYFUNCTION("""COMPUTED_VALUE"""),45904.0) -> 45904 | K15: =IFERROR(__xludf.DUMMYFUNCTION("""COMPUTED_VALUE"""),"Chrysler Windsor Paintshop") -> Chrysler Windsor Paintshop | L15: =IFERROR(__xludf.DUMMYFUNCTION("""COMPUTED_VALUE"""),"TW049") -> TW049 | M15: =IFERROR(__xludf.DUMMYFUNCTION("""COMPUTED_VALUE"""),"Jane Doe") -> Jane Doe | N15: =IFERROR(__xludf.DUMMYFUNCTION("""COMPUTED_VALUE"""),"Vishal.srikanth@team-group.com") -> Vishal.srikanth@team-group.com | O15: =IFERROR(__xludf.DUMMYFUNCTION("""COMPUTED_VALUE"""),"No") -> No | P15: =IFERROR(__xludf.DUMMYFUNCTION("""COMPUTED_VALUE"""),"No") -> No | Q15: =IFERROR(__xludf.DUMMYFUNCTION("""COMPUTED_VALUE"""),"No") -> No | R15: =IFERROR(__xludf.DUMMYFUNCTION("""COMPUTED_VALUE"""),"No") -> No | S15: =IFERROR(__xludf.DUMMYFUNCTION("""COMPUTED_VALUE"""),"No") -> No | T15: =IFERROR(__xludf.DUMMYFUNCTION("""COMPUTED_VALUE"""),"No") -> No | U15: =IFERROR(__xludf.DUMMYFUNCTION("""COMPUTED_VALUE"""),"No") -> No | V15: =IFERROR(__xludf.DUMMYFUNCTION("""COMPUTED_VALUE"""),"No") -> No | ... AD15: =IFERROR(__xludf.DUMMYFUNCTION("""COMPUTED_VALUE"""),"No") -> No | AE15: =IFERROR(__xludf.DUMMYFUNCTION("""COMPUTED_VALUE"""),"Yes") -> Yes | AF15: =IFERROR(__xludf.DUMMYFUNCTION("""COMPUTED_VALUE"""),"No") -> No | AG15: =IFERROR(__xludf.DUMMYFUNCTION("""COMPUTED_VALUE"""),"No") -> No | AH15: =IFERROR(__xludf.DUMMYFUNCTION("""COMPUTED_VALUE"""),"No") -> No | AI15: =IFERROR(__xludf.DUMMYFUNCTION("""COMPUTED_VALUE"""),"No") -> No
A16: =IFERROR(__xludf.DUMMYFUNCTION("""COMPUTED_VALUE"""),2.50806002E8) -> 250806002 | B16: =IFERROR(__xludf.DUMMYFUNCTION("""COMPUTED_VALUE"""),"John") -> John | C16: =IFERROR(__xludf.DUMMYFUNCTION("""COMPUTED_VALUE"""),"JD") -> JD | D16: =IFERROR(__xludf.DUMMYFUNCTION("""COMPUTED_VALUE"""),"Doe") -> Doe | F16: =IFERROR(__xludf.DUMMYFUNCTION("""COMPUTED_VALUE"""),"VP") -> VP | I16: =IFERROR(__xludf.DUMMYFUNCTION("""COMPUTED_VALUE"""),"Hourly") -> Hourly | J16: =IFERROR(__xludf.DUMMYFUNCTION("""COMPUTED_VALUE"""),45894.0) -> 45894 | K16: =IFERROR(__xludf.DUMMYFUNCTION("""COMPUTED_VALUE"""),"Cost Variance - RSI") -> Cost Variance - RSI | L16: =IFERROR(__xludf.DUMMYFUNCTION("""COMPUTED_VALUE"""),171.0) -> 171 | M16: =IFERROR(__xludf.DUMMYFUNCTION("""COMPUTED_VALUE"""),"VS") -> VS | N16: =IFERROR(__xludf.DUMMYFUNCTION("""COMPUTED_VALUE"""),"Vishal.srikanth@team-group.com") -> Vishal.srikanth@team-group.com | O16: =IFERROR(__xludf.DUMMYFUNCTION("""COMPUTED_VALUE"""),"No") -> No | P16: =IFERROR(__xludf.DUMMYFUNCTION("""COMPUTED_VALUE"""),"No") -> No | Q16: =IFERROR(__xludf.DUMMYFUNCTION("""COMPUTED_VALUE"""),"No") -> No | R16: =IFERROR(__xludf.DUMMYFUNCTION("""COMPUTED_VALUE"""),"No") -> No | S16: =IFERROR(__xludf.DUMMYFUNCTION("""COMPUTED_VALUE"""),"No") -> No | T16: =IFERROR(__xludf.DUMMYFUNCTION("""COMPUTED_VALUE"""),"No") -> No | U16: =IFERROR(__xludf.DUMMYFUNCTION("""COMPUTED_VALUE"""),"No") -> No | V16: =IFERROR(__xludf.DUMMYFUNCTION("""COMPUTED_VALUE"""),"No") -> No | ... AI16: =IFERROR(__xludf.DUMMYFUNCTION("""COMPUTED_VALUE"""),"No") -> No
A17: =IFERROR(__xludf.DUMMYFUNCTION("""COMPUTED_VALUE"""),2.50806003E8) -> 250806003 | B17: =IFERROR(__xludf.DUMMYFUNCTION("""COMPUTED_VALUE"""),"John") -> John | C17: =IFERROR(__xludf.DUMMYFUNCTION("""COMPUTED_VALUE"""),"z") -> z | D17: =IFERROR(__xludf.DUMMYFUNCTION("""COMPUTED_VALUE"""),"Doe") -> Doe | E17: =IFERROR(__xludf.DUMMYFUNCTION("""COMPUTED_VALUE"""),"JZ") -> JZ | F17: =IFERROR(__xludf.DUMMYFUNCTION("""COMPUTED_VALUE"""),"VP") -> VP | G17: =IFERROR(__xludf.DUMMYFUNCTION("""COMPUTED_VALUE"""),"email") -> email | H17: =IFERROR(__xludf.DUMMYFUNCTION("""COMPUTED_VALUE"""),123.0) -> 123 | I17: =IFERROR(__xludf.DUMMYFUNCTION("""COMPUTED_VALUE"""),"Hourly") -> Hourly | J17: =IFERROR(__xludf.DUMMYFUNCTION("""COMPUTED_VALUE"""),45896.0) -> 45896 | K17: =IFERROR(__xludf.DUMMYFUNCTION("""COMPUTED_VALUE"""),"Finance") -> Finance | L17: =IFERROR(__xludf.DUMMYFUNCTION("""COMPUTED_VALUE"""),44.0) -> 44 | M17: =IFERROR(__xludf.DUMMYFUNCTION("""COMPUTED_VALUE"""),"Jane Doe") -> Jane Doe | N17: =IFERROR(__xludf.DUMMYFUNCTION("""COMPUTED_VALUE"""),"Vishal.srikanth@team-group.com") -> Vishal.srikanth@team-group.com | O17: =IFERROR(__xludf.DUMMYFUNCTION("""COMPUTED_VALUE"""),"Yes") -> Yes | P17: =IFERROR(__xludf.DUMMYFUNCTION("""COMPUTED_VALUE"""),"Yes") -> Yes | Q17: =IFERROR(__xludf.DUMMYFUNCTION("""COMPUTED_VALUE"""),"Yes") -> Yes | R17: =IFERROR(__xludf.DUMMYFUNCTION("""COMPUTED_VALUE"""),"Yes") -> Yes | S17: =IFERROR(__xludf.DUMMYFUNCTION("""COMPUTED_VALUE"""),"Yes") -> Yes | T17: =IFERROR(__xludf.DUMMYFUNCTION("""COMPUTED_VALUE"""),"Yes") -> Yes | U17: =IFERROR(__xludf.DUMMYFUNCTION("""COMPUTED_VALUE"""),"Yes") -> Yes | V17: =IFERROR(__xludf.DUMMYFUNCTION("""COMPUTED_VALUE"""),"Yes") -> Yes | ... AI17: =IFERROR(__xludf.DUMMYFUNCTION("""COMPUTED_VALUE"""),"Yes") -> Yes
A18: =IFERROR(__xludf.DUMMYFUNCTION("""COMPUTED_VALUE"""),2.50806004E8) -> 250806004 | B18: =IFERROR(__xludf.DUMMYFUNCTION("""COMPUTED_VALUE"""),"John") -> John | C18: =IFERROR(__xludf.DUMMYFUNCTION("""COMPUTED_VALUE"""),"JD") -> JD | D18: =IFERROR(__xludf.DUMMYFUNCTION("""COMPUTED_VALUE"""),"Doe") -> Doe | E18: =IFERROR(__xludf.DUMMYFUNCTION("""COMPUTED_VALUE"""),"JD") -> JD | F18: =IFERROR(__xludf.DUMMYFUNCTION("""COMPUTED_VALUE"""),"VP") -> VP | G18: =IFERROR(__xludf.DUMMYFUNCTION("""COMPUTED_VALUE"""),"email") -> email | I18: =IFERROR(__xludf.DUMMYFUNCTION("""COMPUTED_VALUE"""),"Hourly") -> Hourly | J18: =IFERROR(__xludf.DUMMYFUNCTION("""COMPUTED_VALUE"""),45889.0) -> 45889 | K18: =IFERROR(__xludf.DUMMYFUNCTION("""COMPUTED_VALUE"""),"GM Oshawa Assembly") -> GM Oshawa Assembly | L18: =IFERROR(__xludf.DUMMYFUNCTION("""COMPUTED_VALUE"""),135.0) -> 135 | M18: =IFERROR(__xludf.DUMMYFUNCTION("""COMPUTED_VALUE"""),"Jane Doe") -> Jane Doe | N18: =IFERROR(__xludf.DUMMYFUNCTION("""COMPUTED_VALUE"""),"Vishal.srikanth@team-group.com") -> Vishal.srikanth@team-group.com | O18: =IFERROR(__xludf.DUMMYFUNCTION("""COMPUTED_VALUE"""),"Yes") -> Yes | P18: =IFERROR(__xludf.DUMMYFUNCTION("""COMPUTED_VALUE"""),"No") -> No | Q18: =IFERROR(__xludf.DUMMYFUNCTION("""COMPUTED_VALUE"""),"No") -> No | R18: =IFERROR(__xludf.DUMMYFUNCTION("""COMPUTED_VALUE"""),"No") -> No | S18: =IFERROR(__xludf.DUMMYFUNCTION("""COMPUTED_VALUE"""),"Yes") -> Yes | T18: =IFERROR(__xludf.DUMMYFUNCTION("""COMPUTED_VALUE"""),"No") -> No | U18: =IFERROR(__xludf.DUMMYFUNCTION("""COMPUTED_VALUE"""),"Yes") -> Yes | V18: =IFERROR(__xludf.DUMMYFUNCTION("""COMPUTED_VALUE"""),"No") -> No | W18: =IFERROR(__xludf.DUMMYFUNCTION("""COMPUTED_VALUE"""),"Yes") -> Yes | X18: =IFERROR(__xludf.DUMMYFUNCTION("""COMPUTED_VALUE"""),"No") -> No | Y18: =IFERROR(__xludf.DUMMYFUNCTION("""COMPUTED_VALUE"""),"No") -> No | Z18: =IFERROR(__xludf.DUMMYFUNCTION("""COMPUTED_VALUE"""),"No") -> No | AA18: =IFERROR(__xludf.DUMMYFUNCTION("""COMPUTED_VALUE"""),"No") -> No | AB18: =IFERROR(__xludf.DUMMYFUNCTION("""COMPUTED_VALUE"""),"No") -> No | AC18: =IFERROR(__xludf.DUMMYFUNCTION("""COMPUTED_VALUE"""),"No") -> No | AD18: =IFERROR(__xludf.DUMMYFUNCTION("""COMPUTED_VALUE"""),"No") -> No | AE18: =IFERROR(__xludf.DUMMYFUNCTION("""COMPUTED_VALUE"""),"Yes") -> Yes | AF18: =IFERROR(__xludf.DUMMYFUNCTION("""COMPUTED_VALUE"""),"No") -> No | AG18: =IFERROR(__xludf.DUMMYFUNCTION("""COMPUTED_VALUE"""),"No") -> No | AH18: =IFERROR(__xludf.DUMMYFUNCTION("""COMPUTED_VALUE"""),"Yes") -> Yes | AI18: =IFERROR(__xludf.DUMMYFUNCTION("""COMPUTED_VALUE"""),"No") -> No
A19: =IFERROR(__xludf.DUMMYFUNCTION("""COMPUTED_VALUE"""),2.50807001E8) -> 250807001 | B19: =IFERROR(__xludf.DUMMYFUNCTION("""COMPUTED_VALUE"""),"John") -> John | C19: =IFERROR(__xludf.DUMMYFUNCTION("""COMPUTED_VALUE"""),"JD") -> JD | D19: =IFERROR(__xludf.DUMMYFUNCTION("""COMPUTED_VALUE"""),"Doe") -> Doe | E19: =IFERROR(__xludf.DUMMYFUNCTION("""COMPUTED_VALUE"""),"JD") -> JD | F19: =IFERROR(__xludf.DUMMYFUNCTION("""COMPUTED_VALUE"""),"VP") -> VP | G19: =IFERROR(__xludf.DUMMYFUNCTION("""COMPUTED_VALUE"""),"email") -> email | H19: =IFERROR(__xludf.DUMMYFUNCTION("""COMPUTED_VALUE"""),123.0) -> 123 | I19: =IFERROR(__xludf.DUMMYFUNCTION("""COMPUTED_VALUE"""),"Hourly") -> Hourly | J19: =IFERROR(__xludf.DUMMYFUNCTION("""COMPUTED_VALUE"""),45877.0) -> 45877 | K19: =IFERROR(__xludf.DUMMYFUNCTION("""COMPUTED_VALUE"""),"Decostar Industries") -> Decostar Industries | L19: =IFERROR(__xludf.DUMMYFUNCTION("""COMPUTED_VALUE"""),132.0) -> 132 | M19: =IFERROR(__xludf.DUMMYFUNCTION("""COMPUTED_VALUE"""),"Jane Doe") -> Jane Doe | N19: =IFERROR(__xludf.DUMMYFUNCTION("""COMPUTED_VALUE"""),"Vishal.srikanth@team-group.com") -> Vishal.srikanth@team-group.com | O19: =IFERROR(__xludf.DUMMYFUNCTION("""COMPUTED_VALUE"""),"Yes") -> Yes | P19: =IFERROR(__xludf.DUMMYFUNCTION("""COMPUTED_VALUE"""),"Yes") -> Yes | Q19: =IFERROR(__xludf.DUMMYFUNCTION("""COMPUTED_VALUE"""),"Yes") -> Yes | R19: =IFERROR(__xludf.DUMMYFUNCTION("""COMPUTED_VALUE"""),"Yes") -> Yes | S19: =IFERROR(__xludf.DUMMYFUNCTION("""COMPUTED_VALUE"""),"Yes") -> Yes | T19: =IFERROR(__xludf.DUMMYFUNCTION("""COMPUTED_VALUE"""),"Yes") -> Yes | U19: =IFERROR(__xludf.DUMMYFUNCTION("""COMPUTED_VALUE"""),"Yes") -> Yes | V19: =IFERROR(__xludf.DUMMYFUNCTION("""COMPUTED_VALUE"""),"Yes") -> Yes | ... AI19: =IFERROR(__xludf.DUMMYFUNCTION("""COMPUTED_VALUE"""),"Yes") -> Yes
A20: =IFERROR(__xludf.DUMMYFUNCTION("""COMPUTED_VALUE"""),2.50807002E8) -> 250807002 | B20: =IFERROR(__xludf.DUMMYFUNCTION("""COMPUTED_VALUE"""),"John") -> John | C20: =IFERROR(__xludf.DUMMYFUNCTION("""COMPUTED_VALUE"""),"JD") -> JD | D20: =IFERROR(__xludf.DUMMYFUNCTION("""COMPUTED_VALUE"""),"Doe") -> Doe | E20: =IFERROR(__xludf.DUMMYFUNCTION("""COMPUTED_VALUE"""),"JD") -> JD | F20: =IFERROR(__xludf.DUMMYFUNCTION("""COMPUTED_VALUE"""),"VP") -> VP | G20: =IFERROR(__xludf.DUMMYFUNCTION("""COMPUTED_VALUE"""),"email") -> email | H20: =IFERROR(__xludf.DUMMYFUNCTION("""COMPUTED_VALUE"""),123.0) -> 123 | I20: =IFERROR(__xludf.DUMMYFUNCTION("""COMPUTED_VALUE"""),"Salary") -> Salary | J20: =IFERROR(__xludf.DUMMYFUNCTION("""COMPUTED_VALUE"""),45881.0) -> 45881 | K20: =IFERROR(__xludf.DUMMYFUNCTION("""COMPUTED_VALUE"""),"BMW Spartanburg Assembly") -> BMW Spartanburg Assembly | L20: =IFERROR(__xludf.DUMMYFUNCTION("""COMPUTED_VALUE"""),120.0) -> 120 | M20: =IFERROR(__xludf.DUMMYFUNCTION("""COMPUTED_VALUE"""),"Jane Doe") -> Jane Doe | N20: =IFERROR(__xludf.DUMMYFUNCTION("""COMPUTED_VALUE"""),"Vishal.srikanth@team-group.com") -> Vishal.srikanth@team-group.com | O20: =IFERROR(__xludf.DUMMYFUNCTION("""COMPUTED_VALUE"""),"Yes") -> Yes | P20: =IFERROR(__xludf.DUMMYFUNCTION("""COMPUTED_VALUE"""),"Yes") -> Yes | Q20: =IFERROR(__xludf.DUMMYFUNCTION("""COMPUTED_VALUE"""),"Yes") -> Yes | R20: =IFERROR(__xludf.DUMMYFUNCTION("""COMPUTED_VALUE"""),"Yes") -> Yes | S20: =IFERROR(__xludf.DUMMYFUNCTION("""COMPUTED_VALUE"""),"Yes") -> Yes | T20: =IFERROR(__xludf.DUMMYFUNCTION("""COMPUTED_VALUE"""),"Yes") -> Yes | U20: =IFERROR(__xludf.DUMMYFUNCTION("""COMPUTED_VALUE"""),"Yes") -> Yes | V20: =IFERROR(__xludf.DUMMYFUNCTION("""COMPUTED_VALUE"""),"Yes") -> Yes | ... AI20: =IFERROR(__xludf.DUMMYFUNCTION("""COMPUTED_VALUE"""),"Yes") -> Yes
A21: =IFERROR(__xludf.DUMMYFUNCTION("""COMPUTED_VALUE"""),2.50808007E8) -> 250808007 | B21: =IFERROR(__xludf.DUMMYFUNCTION("""COMPUTED_VALUE"""),"John") -> John | C21: =IFERROR(__xludf.DUMMYFUNCTION("""COMPUTED_VALUE"""),"JD") -> JD | D21: =IFERROR(__xludf.DUMMYFUNCTION("""COMPUTED_VALUE"""),"Doe") -> Doe | E21: =IFERROR(__xludf.DUMMYFUNCTION("""COMPUTED_VALUE"""),"JD") -> JD | F21: =IFERROR(__xludf.DUMMYFUNCTION("""COMPUTED_VALUE"""),"VP") -> VP | G21: =IFERROR(__xludf.DUMMYFUNCTION("""COMPUTED_VALUE"""),"email") -> email | H21: =IFERROR(__xludf.DUMMYFUNCTION("""COMPUTED_VALUE"""),123.0) -> 123 | I21: =IFERROR(__xludf.DUMMYFUNCTION("""COMPUTED_VALUE"""),"Salary") -> Salary | J21: =IFERROR(__xludf.DUMMYFUNCTION("""COMPUTED_VALUE"""),45896.0) -> 45896 | K21: =IFERROR(__xludf.DUMMYFUNCTION("""COMPUTED_VALUE"""),"Burns MacDonald") -> Burns MacDonald | L21: =IFERROR(__xludf.DUMMYFUNCTION("""COMPUTED_VALUE"""),"TC014") -> TC014 | M21: =IFERROR(__xludf.DUMMYFUNCTION("""COMPUTED_VALUE"""),"Jane Doe") -> Jane Doe | N21: =IFERROR(__xludf.DUMMYFUNCTION("""COMPUTED_VALUE"""),"Vishal.srikanth@team-group.com") -> Vishal.srikanth@team-group.com | O21: =IFERROR(__xludf.DUMMYFUNCTION("""COMPUTED_VALUE"""),"Yes") -> Yes | P21: =IFERROR(__xludf.DUMMYFUNCTION("""COMPUTED_VALUE"""),"Yes") -> Yes | Q21: =IFERROR(__xludf.DUMMYFUNCTION("""COMPUTED_VALUE"""),"Yes") -> Yes | R21: =IFERROR(__xludf.DUMMYFUNCTION("""COMPUTED_VALUE"""),"No") -> No | S21: =IFERROR(__xludf.DUMMYFUNCTION("""COMPUTED_VALUE"""),"No") -> No | T21: =IFERROR(__xludf.DUMMYFUNCTION("""COMPUTED_VALUE"""),"No") -> No | U21: =IFERROR(__xludf.DUMMYFUNCTION("""COMPUTED_VALUE"""),"No") -> No | V21: =IFERROR(__xludf.DUMMYFUNCTION("""COMPUTED_VALUE"""),"No") -> No | W21: =IFERROR(__xludf.DUMMYFUNCTION("""COMPUTED_VALUE"""),"Yes") -> Yes | X21: =IFERROR(__xludf.DUMMYFUNCTION("""COMPUTED_VALUE"""),"No") -> No | Y21: =IFERROR(__xludf.DUMMYFUNCTION("""COMPUTED_VALUE"""),"No") -> No | Z21: =IFERROR(__xludf.DUMMYFUNCTION("""COMPUTED_VALUE"""),"No") -> No | AA21: =IFERROR(__xludf.DUMMYFUNCTION("""COMPUTED_VALUE"""),"No") -> No | AC21: =IFERROR(__xludf.DUMMYFUNCTION("""COMPUTED_VALUE"""),"No") -> No | AD21: =IFERROR(__xludf.DUMMYFUNCTION("""COMPUTED_VALUE"""),"No") -> No | AE21: =IFERROR(__xludf.DUMMYFUNCTION("""COMPUTED_VALUE"""),"No") -> No | AF21: =IFERROR(__xludf.DUMMYFUNCTION("""COMPUTED_VALUE"""),"No") -> No | AG21: =IFERROR(__xludf.DUMMYFUNCTION("""COMPUTED_VALUE"""),"Yes") -> Yes | AH21: =IFERROR(__xludf.DUMMYFUNCTION("""COMPUTED_VALUE"""),"No") -> No
A22: =IFERROR(__xludf.DUMMYFUNCTION("""COMPUTED_VALUE"""),2.5080801E8) -> 250808010 | B22: =IFERROR(__xludf.DUMMYFUNCTION("""COMPUTED_VALUE"""),"John") -> John | C22: =IFERROR(__xludf.DUMMYFUNCTION("""COMPUTED_VALUE"""),"JD") -> JD | D22: =IFERROR(__xludf.DUMMYFUNCTION("""COMPUTED_VALUE"""),"Doe") -> Doe | E22: =IFERROR(__xludf.DUMMYFUNCTION("""COMPUTED_VALUE"""),"JD") -> JD | F22: =IFERROR(__xludf.DUMMYFUNCTION("""COMPUTED_VALUE"""),"VP") -> VP | G22: =IFERROR(__xludf.DUMMYFUNCTION("""COMPUTED_VALUE"""),"email") -> email | I22: =IFERROR(__xludf.DUMMYFUNCTION("""COMPUTED_VALUE"""),"Salary") -> Salary | J22: =IFERROR(__xludf.DUMMYFUNCTION("""COMPUTED_VALUE"""),45897.0) -> 45897 | K22: =IFERROR(__xludf.DUMMYFUNCTION("""COMPUTED_VALUE"""),"Chrysler Brampton GSO") -> Chrysler Brampton GSO | L22: =IFERROR(__xludf.DUMMYFUNCTION("""COMPUTED_VALUE"""),"TC800") -> TC800 | O22: =IFERROR(__xludf.DUMMYFUNCTION("""COMPUTED_VALUE"""),"Yes") -> Yes | P22: =IFERROR(__xludf.DUMMYFUNCTION("""COMPUTED_VALUE"""),"Yes") -> Yes | Q22: =IFERROR(__xludf.DUMMYFUNCTION("""COMPUTED_VALUE"""),"No") -> No | R22: =IFERROR(__xludf.DUMMYFUNCTION("""COMPUTED_VALUE"""),"No") -> No | S22: =IFERROR(__xludf.DUMMYFUNCTION("""COMPUTED_VALUE"""),"No") -> No | T22: =IFERROR(__xludf.DUMMYFUNCTION("""COMPUTED_VALUE"""),"No") -> No | U22: =IFERROR(__xludf.DUMMYFUNCTION("""COMPUTED_VALUE"""),"No") -> No | V22: =IFERROR(__xludf.DUMMYFUNCTION("""COMPUTED_VALUE"""),"No") -> No | W22: =IFERROR(__xludf.DUMMYFUNCTION("""COMPUTED_VALUE"""),"No") -> No | X22: =IFERROR(__xludf.DUMMYFUNCTION("""COMPUTED_VALUE"""),"No") -> No | ... AA22: =IFERROR(__xludf.DUMMYFUNCTION("""COMPUTED_VALUE"""),"No") -> No | AC22: =IFERROR(__xludf.DUMMYFUNCTION("""COMPUTED_VALUE"""),"No") -> No | AD22: =IFERROR(__xludf.DUMMYFUNCTION("""COMPUTED_VALUE"""),"No") -> No | AE22: =IFERROR(__xludf.DUMMYFUNCTION("""COMPUTED_VALUE"""),"Yes") -> Yes | AF22: =IFERROR(__xludf.DUMMYFUNCTION("""COMPUTED_VALUE"""),"No") -> No | AG22: =IFERROR(__xludf.DUMMYFUNCTION("""COMPUTED_VALUE"""),"No") -> No | AH22: =IFERROR(__xludf.DUMMYFUNCTION("""COMPUTED_VALUE"""),"No") -> No
A23: =IFERROR(__xludf.DUMMYFUNCTION("""COMPUTED_VALUE"""),2.50808011E8) -> 250808011 | G23: =IFERROR(__xludf.DUMMYFUNCTION("""COMPUTED_VALUE"""),"email") -> email | I23: =IFERROR(__xludf.DUMMYFUNCTION("""COMPUTED_VALUE"""),"Salary") -> Salary | J23: =IFERROR(__xludf.DUMMYFUNCTION("""COMPUTED_VALUE"""),45896.0) -> 45896 | K23: =IFERROR(__xludf.DUMMYFUNCTION("""COMPUTED_VALUE"""),"Toyota Burnaston") -> Toyota Burnaston | L23: =IFERROR(__xludf.DUMMYFUNCTION("""COMPUTED_VALUE"""),"UP168") -> UP168 | M23: =IFERROR(__xludf.DUMMYFUNCTION("""COMPUTED_VALUE"""),"Jane Doe") -> Jane Doe | N23: =IFERROR(__xludf.DUMMYFUNCTION("""COMPUTED_VALUE"""),"Vishal.srikanth@team-group.com") -> Vishal.srikanth@team-group.com | O23: =IFERROR(__xludf.DUMMYFUNCTION("""COMPUTED_VALUE"""),"Yes") -> Yes | P23: =IFERROR(__xludf.DUMMYFUNCTION("""COMPUTED_VALUE"""),"Yes") -> Yes | Q23: =IFERROR(__xludf.DUMMYFUNCTION("""COMPUTED_VALUE"""),"No") -> No | R23: =IFERROR(__xludf.DUMMYFUNCTION("""COMPUTED_VALUE"""),"No") -> No | S23: =IFERROR(__xludf.DUMMYFUNCTION("""COMPUTED_VALUE"""),"No") -> No | T23: =IFERROR(__xludf.DUMMYFUNCTION("""COMPUTED_VALUE"""),"No") -> No | U23: =IFERROR(__xludf.DUMMYFUNCTION("""COMPUTED_VALUE"""),"No") -> No | V23: =IFERROR(__xludf.DUMMYFUNCTION("""COMPUTED_VALUE"""),"No") -> No | W23: =IFERROR(__xludf.DUMMYFUNCTION("""COMPUTED_VALUE"""),"No") -> No | X23: =IFERROR(__xludf.DUMMYFUNCTION("""COMPUTED_VALUE"""),"No") -> No | ... AA23: =IFERROR(__xludf.DUMMYFUNCTION("""COMPUTED_VALUE"""),"No") -> No | AC23: =IFERROR(__xludf.DUMMYFUNCTION("""COMPUTED_VALUE"""),"No") -> No | AD23: =IFERROR(__xludf.DUMMYFUNCTION("""COMPUTED_VALUE"""),"No") -> No | AE23: =IFERROR(__xludf.DUMMYFUNCTION("""COMPUTED_VALUE"""),"Yes") -> Yes | AF23: =IFERROR(__xludf.DUMMYFUNCTION("""COMPUTED_VALUE"""),"No") -> No | AG23: =IFERROR(__xludf.DUMMYFUNCTION("""COMPUTED_VALUE"""),"No") -> No | AH23: =IFERROR(__xludf.DUMMYFUNCTION("""COMPUTED_VALUE"""),"No") -> No
A24: =IFERROR(__xludf.DUMMYFUNCTION("""COMPUTED_VALUE"""),2.50811001E8) -> 250811001 | B24: =IFERROR(__xludf.DUMMYFUNCTION("""COMPUTED_VALUE"""),"John") -> John | C24: =IFERROR(__xludf.DUMMYFUNCTION("""COMPUTED_VALUE"""),"JD") -> JD | D24: =IFERROR(__xludf.DUMMYFUNCTION("""COMPUTED_VALUE"""),"Doe") -> Doe | E24: =IFERROR(__xludf.DUMMYFUNCTION("""COMPUTED_VALUE"""),"JD") -> JD | F24: =IFERROR(__xludf.DUMMYFUNCTION("""COMPUTED_VALUE"""),"VP") -> VP | I24: =IFERROR(__xludf.DUMMYFUNCTION("""COMPUTED_VALUE"""),"Hourly") -> Hourly | J24: =IFERROR(__xludf.DUMMYFUNCTION("""COMPUTED_VALUE"""),45888.0) -> 45888 | K24: =IFERROR(__xludf.DUMMYFUNCTION("""COMPUTED_VALUE"""),"GM Oshawa PPS") -> GM Oshawa PPS | L24: =IFERROR(__xludf.DUMMYFUNCTION("""COMPUTED_VALUE"""),"TW010") -> TW010 | M24: =IFERROR(__xludf.DUMMYFUNCTION("""COMPUTED_VALUE"""),"Jane Doe") -> Jane Doe | N24: =IFERROR(__xludf.DUMMYFUNCTION("""COMPUTED_VALUE"""),"Vishal.srikanth@team-group.com") -> Vishal.srikanth@team-group.com | O24: =IFERROR(__xludf.DUMMYFUNCTION("""COMPUTED_VALUE"""),"No") -> No | P24: =IFERROR(__xludf.DUMMYFUNCTION("""COMPUTED_VALUE"""),"No") -> No | Q24: =IFERROR(__xludf.DUMMYFUNCTION("""COMPUTED_VALUE"""),"No") -> No | R24: =IFERROR(__xludf.DUMMYFUNCTION("""COMPUTED_VALUE"""),"No") -> No | S24: =IFERROR(__xludf.DUMMYFUNCTION("""COMPUTED_VALUE"""),"No") -> No | T24: =IFERROR(__xludf.DUMMYFUNCTION("""COMPUTED_VALUE"""),"No") -> No | U24: =IFERROR(__xludf.DUMMYFUNCTION("""COMPUTED_VALUE"""),"No") -> No | V24: =IFERROR(__xludf.DUMMYFUNCTION("""COMPUTED_VALUE"""),"No") -> No | ... AA24: =IFERROR(__xludf.DUMMYFUNCTION("""COMPUTED_VALUE"""),"No") -> No | AC24: =IFERROR(__xludf.DUMMYFUNCTION("""COMPUTED_VALUE"""),"No") -> No | AD24: =IFERROR(__xludf.DUMMYFUNCTION("""COMPUTED_VALUE"""),"Yes") -> Yes | AE24: =IFERROR(__xludf.DUMMYFUNCTION("""COMPUTED_VALUE"""),"Yes") -> Yes | AF24: =IFERROR(__xludf.DUMMYFUNCTION("""COMPUTED_VALUE"""),"No") -> No | AG24: =IFERROR(__xludf.DUMMYFUNCTION("""COMPUTED_VALUE"""),"No") -> No | AH24: =IFERROR(__xludf.DUMMYFUNCTION("""COMPUTED_VALUE"""),"No") -> No
A25: =IFERROR(__xludf.DUMMYFUNCTION("""COMPUTED_VALUE"""),2.50811003E8) -> 250811003 | B25: =IFERROR(__xludf.DUMMYFUNCTION("""COMPUTED_VALUE"""),"Angie") -> Angie | C25: =IFERROR(__xludf.DUMMYFUNCTION("""COMPUTED_VALUE"""),"O") -> O | D25: =IFERROR(__xludf.DUMMYFUNCTION("""COMPUTED_VALUE"""),"O'Plasty") -> O'Plasty | F25: =IFERROR(__xludf.DUMMYFUNCTION("""COMPUTED_VALUE"""),"VP") -> VP | G25: =IFERROR(__xludf.DUMMYFUNCTION("""COMPUTED_VALUE"""),"email") -> email | I25: =IFERROR(__xludf.DUMMYFUNCTION("""COMPUTED_VALUE"""),"Salary") -> Salary | K25: =IFERROR(__xludf.DUMMYFUNCTION("""COMPUTED_VALUE"""),"ArcelorMittal") -> ArcelorMittal | L25: =IFERROR(__xludf.DUMMYFUNCTION("""COMPUTED_VALUE"""),"TC001") -> TC001 | O25: =IFERROR(__xludf.DUMMYFUNCTION("""COMPUTED_VALUE"""),"Yes") -> Yes | P25: =IFERROR(__xludf.DUMMYFUNCTION("""COMPUTED_VALUE"""),"No") -> No | Q25: =IFERROR(__xludf.DUMMYFUNCTION("""COMPUTED_VALUE"""),"No") -> No | R25: =IFERROR(__xludf.DUMMYFUNCTION("""COMPUTED_VALUE"""),"No") -> No | S25: =IFERROR(__xludf.DUMMYFUNCTION("""COMPUTED_VALUE"""),"Yes") -> Yes | T25: =IFERROR(__xludf.DUMMYFUNCTION("""COMPUTED_VALUE"""),"Yes") -> Yes | U25: =IFERROR(__xludf.DUMMYFUNCTION("""COMPUTED_VALUE"""),"No") -> No | V25: =IFERROR(__xludf.DUMMYFUNCTION("""COMPUTED_VALUE"""),"No") -> No | W25: =IFERROR(__xludf.DUMMYFUNCTION("""COMPUTED_VALUE"""),"No") -> No | X25: =IFERROR(__xludf.DUMMYFUNCTION("""COMPUTED_VALUE"""),"No") -> No | Y25: =IFERROR(__xludf.DUMMYFUNCTION("""COMPUTED_VALUE"""),"No") -> No | Z25: =IFERROR(__xludf.DUMMYFUNCTION("""COMPUTED_VALUE"""),"No") -> No | AA25: =IFERROR(__xludf.DUMMYFUNCTION("""COMPUTED_VALUE"""),"No") -> No | AC25: =IFERROR(__xludf.DUMMYFUNCTION("""COMPUTED_VALUE"""),"No") -> No | AD25: =IFERROR(__xludf.DUMMYFUNCTION("""COMPUTED_VALUE"""),"No") -> No | AE25: =IFERROR(__xludf.DUMMYFUNCTION("""COMPUTED_VALUE"""),"Yes") -> Yes | AF25: =IFERROR(__xludf.DUMMYFUNCTION("""COMPUTED_VALUE"""),"No") -> No | AG25: =IFERROR(__xludf.DUMMYFUNCTION("""COMPUTED_VALUE"""),"No") -> No | AH25: =IFERROR(__xludf.DUMMYFUNCTION("""COMPUTED_VALUE"""),"No") -> No
A26: =IFERROR(__xludf.DUMMYFUNCTION("""COMPUTED_VALUE"""),2.50811004E8) -> 250811004 | B26: =IFERROR(__xludf.DUMMYFUNCTION("""COMPUTED_VALUE"""),"John") -> John | D26: =IFERROR(__xludf.DUMMYFUNCTION("""COMPUTED_VALUE"""),"O'Plasty") -> O'Plasty | F26: =IFERROR(__xludf.DUMMYFUNCTION("""COMPUTED_VALUE"""),"Director") -> Director | G26: =IFERROR(__xludf.DUMMYFUNCTION("""COMPUTED_VALUE"""),"email") -> email | I26: =IFERROR(__xludf.DUMMYFUNCTION("""COMPUTED_VALUE"""),"Salary") -> Salary | J26: =IFERROR(__xludf.DUMMYFUNCTION("""COMPUTED_VALUE"""),45897.0) -> 45897 | K26: =IFERROR(__xludf.DUMMYFUNCTION("""COMPUTED_VALUE"""),"Chrysler Brampton") -> Chrysler Brampton | L26: =IFERROR(__xludf.DUMMYFUNCTION("""COMPUTED_VALUE"""),"TC700") -> TC700 | O26: =IFERROR(__xludf.DUMMYFUNCTION("""COMPUTED_VALUE"""),"Yes") -> Yes | P26: =IFERROR(__xludf.DUMMYFUNCTION("""COMPUTED_VALUE"""),"No") -> No | Q26: =IFERROR(__xludf.DUMMYFUNCTION("""COMPUTED_VALUE"""),"No") -> No | R26: =IFERROR(__xludf.DUMMYFUNCTION("""COMPUTED_VALUE"""),"No") -> No | S26: =IFERROR(__xludf.DUMMYFUNCTION("""COMPUTED_VALUE"""),"No") -> No | T26: =IFERROR(__xludf.DUMMYFUNCTION("""COMPUTED_VALUE"""),"No") -> No | U26: =IFERROR(__xludf.DUMMYFUNCTION("""COMPUTED_VALUE"""),"No") -> No | V26: =IFERROR(__xludf.DUMMYFUNCTION("""COMPUTED_VALUE"""),"No") -> No | W26: =IFERROR(__xludf.DUMMYFUNCTION("""COMPUTED_VALUE"""),"No") -> No | ... AA26: =IFERROR(__xludf.DUMMYFUNCTION("""COMPUTED_VALUE"""),"No") -> No | AC26: =IFERROR(__xludf.DUMMYFUNCTION("""COMPUTED_VALUE"""),"No") -> No | AD26: =IFERROR(__xludf.DUMMYFUNCTION("""COMPUTED_VALUE"""),"No") -> No | AE26: =IFERROR(__xludf.DUMMYFUNCTION("""COMPUTED_VALUE"""),"Yes") -> Yes | AF26: =IFERROR(__xludf.DUMMYFUNCTION("""COMPUTED_VALUE"""),"No") -> No | AG26: =IFERROR(__xludf.DUMMYFUNCTION("""COMPUTED_VALUE"""),"No") -> No | AH26: =IFERROR(__xludf.DUMMYFUNCTION("""COMPUTED_VALUE"""),"No") -> No
A27: =IFERROR(__xludf.DUMMYFUNCTION("""COMPUTED_VALUE"""),2.50812004E8) -> 250812004 | B27: =IFERROR(__xludf.DUMMYFUNCTION("""COMPUTED_VALUE"""),"May ") -> May | C27: =IFERROR(__xludf.DUMMYFUNCTION("""COMPUTED_VALUE"""),"B") -> B | D27: =IFERROR(__xludf.DUMMYFUNCTION("""COMPUTED_VALUE"""),"Tomorrow") -> Tomorrow | F27: =IFERROR(__xludf.DUMMYFUNCTION("""COMPUTED_VALUE"""),"Director") -> Director | I27: =IFERROR(__xludf.DUMMYFUNCTION("""COMPUTED_VALUE"""),"Hourly") -> Hourly | J27: =IFERROR(__xludf.DUMMYFUNCTION("""COMPUTED_VALUE"""),45884.0) -> 45884 | K27: =IFERROR(__xludf.DUMMYFUNCTION("""COMPUTED_VALUE"""),"BBI Enterprises") -> BBI Enterprises | L27: =IFERROR(__xludf.DUMMYFUNCTION("""COMPUTED_VALUE"""),"TC009") -> TC009 | O27: =IFERROR(__xludf.DUMMYFUNCTION("""COMPUTED_VALUE"""),"No") -> No | P27: =IFERROR(__xludf.DUMMYFUNCTION("""COMPUTED_VALUE"""),"No") -> No | Q27: =IFERROR(__xludf.DUMMYFUNCTION("""COMPUTED_VALUE"""),"No") -> No | R27: =IFERROR(__xludf.DUMMYFUNCTION("""COMPUTED_VALUE"""),"No") -> No | S27: =IFERROR(__xludf.DUMMYFUNCTION("""COMPUTED_VALUE"""),"No") -> No | T27: =IFERROR(__xludf.DUMMYFUNCTION("""COMPUTED_VALUE"""),"No") -> No | U27: =IFERROR(__xludf.DUMMYFUNCTION("""COMPUTED_VALUE"""),"No") -> No | V27: =IFERROR(__xludf.DUMMYFUNCTION("""COMPUTED_VALUE"""),"No") -> No | ... AA27: =IFERROR(__xludf.DUMMYFUNCTION("""COMPUTED_VALUE"""),"No") -> No | AC27: =IFERROR(__xludf.DUMMYFUNCTION("""COMPUTED_VALUE"""),"No") -> No | AD27: =IFERROR(__xludf.DUMMYFUNCTION("""COMPUTED_VALUE"""),"No") -> No | AE27: =IFERROR(__xludf.DUMMYFUNCTION("""COMPUTED_VALUE"""),"Yes") -> Yes | AF27: =IFERROR(__xludf.DUMMYFUNCTION("""COMPUTED_VALUE"""),"No") -> No | AG27: =IFERROR(__xludf.DUMMYFUNCTION("""COMPUTED_VALUE"""),"No") -> No | AH27: =IFERROR(__xludf.DUMMYFUNCTION("""COMPUTED_VALUE"""),"No") -> No
A28: =IFERROR(__xludf.DUMMYFUNCTION("""COMPUTED_VALUE"""),2.50812005E8) -> 250812005 | B28: =IFERROR(__xludf.DUMMYFUNCTION("""COMPUTED_VALUE"""),"Angie") -> Angie | D28: =IFERROR(__xludf.DUMMYFUNCTION("""COMPUTED_VALUE"""),"O'Plasty") -> O'Plasty | I28: =IFERROR(__xludf.DUMMYFUNCTION("""COMPUTED_VALUE"""),"Hourly") -> Hourly | J28: =IFERROR(__xludf.DUMMYFUNCTION("""COMPUTED_VALUE"""),45888.0) -> 45888 | K28: =IFERROR(__xludf.DUMMYFUNCTION("""COMPUTED_VALUE"""),"PC Gaming") -> PC Gaming | L28: =IFERROR(__xludf.DUMMYFUNCTION("""COMPUTED_VALUE"""),"UC216") -> UC216 | M28: =IFERROR(__xludf.DUMMYFUNCTION("""COMPUTED_VALUE"""),"Jane Doe") -> Jane Doe | N28: =IFERROR(__xludf.DUMMYFUNCTION("""COMPUTED_VALUE"""),"Vishal.srikanth@team-group.com") -> Vishal.srikanth@team-group.com | O28: =IFERROR(__xludf.DUMMYFUNCTION("""COMPUTED_VALUE"""),"No") -> No | P28: =IFERROR(__xludf.DUMMYFUNCTION("""COMPUTED_VALUE"""),"No") -> No | Q28: =IFERROR(__xludf.DUMMYFUNCTION("""COMPUTED_VALUE"""),"No") -> No | R28: =IFERROR(__xludf.DUMMYFUNCTION("""COMPUTED_VALUE"""),"No") -> No | S28: =IFERROR(__xludf.DUMMYFUNCTION("""COMPUTED_VALUE"""),"No") -> No | T28: =IFERROR(__xludf.DUMMYFUNCTION("""COMPUTED_VALUE"""),"No") -> No | U28: =IFERROR(__xludf.DUMMYFUNCTION("""COMPUTED_VALUE"""),"No") -> No | V28: =IFERROR(__xludf.DUMMYFUNCTION("""COMPUTED_VALUE"""),"No") -> No | ... AA28: =IFERROR(__xludf.DUMMYFUNCTION("""COMPUTED_VALUE"""),"No") -> No | AC28: =IFERROR(__xludf.DUMMYFUNCTION("""COMPUTED_VALUE"""),"No") -> No | AD28: =IFERROR(__xludf.DUMMYFUNCTION("""COMPUTED_VALUE"""),"Yes") -> Yes | AE28: =IFERROR(__xludf.DUMMYFUNCTION("""COMPUTED_VALUE"""),"Yes") -> Yes | AF28: =IFERROR(__xludf.DUMMYFUNCTION("""COMPUTED_VALUE"""),"No") -> No | AG28: =IFERROR(__xludf.DUMMYFUNCTION("""COMPUTED_VALUE"""),"No") -> No | AH28: =IFERROR(__xludf.DUMMYFUNCTION("""COMPUTED_VALUE"""),"No") -> No
A29: =IFERROR(__xludf.DUMMYFUNCTION("""COMPUTED_VALUE"""),2.50812007E8) -> 250812007 | B29: =IFERROR(__xludf.DUMMYFUNCTION("""COMPUTED_VALUE"""),"John") -> John | D29: =IFERROR(__xludf.DUMMYFUNCTION("""COMPUTED_VALUE"""),"Athon") -> Athon | F29: =IFERROR(__xludf.DUMMYFUNCTION("""COMPUTED_VALUE"""),"Director") -> Director | G29: =IFERROR(__xludf.DUMMYFUNCTION("""COMPUTED_VALUE"""),"email") -> email | I29: =IFERROR(__xludf.DUMMYFUNCTION("""COMPUTED_VALUE"""),"Salary") -> Salary | J29: =IFERROR(__xludf.DUMMYFUNCTION("""COMPUTED_VALUE"""),45898.0) -> 45898 | K29: =IFERROR(__xludf.DUMMYFUNCTION("""COMPUTED_VALUE"""),"Ventra Group ") -> Ventra Group | L29: =IFERROR(__xludf.DUMMYFUNCTION("""COMPUTED_VALUE"""),"UP506") -> UP506 | M29: =IFERROR(__xludf.DUMMYFUNCTION("""COMPUTED_VALUE"""),"Jane Doe") -> Jane Doe | N29: =IFERROR(__xludf.DUMMYFUNCTION("""COMPUTED_VALUE"""),"Vishal.srikanth@team-group.com") -> Vishal.srikanth@team-group.com | O29: =IFERROR(__xludf.DUMMYFUNCTION("""COMPUTED_VALUE"""),"Yes") -> Yes | P29: =IFERROR(__xludf.DUMMYFUNCTION("""COMPUTED_VALUE"""),"No") -> No | Q29: =IFERROR(__xludf.DUMMYFUNCTION("""COMPUTED_VALUE"""),"Yes") -> Yes | R29: =IFERROR(__xludf.DUMMYFUNCTION("""COMPUTED_VALUE"""),"No") -> No | S29: =IFERROR(__xludf.DUMMYFUNCTION("""COMPUTED_VALUE"""),"No") -> No | T29: =IFERROR(__xludf.DUMMYFUNCTION("""COMPUTED_VALUE"""),"No") -> No | U29: =IFERROR(__xludf.DUMMYFUNCTION("""COMPUTED_VALUE"""),"No") -> No | V29: =IFERROR(__xludf.DUMMYFUNCTION("""COMPUTED_VALUE"""),"No") -> No | W29: =IFERROR(__xludf.DUMMYFUNCTION("""COMPUTED_VALUE"""),"Yes") -> Yes | X29: =IFERROR(__xludf.DUMMYFUNCTION("""COMPUTED_VALUE"""),"No") -> No | Y29: =IFERROR(__xludf.DUMMYFUNCTION("""COMPUTED_VALUE"""),"No") -> No | Z29: =IFERROR(__xludf.DUMMYFUNCTION("""COMPUTED_VALUE"""),"No") -> No | AA29: =IFERROR(__xludf.DUMMYFUNCTION("""COMPUTED_VALUE"""),"No") -> No | AC29: =IFERROR(__xludf.DUMMYFUNCTION("""COMPUTED_VALUE"""),"No") -> No | AD29: =IFERROR(__xludf.DUMMYFUNCTION("""COMPUTED_VALUE"""),"Yes") -> Yes | AE29: =IFERROR(__xludf.DUMMYFUNCTION("""COMPUTED_VALUE"""),"Yes") -> Yes | AF29: =IFERROR(__xludf.DUMMYFUNCTION("""COMPUTED_VALUE"""),"No") -> No | AG29: =IFERROR(__xludf.DUMMYFUNCTION("""COMPUTED_VALUE"""),"No") -> No | AH29: =IFERROR(__xludf.DUMMYFUNCTION("""COMPUTED_VALUE"""),"No") -> No
A30: =IFERROR(__xludf.DUMMYFUNCTION("""COMPUTED_VALUE"""),2.50812008E8) -> 250812008 | B30: =IFERROR(__xludf.DUMMYFUNCTION("""COMPUTED_VALUE"""),"May ") -> May | C30: =IFERROR(__xludf.DUMMYFUNCTION("""COMPUTED_VALUE"""),"B") -> B | D30: =IFERROR(__xludf.DUMMYFUNCTION("""COMPUTED_VALUE"""),"Tomorrow") -> Tomorrow | E30: =IFERROR(__xludf.DUMMYFUNCTION("""COMPUTED_VALUE"""),"B") -> B | F30: =IFERROR(__xludf.DUMMYFUNCTION("""COMPUTED_VALUE"""),"Director") -> Director | I30: =IFERROR(__xludf.DUMMYFUNCTION("""COMPUTED_VALUE"""),"Hourly") -> Hourly | J30: =IFERROR(__xludf.DUMMYFUNCTION("""COMPUTED_VALUE"""),45895.0) -> 45895 | K30: =IFERROR(__xludf.DUMMYFUNCTION("""COMPUTED_VALUE"""),"Bunge Canada") -> Bunge Canada | L30: =IFERROR(__xludf.DUMMYFUNCTION("""COMPUTED_VALUE"""),"TC013") -> TC013 | O30: =IFERROR(__xludf.DUMMYFUNCTION("""COMPUTED_VALUE"""),"No") -> No | P30: =IFERROR(__xludf.DUMMYFUNCTION("""COMPUTED_VALUE"""),"No") -> No | Q30: =IFERROR(__xludf.DUMMYFUNCTION("""COMPUTED_VALUE"""),"No") -> No | R30: =IFERROR(__xludf.DUMMYFUNCTION("""COMPUTED_VALUE"""),"No") -> No | S30: =IFERROR(__xludf.DUMMYFUNCTION("""COMPUTED_VALUE"""),"No") -> No | T30: =IFERROR(__xludf.DUMMYFUNCTION("""COMPUTED_VALUE"""),"No") -> No | U30: =IFERROR(__xludf.DUMMYFUNCTION("""COMPUTED_VALUE"""),"No") -> No | V30: =IFERROR(__xludf.DUMMYFUNCTION("""COMPUTED_VALUE"""),"No") -> No | ... AA30: =IFERROR(__xludf.DUMMYFUNCTION("""COMPUTED_VALUE"""),"No") -> No | AC30: =IFERROR(__xludf.DUMMYFUNCTION("""COMPUTED_VALUE"""),"No") -> No | AD30: =IFERROR(__xludf.DUMMYFUNCTION("""COMPUTED_VALUE"""),"Yes") -> Yes | AE30: =IFERROR(__xludf.DUMMYFUNCTION("""COMPUTED_VALUE"""),"No") -> No | AF30: =IFERROR(__xludf.DUMMYFUNCTION("""COMPUTED_VALUE"""),"No") -> No | AG30: =IFERROR(__xludf.DUMMYFUNCTION("""COMPUTED_VALUE"""),"No") -> No | AH30: =IFERROR(__xludf.DUMMYFUNCTION("""COMPUTED_VALUE"""),"No") -> No
A31: =IFERROR(__xludf.DUMMYFUNCTION("""COMPUTED_VALUE"""),2.50826001E8) -> 250826001 | B31: =IFERROR(__xludf.DUMMYFUNCTION("""COMPUTED_VALUE"""),"John") -> John | D31: =IFERROR(__xludf.DUMMYFUNCTION("""COMPUTED_VALUE"""),"Doe") -> Doe | E31: =IFERROR(__xludf.DUMMYFUNCTION("""COMPUTED_VALUE"""),"Johnny") -> Johnny | F31: =IFERROR(__xludf.DUMMYFUNCTION("""COMPUTED_VALUE"""),"Industrial Cleaner") -> Industrial Cleaner | I31: =IFERROR(__xludf.DUMMYFUNCTION("""COMPUTED_VALUE"""),"Hourly") -> Hourly | J31: =IFERROR(__xludf.DUMMYFUNCTION("""COMPUTED_VALUE"""),45896.0) -> 45896 | K31: =IFERROR(__xludf.DUMMYFUNCTION("""COMPUTED_VALUE"""),"Geely YuYao") -> Geely YuYao | L31: =IFERROR(__xludf.DUMMYFUNCTION("""COMPUTED_VALUE"""),"TR500") -> TR500 | M31: =IFERROR(__xludf.DUMMYFUNCTION("""COMPUTED_VALUE"""),"Mike Buday") -> Mike Buday | N31: =IFERROR(__xludf.DUMMYFUNCTION("""COMPUTED_VALUE"""),"Vishal.srikanth@team-group.com") -> Vishal.srikanth@team-group.com | O31: =IFERROR(__xludf.DUMMYFUNCTION("""COMPUTED_VALUE"""),"No") -> No | P31: =IFERROR(__xludf.DUMMYFUNCTION("""COMPUTED_VALUE"""),"No") -> No | Q31: =IFERROR(__xludf.DUMMYFUNCTION("""COMPUTED_VALUE"""),"No") -> No | R31: =IFERROR(__xludf.DUMMYFUNCTION("""COMPUTED_VALUE"""),"No") -> No | S31: =IFERROR(__xludf.DUMMYFUNCTION("""COMPUTED_VALUE"""),"No") -> No | T31: =IFERROR(__xludf.DUMMYFUNCTION("""COMPUTED_VALUE"""),"No") -> No | U31: =IFERROR(__xludf.DUMMYFUNCTION("""COMPUTED_VALUE"""),"No") -> No | V31: =IFERROR(__xludf.DUMMYFUNCTION("""COMPUTED_VALUE"""),"No") -> No | ... AA31: =IFERROR(__xludf.DUMMYFUNCTION("""COMPUTED_VALUE"""),"No") -> No | AC31: =IFERROR(__xludf.DUMMYFUNCTION("""COMPUTED_VALUE"""),"No") -> No | AD31: =IFERROR(__xludf.DUMMYFUNCTION("""COMPUTED_VALUE"""),"No") -> No | AE31: =IFERROR(__xludf.DUMMYFUNCTION("""COMPUTED_VALUE"""),"No") -> No | AF31: =IFERROR(__xludf.DUMMYFUNCTION("""COMPUTED_VALUE"""),"No") -> No | AG31: =IFERROR(__xludf.DUMMYFUNCTION("""COMPUTED_VALUE"""),"No") -> No | AH31: =IFERROR(__xludf.DUMMYFUNCTION("""COMPUTED_VALUE"""),"No") -> No
A32: =IFERROR(__xludf.DUMMYFUNCTION("""COMPUTED_VALUE"""),2.50826002E8) -> 250826002 | B32: =IFERROR(__xludf.DUMMYFUNCTION("""COMPUTED_VALUE"""),"John") -> John | D32: =IFERROR(__xludf.DUMMYFUNCTION("""COMPUTED_VALUE"""),"Doe") -> Doe | F32: =IFERROR(__xludf.DUMMYFUNCTION("""COMPUTED_VALUE"""),"Director") -> Director | G32: =IFERROR(__xludf.DUMMYFUNCTION("""COMPUTED_VALUE"""),"email") -> email | H32: =IFERROR(__xludf.DUMMYFUNCTION("""COMPUTED_VALUE"""),123.0) -> 123 | I32: =IFERROR(__xludf.DUMMYFUNCTION("""COMPUTED_VALUE"""),"Salary") -> Salary | J32: =IFERROR(__xludf.DUMMYFUNCTION("""COMPUTED_VALUE"""),45897.0) -> 45897 | K32: =IFERROR(__xludf.DUMMYFUNCTION("""COMPUTED_VALUE"""),"Geely YuYao") -> Geely YuYao | L32: =IFERROR(__xludf.DUMMYFUNCTION("""COMPUTED_VALUE"""),"TR500") -> TR500 | M32: =IFERROR(__xludf.DUMMYFUNCTION("""COMPUTED_VALUE"""),"Jane Doe") -> Jane Doe | N32: =IFERROR(__xludf.DUMMYFUNCTION("""COMPUTED_VALUE"""),"Vishal.srikanth@team-group.com") -> Vishal.srikanth@team-group.com | O32: =IFERROR(__xludf.DUMMYFUNCTION("""COMPUTED_VALUE"""),"Yes") -> Yes | P32: =IFERROR(__xludf.DUMMYFUNCTION("""COMPUTED_VALUE"""),"No") -> No | Q32: =IFERROR(__xludf.DUMMYFUNCTION("""COMPUTED_VALUE"""),"Yes") -> Yes | R32: =IFERROR(__xludf.DUMMYFUNCTION("""COMPUTED_VALUE"""),"Yes") -> Yes | S32: =IFERROR(__xludf.DUMMYFUNCTION("""COMPUTED_VALUE"""),"Yes") -> Yes | T32: =IFERROR(__xludf.DUMMYFUNCTION("""COMPUTED_VALUE"""),"Yes") -> Yes | U32: =IFERROR(__xludf.DUMMYFUNCTION("""COMPUTED_VALUE"""),"Yes") -> Yes | V32: =IFERROR(__xludf.DUMMYFUNCTION("""COMPUTED_VALUE"""),"Yes") -> Yes | W32: =IFERROR(__xludf.DUMMYFUNCTION("""COMPUTED_VALUE"""),"Yes") -> Yes | X32: =IFERROR(__xludf.DUMMYFUNCTION("""COMPUTED_VALUE"""),"Yes") -> Yes | Y32: =IFERROR(__xludf.DUMMYFUNCTION("""COMPUTED_VALUE"""),"No") -> No | Z32: =IFERROR(__xludf.DUMMYFUNCTION("""COMPUTED_VALUE"""),"No") -> No | AA32: =IFERROR(__xludf.DUMMYFUNCTION("""COMPUTED_VALUE"""),"Yes") -> Yes | AC32: =IFERROR(__xludf.DUMMYFUNCTION("""COMPUTED_VALUE"""),"No") -> No | AD32: =IFERROR(__xludf.DUMMYFUNCTION("""COMPUTED_VALUE"""),"No") -> No | AE32: =IFERROR(__xludf.DUMMYFUNCTION("""COMPUTED_VALUE"""),"No") -> No | AF32: =IFERROR(__xludf.DUMMYFUNCTION("""COMPUTED_VALUE"""),"No") -> No | AG32: =IFERROR(__xludf.DUMMYFUNCTION("""COMPUTED_VALUE"""),"Yes") -> Yes | AH32: =IFERROR(__xludf.DUMMYFUNCTION("""COMPUTED_VALUE"""),"No") -> No
A33: =IFERROR(__xludf.DUMMYFUNCTION("""COMPUTED_VALUE"""),2.50826003E8) -> 250826003 | B33: =IFERROR(__xludf.DUMMYFUNCTION("""COMPUTED_VALUE"""),"John") -> John | C33: =IFERROR(__xludf.DUMMYFUNCTION("""COMPUTED_VALUE"""),"JD") -> JD | D33: =IFERROR(__xludf.DUMMYFUNCTION("""COMPUTED_VALUE"""),"Doe") -> Doe | E33: =IFERROR(__xludf.DUMMYFUNCTION("""COMPUTED_VALUE"""),"Johnny") -> Johnny | F33: =IFERROR(__xludf.DUMMYFUNCTION("""COMPUTED_VALUE"""),"Director") -> Director | I33: =IFERROR(__xludf.DUMMYFUNCTION("""COMPUTED_VALUE"""),"Hourly") -> Hourly | J33: =IFERROR(__xludf.DUMMYFUNCTION("""COMPUTED_VALUE"""),45902.0) -> 45902 | K33: =IFERROR(__xludf.DUMMYFUNCTION("""COMPUTED_VALUE"""),"Detroit Edison ") -> Detroit Edison | L33: =IFERROR(__xludf.DUMMYFUNCTION("""COMPUTED_VALUE"""),"TJ197") -> TJ197 | M33: =IFERROR(__xludf.DUMMYFUNCTION("""COMPUTED_VALUE"""),"Jane Doe") -> Jane Doe | N33: =IFERROR(__xludf.DUMMYFUNCTION("""COMPUTED_VALUE"""),"Vishal.srikanth@team-group.com") -> Vishal.srikanth@team-group.com | O33: =IFERROR(__xludf.DUMMYFUNCTION("""COMPUTED_VALUE"""),"No") -> No | P33: =IFERROR(__xludf.DUMMYFUNCTION("""COMPUTED_VALUE"""),"No") -> No | Q33: =IFERROR(__xludf.DUMMYFUNCTION("""COMPUTED_VALUE"""),"No") -> No | R33: =IFERROR(__xludf.DUMMYFUNCTION("""COMPUTED_VALUE"""),"No") -> No | S33: =IFERROR(__xludf.DUMMYFUNCTION("""COMPUTED_VALUE"""),"No") -> No | T33: =IFERROR(__xludf.DUMMYFUNCTION("""COMPUTED_VALUE"""),"No") -> No | U33: =IFERROR(__xludf.DUMMYFUNCTION("""COMPUTED_VALUE"""),"No") -> No | V33: =IFERROR(__xludf.DUMMYFUNCTION("""COMPUTED_VALUE"""),"No") -> No | ... AA33: =IFERROR(__xludf.DUMMYFUNCTION("""COMPUTED_VALUE"""),"No") -> No | AC33: =IFERROR(__xludf.DUMMYFUNCTION("""COMPUTED_VALUE"""),"No") -> No | AD33: =IFERROR(__xludf.DUMMYFUNCTION("""COMPUTED_VALUE"""),"No") -> No | AE33: =IFERROR(__xludf.DUMMYFUNCTION("""COMPUTED_VALUE"""),"No") -> No | AF33: =IFERROR(__xludf.DUMMYFUNCTION("""COMPUTED_VALUE"""),"No") -> No | AG33: =IFERROR(__xludf.DUMMYFUNCTION("""COMPUTED_VALUE"""),"No") -> No | AH33: =IFERROR(__xludf.DUMMYFUNCTION("""COMPUTED_VALUE"""),"No") -> No
A34: =IFERROR(__xludf.DUMMYFUNCTION("""COMPUTED_VALUE"""),2.51125004E8) -> 251125004 | B34: =IFERROR(__xludf.DUMMYFUNCTION("""COMPUTED_VALUE"""),"DANIEL") -> DANIEL | D34: =IFERROR(__xludf.DUMMYFUNCTION("""COMPUTED_VALUE"""),"BINNS") -> BINNS | F34: =IFERROR(__xludf.DUMMYFUNCTION("""COMPUTED_VALUE"""),"Cleaner") -> Cleaner | I34: =IFERROR(__xludf.DUMMYFUNCTION("""COMPUTED_VALUE"""),"Hourly") -> Hourly | J34: =IFERROR(__xludf.DUMMYFUNCTION("""COMPUTED_VALUE"""),45986.0) -> 45986 | K34: =IFERROR(__xludf.DUMMYFUNCTION("""COMPUTED_VALUE"""),"Chrysler Brampton") -> Chrysler Brampton | L34: =IFERROR(__xludf.DUMMYFUNCTION("""COMPUTED_VALUE"""),"TJ005") -> TJ005 | M34: =IFERROR(__xludf.DUMMYFUNCTION("""COMPUTED_VALUE"""),"Binns") -> Binns | N34: =IFERROR(__xludf.DUMMYFUNCTION("""COMPUTED_VALUE"""),"dbinns@team-group.com") -> dbinns@team-group.com | O34: =IFERROR(__xludf.DUMMYFUNCTION("""COMPUTED_VALUE"""),"No") -> No | P34: =IFERROR(__xludf.DUMMYFUNCTION("""COMPUTED_VALUE"""),"No") -> No | Q34: =IFERROR(__xludf.DUMMYFUNCTION("""COMPUTED_VALUE"""),"No") -> No | R34: =IFERROR(__xludf.DUMMYFUNCTION("""COMPUTED_VALUE"""),"No") -> No | W34: =IFERROR(__xludf.DUMMYFUNCTION("""COMPUTED_VALUE"""),"No") -> No | X34: =IFERROR(__xludf.DUMMYFUNCTION("""COMPUTED_VALUE"""),"No") -> No | Y34: =IFERROR(__xludf.DUMMYFUNCTION("""COMPUTED_VALUE"""),"No") -> No | Z34: =IFERROR(__xludf.DUMMYFUNCTION("""COMPUTED_VALUE"""),"No") -> No | AA34: =IFERROR(__xludf.DUMMYFUNCTION("""COMPUTED_VALUE"""),"No") -> No | AC34: =IFERROR(__xludf.DUMMYFUNCTION("""COMPUTED_VALUE"""),"No") -> No | AD34: =IFERROR(__xludf.DUMMYFUNCTION("""COMPUTED_VALUE"""),"No") -> No | AE34: =IFERROR(__xludf.DUMMYFUNCTION("""COMPUTED_VALUE"""),"No") -> No | AF34: =IFERROR(__xludf.DUMMYFUNCTION("""COMPUTED_VALUE"""),"No") -> No | AG34: =IFERROR(__xludf.DUMMYFUNCTION("""COMPUTED_VALUE"""),"No") -> No | AH34: =IFERROR(__xludf.DUMMYFUNCTION("""COMPUTED_VALUE"""),"No") -> No
B151: ='All Responses'!N:N
B152: ='All Responses'!N:N
B153: ='All Responses'!N:N
B154: ='All Responses'!N:N
B155: ='All Responses'!N:N
B156: ='All Responses'!N:N
B157: ='All Responses'!N:N
B158: ='All Responses'!N:N
B159: ='All Responses'!N:N
B160: ='All Responses'!N:N
B161: ='All Responses'!N:N
B162: ='All Responses'!N:N
... B1000: ='All Responses'!N:N

Sheet Onboarding Tracker
A1: Employee ID | B1: First Name | C1: Middle Name | D1: Last Name | E1: Preferred Name | F1: Hire / Start Date | G1: Job Site Name | H1: Hire Date | I1: Employee Setup | J1: IT Setup | K1: Fleetio | L1: Credit Card | M1: Business Card | N1: 30-60-90 | O1: ADP | P1: JR | Q1: JONAS | R1: SiteDocs Tablet | S1: Workflow Status | T1: Employee Request Submission | U1: Final Approval Time | V1: Needed By? (Date Requested) | W1: Urgency | X1: Response Time | Y1: .
A2: =IFERROR(__xludf.DUMMYFUNCTION("FILTER('All Responses'!M:M, 'All Responses'!C:C = ""Completed"")"),2.5072906E8) -> 250729060 | B2: =IFERROR(__xludf.DUMMYFUNCTION("FILTER('All Responses'!N:N, 'All Responses'!C:C = ""Completed"")"),"John") -> John | C2: =IFERROR(__xludf.DUMMYFUNCTION("FILTER('All Responses'!O:O, 'All Responses'!C:C = ""Completed"")"),"JD") -> JD | D2: =IFERROR(__xludf.DUMMYFUNCTION("FILTER('All Responses'!P:P, 'All Responses'!C:C = ""Completed"")"),"Doe") -> Doe | E2: =IFERROR(__xludf.DUMMYFUNCTION("FILTER('All Responses'!Q:Q, 'All Responses'!C:C = ""Completed"")"),"JD") -> JD | F2: =IFERROR(__xludf.DUMMYFUNCTION("FILTER('All Responses'!I:I, 'All Responses'!C:C = ""Completed"")"),"") | G2: =IFERROR(__xludf.DUMMYFUNCTION("FILTER('All Responses'!S:S, 'All Responses'!C:C = ""Completed"")"),"Decostar") -> Decostar | H2: =IFERROR(__xludf.DUMMYFUNCTION("FILTER('All Responses'!I:I, 'All Responses'!C:C = ""Completed"")"),"") | I2: =IFERROR(__xludf.DUMMYFUNCTION("FILTER('All Responses'!BW:BW, 'All Responses'!C:C = ""Completed"")"),45867.62397212963) -> 45867.624 | J2: =IFERROR(__xludf.DUMMYFUNCTION("FILTER('All Responses'!CP:CP, 'All Responses'!C:C = ""Completed"")"),45867.62460070602) -> 45867.625 | K2: =IFERROR(__xludf.DUMMYFUNCTION("FILTER('All Responses'!CV:CV, 'All Responses'!C:C = ""Completed"")"),"") | L2: =IFERROR(__xludf.DUMMYFUNCTION("FILTER('All Responses'!DI:DI, 'All Responses'!C:C = ""Completed"")"),"") | M2: =IFERROR(__xludf.DUMMYFUNCTION("FILTER('All Responses'!DK:DK, 'All Responses'!C:C = ""Completed"")"),"") | N2: =IFERROR(__xludf.DUMMYFUNCTION("FILTER('All Responses'!DM:DM, 'All Responses'!C:C = ""Completed"")"),"") | O2: =IFERROR(__xludf.DUMMYFUNCTION("FILTER('All Responses'!DO:DO, 'All Responses'!C:C = ""Completed"")"),"") | P2: =IFERROR(__xludf.DUMMYFUNCTION("FILTER('All Responses'!DX:DX, 'All Responses'!C:C = ""Completed"")"),"") | Q2: =IFERROR(__xludf.DUMMYFUNCTION("FILTER('All Responses'!DZ:DZ, 'All Responses'!C:C = ""Completed"")"),"") | R2: =IFERROR(__xludf.DUMMYFUNCTION("FILTER('All Responses'!DT:DT, 'All Responses'!C:C = ""Completed"")"),"") | S2: =IFERROR(__xludf.DUMMYFUNCTION("FILTER('All Responses'!C:C, 'All Responses'!C:C = ""Completed"")"),"Completed") -> Completed | T2: =IFERROR(__xludf.DUMMYFUNCTION("FILTER('All Responses'!A:A, 'All Responses'!C:C = ""Completed"")"),45867.62260074074) -> 45867.623 | U2: =IFERROR(__xludf.DUMMYFUNCTION("FILTER('All Responses'!ED:ED, 'All Responses'!C:C = ""Completed"")"),45867.62509259259) -> 45867.625 | V2: =IFERROR(__xludf.DUMMYFUNCTION("FILTER('All Responses'!BK:BK, 'All Responses'!C:C = ""Completed"")"),45873.0) -> 45873 | W2: {=DATEDIF(T2, V2, "D")} -> 6 | X2: =DATEDIF(T2, U2, "D") -> 0
A3: =IFERROR(__xludf.DUMMYFUNCTION("""COMPUTED_VALUE"""),2.50729062E8) -> 250729062 | B3: =IFERROR(__xludf.DUMMYFUNCTION("""COMPUTED_VALUE"""),"John") -> John | C3: =IFERROR(__xludf.DUMMYFUNCTION("""COMPUTED_VALUE"""),"z") -> z | D3: =IFERROR(__xludf.DUMMYFUNCTION("""COMPUTED_VALUE"""),"Doe") -> Doe | E3: =IFERROR(__xludf.DUMMYFUNCTION("""COMPUTED_VALUE"""),"JZ") -> JZ | F3: =IFERROR(__xludf.DUMMYFUNCTION("""COMPUTED_VALUE"""),45875.0) -> 45875 | G3: =IFERROR(__xludf.DUMMYFUNCTION("""COMPUTED_VALUE"""),"Etobicote") -> Etobicote | H3: =IFERROR(__xludf.DUMMYFUNCTION("""COMPUTED_VALUE"""),45875.0) -> 45875 | I3: =IFERROR(__xludf.DUMMYFUNCTION("""COMPUTED_VALUE"""),45867.63691163194) -> 45867.637 | J3: =IFERROR(__xludf.DUMMYFUNCTION("""COMPUTED_VALUE"""),45867.63854743056) -> 45867.639 | S3: =IFERROR(__xludf.DUMMYFUNCTION("""COMPUTED_VALUE"""),"Completed") -> Completed | U3: =IFERROR(__xludf.DUMMYFUNCTION("""COMPUTED_VALUE"""),45867.639444444445) -> 45867.639 | V3: =IFERROR(__xludf.DUMMYFUNCTION("""COMPUTED_VALUE"""),45867.0) -> 45867 | W3: {=DATEDIF(T3, V3, "D")} -> 45867 | X3: =DATEDIF(T3, U3, "D") -> 45867
A4: =IFERROR(__xludf.DUMMYFUNCTION("""COMPUTED_VALUE"""),2.50729063E8) -> 250729063 | B4: =IFERROR(__xludf.DUMMYFUNCTION("""COMPUTED_VALUE"""),"John") -> John | C4: =IFERROR(__xludf.DUMMYFUNCTION("""COMPUTED_VALUE"""),"JD") -> JD | D4: =IFERROR(__xludf.DUMMYFUNCTION("""COMPUTED_VALUE"""),"Doe") -> Doe | E4: =IFERROR(__xludf.DUMMYFUNCTION("""COMPUTED_VALUE"""),"JD") -> JD | F4: =IFERROR(__xludf.DUMMYFUNCTION("""COMPUTED_VALUE"""),45876.0) -> 45876 | G4: =IFERROR(__xludf.DUMMYFUNCTION("""COMPUTED_VALUE"""),"Decostar") -> Decostar | H4: =IFERROR(__xludf.DUMMYFUNCTION("""COMPUTED_VALUE"""),45876.0) -> 45876 | I4: =IFERROR(__xludf.DUMMYFUNCTION("""COMPUTED_VALUE"""),45867.6603109375) -> 45867.66 | J4: =IFERROR(__xludf.DUMMYFUNCTION("""COMPUTED_VALUE"""),45867.66179622685) -> 45867.662 | S4: =IFERROR(__xludf.DUMMYFUNCTION("""COMPUTED_VALUE"""),"Completed") -> Completed | T4: =IFERROR(__xludf.DUMMYFUNCTION("""COMPUTED_VALUE"""),45867.65915564814) -> 45867.659 | U4: =IFERROR(__xludf.DUMMYFUNCTION("""COMPUTED_VALUE"""),45867.66239690973) -> 45867.662 | V4: =IFERROR(__xludf.DUMMYFUNCTION("""COMPUTED_VALUE"""),45875.0) -> 45875 | W4: {=DATEDIF(T4, V4, "D")} -> 8 | X4: =DATEDIF(T4, U4, "D") -> 0
A5: =IFERROR(__xludf.DUMMYFUNCTION("""COMPUTED_VALUE"""),2.50729064E8) -> 250729064 | B5: =IFERROR(__xludf.DUMMYFUNCTION("""COMPUTED_VALUE"""),"John") -> John | C5: =IFERROR(__xludf.DUMMYFUNCTION("""COMPUTED_VALUE"""),"JD") -> JD | D5: =IFERROR(__xludf.DUMMYFUNCTION("""COMPUTED_VALUE"""),"Doe") -> Doe | E5: =IFERROR(__xludf.DUMMYFUNCTION("""COMPUTED_VALUE"""),"JD") -> JD | F5: =IFERROR(__xludf.DUMMYFUNCTION("""COMPUTED_VALUE"""),45875.0) -> 45875 | G5: =IFERROR(__xludf.DUMMYFUNCTION("""COMPUTED_VALUE"""),"Etobicote") -> Etobicote | H5: =IFERROR(__xludf.DUMMYFUNCTION("""COMPUTED_VALUE"""),45875.0) -> 45875 | I5: =IFERROR(__xludf.DUMMYFUNCTION("""COMPUTED_VALUE"""),45867.673139085644) -> 45867.673 | J5: =IFERROR(__xludf.DUMMYFUNCTION("""COMPUTED_VALUE"""),45867.67417868055) -> 45867.674 | S5: =IFERROR(__xludf.DUMMYFUNCTION("""COMPUTED_VALUE"""),"Completed") -> Completed | T5: =IFERROR(__xludf.DUMMYFUNCTION("""COMPUTED_VALUE"""),45867.67209059028) -> 45867.672 | U5: =IFERROR(__xludf.DUMMYFUNCTION("""COMPUTED_VALUE"""),45867.674659027776) -> 45867.675 | V5: =IFERROR(__xludf.DUMMYFUNCTION("""COMPUTED_VALUE"""),45874.0) -> 45874 | W5: {=DATEDIF(T5, V5, "D")} -> 7 | X5: =DATEDIF(T5, U5, "D") -> 0
A6: =IFERROR(__xludf.DUMMYFUNCTION("""COMPUTED_VALUE"""),2.50729065E8) -> 250729065 | B6: =IFERROR(__xludf.DUMMYFUNCTION("""COMPUTED_VALUE"""),"John") -> John | C6: =IFERROR(__xludf.DUMMYFUNCTION("""COMPUTED_VALUE"""),"JD") -> JD | D6: =IFERROR(__xludf.DUMMYFUNCTION("""COMPUTED_VALUE"""),"Doe") -> Doe | E6: =IFERROR(__xludf.DUMMYFUNCTION("""COMPUTED_VALUE"""),"JD") -> JD | F6: =IFERROR(__xludf.DUMMYFUNCTION("""COMPUTED_VALUE"""),45875.0) -> 45875 | G6: =IFERROR(__xludf.DUMMYFUNCTION("""COMPUTED_VALUE"""),"Etobicote") -> Etobicote | H6: =IFERROR(__xludf.DUMMYFUNCTION("""COMPUTED_VALUE"""),45875.0) -> 45875 | I6: =IFERROR(__xludf.DUMMYFUNCTION("""COMPUTED_VALUE"""),45867.68293570602) -> 45867.683 | J6: =IFERROR(__xludf.DUMMYFUNCTION("""COMPUTED_VALUE"""),45867.68350280092) -> 45867.683 | S6: =IFERROR(__xludf.DUMMYFUNCTION("""COMPUTED_VALUE"""),"Completed") -> Completed | T6: =IFERROR(__xludf.DUMMYFUNCTION("""COMPUTED_VALUE"""),45867.68225277778) -> 45867.682 | U6: =IFERROR(__xludf.DUMMYFUNCTION("""COMPUTED_VALUE"""),45867.683977002314) -> 45867.684 | V6: =IFERROR(__xludf.DUMMYFUNCTION("""COMPUTED_VALUE"""),45874.0) -> 45874 | W6: {=DATEDIF(T6, V6, "D")} -> 7 | X6: =DATEDIF(T6, U6, "D") -> 0
A7: =IFERROR(__xludf.DUMMYFUNCTION("""COMPUTED_VALUE"""),2.50729066E8) -> 250729066 | B7: =IFERROR(__xludf.DUMMYFUNCTION("""COMPUTED_VALUE"""),"John") -> John | C7: =IFERROR(__xludf.DUMMYFUNCTION("""COMPUTED_VALUE"""),"JD") -> JD | D7: =IFERROR(__xludf.DUMMYFUNCTION("""COMPUTED_VALUE"""),"Doe") -> Doe | E7: =IFERROR(__xludf.DUMMYFUNCTION("""COMPUTED_VALUE"""),"JD") -> JD | F7: =IFERROR(__xludf.DUMMYFUNCTION("""COMPUTED_VALUE"""),45875.0) -> 45875 | G7: =IFERROR(__xludf.DUMMYFUNCTION("""COMPUTED_VALUE"""),"Edmonton") -> Edmonton | H7: =IFERROR(__xludf.DUMMYFUNCTION("""COMPUTED_VALUE"""),45875.0) -> 45875 | I7: =IFERROR(__xludf.DUMMYFUNCTION("""COMPUTED_VALUE"""),45867.70395549768) -> 45867.704 | J7: =IFERROR(__xludf.DUMMYFUNCTION("""COMPUTED_VALUE"""),45867.70906474537) -> 45867.709 | S7: =IFERROR(__xludf.DUMMYFUNCTION("""COMPUTED_VALUE"""),"Completed") -> Completed | T7: =IFERROR(__xludf.DUMMYFUNCTION("""COMPUTED_VALUE"""),45867.70198914352) -> 45867.702 | U7: =IFERROR(__xludf.DUMMYFUNCTION("""COMPUTED_VALUE"""),45867.709885625) -> 45867.71 | V7: =IFERROR(__xludf.DUMMYFUNCTION("""COMPUTED_VALUE"""),45874.0) -> 45874 | W7: {=DATEDIF(T7, V7, "D")} -> 7 | X7: =DATEDIF(T7, U7, "D") -> 0
A8: =IFERROR(__xludf.DUMMYFUNCTION("""COMPUTED_VALUE"""),2.50730001E8) -> 250730001 | B8: =IFERROR(__xludf.DUMMYFUNCTION("""COMPUTED_VALUE"""),"John") -> John | C8: =IFERROR(__xludf.DUMMYFUNCTION("""COMPUTED_VALUE"""),"JD") -> JD | D8: =IFERROR(__xludf.DUMMYFUNCTION("""COMPUTED_VALUE"""),"Doe") -> Doe | E8: =IFERROR(__xludf.DUMMYFUNCTION("""COMPUTED_VALUE"""),"JD") -> JD | F8: =IFERROR(__xludf.DUMMYFUNCTION("""COMPUTED_VALUE"""),45876.0) -> 45876 | G8: =IFERROR(__xludf.DUMMYFUNCTION("""COMPUTED_VALUE"""),"Bluebird") -> Bluebird | H8: =IFERROR(__xludf.DUMMYFUNCTION("""COMPUTED_VALUE"""),45876.0) -> 45876 | I8: =IFERROR(__xludf.DUMMYFUNCTION("""COMPUTED_VALUE"""),45868.5069280787) -> 45868.507 | J8: =IFERROR(__xludf.DUMMYFUNCTION("""COMPUTED_VALUE"""),45868.510857939815) -> 45868.511 | L8: =IFERROR(__xludf.DUMMYFUNCTION("""COMPUTED_VALUE"""),45868.509198472224) -> 45868.509 | M8: =IFERROR(__xludf.DUMMYFUNCTION("""COMPUTED_VALUE"""),45868.50902701389) -> 45868.509 | N8: =IFERROR(__xludf.DUMMYFUNCTION("""COMPUTED_VALUE"""),45868.5093472338) -> 45868.509 | O8: =IFERROR(__xludf.DUMMYFUNCTION("""COMPUTED_VALUE"""),45868.509892789356) -> 45868.51 | S8: =IFERROR(__xludf.DUMMYFUNCTION("""COMPUTED_VALUE"""),"Completed") -> Completed | U8: =IFERROR(__xludf.DUMMYFUNCTION("""COMPUTED_VALUE"""),45868.51295658565) -> 45868.513 | V8: =IFERROR(__xludf.DUMMYFUNCTION("""COMPUTED_VALUE"""),45874.0) -> 45874 | W8: {=DATEDIF(T8, V8, "D")} -> 45874 | X8: =DATEDIF(T8, U8, "D") -> 45868
A9: =IFERROR(__xludf.DUMMYFUNCTION("""COMPUTED_VALUE"""),2.50730003E8) -> 250730003 | B9: =IFERROR(__xludf.DUMMYFUNCTION("""COMPUTED_VALUE"""),"John") -> John | C9: =IFERROR(__xludf.DUMMYFUNCTION("""COMPUTED_VALUE"""),"JD") -> JD | D9: =IFERROR(__xludf.DUMMYFUNCTION("""COMPUTED_VALUE"""),"Doe") -> Doe | E9: =IFERROR(__xludf.DUMMYFUNCTION("""COMPUTED_VALUE"""),"JD") -> JD | F9: =IFERROR(__xludf.DUMMYFUNCTION("""COMPUTED_VALUE"""),45875.0) -> 45875 | G9: =IFERROR(__xludf.DUMMYFUNCTION("""COMPUTED_VALUE"""),"Edmonton") -> Edmonton | H9: =IFERROR(__xludf.DUMMYFUNCTION("""COMPUTED_VALUE"""),45875.0) -> 45875 | I9: =IFERROR(__xludf.DUMMYFUNCTION("""COMPUTED_VALUE"""),45868.53345365741) -> 45868.533 | J9: =IFERROR(__xludf.DUMMYFUNCTION("""COMPUTED_VALUE"""),45868.534792418985) -> 45868.535 | M9: =IFERROR(__xludf.DUMMYFUNCTION("""COMPUTED_VALUE"""),45868.53482148148) -> 45868.535 | O9: =IFERROR(__xludf.DUMMYFUNCTION("""COMPUTED_VALUE"""),45868.534762662035) -> 45868.535 | S9: =IFERROR(__xludf.DUMMYFUNCTION("""COMPUTED_VALUE"""),"Completed") -> Completed | U9: =IFERROR(__xludf.DUMMYFUNCTION("""COMPUTED_VALUE"""),45868.535658402776) -> 45868.536 | V9: =IFERROR(__xludf.DUMMYFUNCTION("""COMPUTED_VALUE"""),45874.0) -> 45874 | W9: {=DATEDIF(T9, V9, "D")} -> 45874 | X9: =DATEDIF(T9, U9, "D") -> 45868
A10: =IFERROR(__xludf.DUMMYFUNCTION("""COMPUTED_VALUE"""),2.50730004E8) -> 250730004 | B10: =IFERROR(__xludf.DUMMYFUNCTION("""COMPUTED_VALUE"""),"John") -> John | C10: =IFERROR(__xludf.DUMMYFUNCTION("""COMPUTED_VALUE"""),"JD") -> JD | D10: =IFERROR(__xludf.DUMMYFUNCTION("""COMPUTED_VALUE"""),"Doe") -> Doe | E10: =IFERROR(__xludf.DUMMYFUNCTION("""COMPUTED_VALUE"""),"JD") -> JD | F10: =IFERROR(__xludf.DUMMYFUNCTION("""COMPUTED_VALUE"""),45877.0) -> 45877 | G10: =IFERROR(__xludf.DUMMYFUNCTION("""COMPUTED_VALUE"""),"Edmonton") -> Edmonton | H10: =IFERROR(__xludf.DUMMYFUNCTION("""COMPUTED_VALUE"""),45877.0) -> 45877 | I10: =IFERROR(__xludf.DUMMYFUNCTION("""COMPUTED_VALUE"""),45868.54598755787) -> 45868.546 | J10: =IFERROR(__xludf.DUMMYFUNCTION("""COMPUTED_VALUE"""),45868.547487766205) -> 45868.547 | L10: =IFERROR(__xludf.DUMMYFUNCTION("""COMPUTED_VALUE"""),45868.5472312037) -> 45868.547 | M10: =IFERROR(__xludf.DUMMYFUNCTION("""COMPUTED_VALUE"""),45868.54729369213) -> 45868.547 | N10: =IFERROR(__xludf.DUMMYFUNCTION("""COMPUTED_VALUE"""),45868.54726633102) -> 45868.547 | O10: =IFERROR(__xludf.DUMMYFUNCTION("""COMPUTED_VALUE"""),45868.547310497685) -> 45868.547 | P10: =IFERROR(__xludf.DUMMYFUNCTION("""COMPUTED_VALUE"""),45868.54654434028) -> 45868.547 | S10: =IFERROR(__xludf.DUMMYFUNCTION("""COMPUTED_VALUE"""),"Completed") -> Completed | U10: =IFERROR(__xludf.DUMMYFUNCTION("""COMPUTED_VALUE"""),45868.549081087964) -> 45868.549 | V10: =IFERROR(__xludf.DUMMYFUNCTION("""COMPUTED_VALUE"""),45874.0) -> 45874 | W10: {=DATEDIF(T10, V10, "D")} -> 45874 | X10: =DATEDIF(T10, U10, "D") -> 45868
A11: =IFERROR(__xludf.DUMMYFUNCTION("""COMPUTED_VALUE"""),2.50730005E8) -> 250730005 | B11: =IFERROR(__xludf.DUMMYFUNCTION("""COMPUTED_VALUE"""),"John") -> John | C11: =IFERROR(__xludf.DUMMYFUNCTION("""COMPUTED_VALUE"""),"JD") -> JD | D11: =IFERROR(__xludf.DUMMYFUNCTION("""COMPUTED_VALUE"""),"Doe") -> Doe | E11: =IFERROR(__xludf.DUMMYFUNCTION("""COMPUTED_VALUE"""),"JD") -> JD | F11: =IFERROR(__xludf.DUMMYFUNCTION("""COMPUTED_VALUE"""),45874.0) -> 45874 | G11: =IFERROR(__xludf.DUMMYFUNCTION("""COMPUTED_VALUE"""),"Bluebird") -> Bluebird | H11: =IFERROR(__xludf.DUMMYFUNCTION("""COMPUTED_VALUE"""),45874.0) -> 45874 | I11: =IFERROR(__xludf.DUMMYFUNCTION("""COMPUTED_VALUE"""),45868.64808284723) -> 45868.648 | J11: =IFERROR(__xludf.DUMMYFUNCTION("""COMPUTED_VALUE"""),45868.65063725694) -> 45868.651 | L11: =IFERROR(__xludf.DUMMYFUNCTION("""COMPUTED_VALUE"""),45868.64911247685) -> 45868.649 | M11: =IFERROR(__xludf.DUMMYFUNCTION("""COMPUTED_VALUE"""),45868.65035748843) -> 45868.65 | N11: =IFERROR(__xludf.DUMMYFUNCTION("""COMPUTED_VALUE"""),45868.65032825232) -> 45868.65 | O11: =IFERROR(__xludf.DUMMYFUNCTION("""COMPUTED_VALUE"""),45868.650301076384) -> 45868.65 | P11: =IFERROR(__xludf.DUMMYFUNCTION("""COMPUTED_VALUE"""),45868.650272604165) -> 45868.65 | S11: =IFERROR(__xludf.DUMMYFUNCTION("""COMPUTED_VALUE"""),"Completed") -> Completed | U11: =IFERROR(__xludf.DUMMYFUNCTION("""COMPUTED_VALUE"""),45868.65177681713) -> 45868.652 | V11: =IFERROR(__xludf.DUMMYFUNCTION("""COMPUTED_VALUE"""),45874.0) -> 45874 | W11: {=DATEDIF(T11, V11, "D")} -> 45874 | X11: =DATEDIF(T11, U11, "D") -> 45868
A12: =IFERROR(__xludf.DUMMYFUNCTION("""COMPUTED_VALUE"""),2.50805002E8) -> 250805002 | B12: =IFERROR(__xludf.DUMMYFUNCTION("""COMPUTED_VALUE"""),"John") -> John | C12: =IFERROR(__xludf.DUMMYFUNCTION("""COMPUTED_VALUE"""),"JD") -> JD | D12: =IFERROR(__xludf.DUMMYFUNCTION("""COMPUTED_VALUE"""),"Doe") -> Doe | E12: =IFERROR(__xludf.DUMMYFUNCTION("""COMPUTED_VALUE"""),"JD") -> JD | F12: =IFERROR(__xludf.DUMMYFUNCTION("""COMPUTED_VALUE"""),45881.0) -> 45881 | G12: =IFERROR(__xludf.DUMMYFUNCTION("""COMPUTED_VALUE"""),"Bluebird") -> Bluebird | H12: =IFERROR(__xludf.DUMMYFUNCTION("""COMPUTED_VALUE"""),45881.0) -> 45881 | I12: =IFERROR(__xludf.DUMMYFUNCTION("""COMPUTED_VALUE"""),45874.509130543986) -> 45874.509 | J12: =IFERROR(__xludf.DUMMYFUNCTION("""COMPUTED_VALUE"""),45874.51171849537) -> 45874.512 | L12: =IFERROR(__xludf.DUMMYFUNCTION("""COMPUTED_VALUE"""),45874.51092398148) -> 45874.511 | M12: =IFERROR(__xludf.DUMMYFUNCTION("""COMPUTED_VALUE"""),45874.51084113426) -> 45874.511 | N12: =IFERROR(__xludf.DUMMYFUNCTION("""COMPUTED_VALUE"""),45874.5108705787) -> 45874.511 | O12: =IFERROR(__xludf.DUMMYFUNCTION("""COMPUTED_VALUE"""),45874.51057351852) -> 45874.511 | P12: =IFERROR(__xludf.DUMMYFUNCTION("""COMPUTED_VALUE"""),45874.51074017361) -> 45874.511 | S12: =IFERROR(__xludf.DUMMYFUNCTION("""COMPUTED_VALUE"""),"Completed") -> Completed | U12: =IFERROR(__xludf.DUMMYFUNCTION("""COMPUTED_VALUE"""),45874.513895462966) -> 45874.514 | V12: =IFERROR(__xludf.DUMMYFUNCTION("""COMPUTED_VALUE"""),45880.0) -> 45880 | W12: {=DATEDIF(T12, V12, "D")} -> 45880 | X12: =DATEDIF(T12, U12, "D") -> 45874
A13: =IFERROR(__xludf.DUMMYFUNCTION("""COMPUTED_VALUE"""),2.50805006E8) -> 250805006 | B13: =IFERROR(__xludf.DUMMYFUNCTION("""COMPUTED_VALUE"""),"John") -> John | C13: =IFERROR(__xludf.DUMMYFUNCTION("""COMPUTED_VALUE"""),"JD") -> JD | D13: =IFERROR(__xludf.DUMMYFUNCTION("""COMPUTED_VALUE"""),"Doe") -> Doe | E13: =IFERROR(__xludf.DUMMYFUNCTION("""COMPUTED_VALUE"""),"JD") -> JD | F13: =IFERROR(__xludf.DUMMYFUNCTION("""COMPUTED_VALUE"""),45889.0) -> 45889 | G13: =IFERROR(__xludf.DUMMYFUNCTION("""COMPUTED_VALUE"""),"Decostar") -> Decostar | H13: =IFERROR(__xludf.DUMMYFUNCTION("""COMPUTED_VALUE"""),45889.0) -> 45889 | I13: =IFERROR(__xludf.DUMMYFUNCTION("""COMPUTED_VALUE"""),45874.62465240741) -> 45874.625 | J13: =IFERROR(__xludf.DUMMYFUNCTION("""COMPUTED_VALUE"""),45874.62547972222) -> 45874.625 | L13: =IFERROR(__xludf.DUMMYFUNCTION("""COMPUTED_VALUE"""),45874.625566608796) -> 45874.626 | R13: =IFERROR(__xludf.DUMMYFUNCTION("""COMPUTED_VALUE"""),45874.62554165509) -> 45874.626 | S13: =IFERROR(__xludf.DUMMYFUNCTION("""COMPUTED_VALUE"""),"Completed") -> Completed | U13: =IFERROR(__xludf.DUMMYFUNCTION("""COMPUTED_VALUE"""),45874.625547800926) -> 45874.626 | V13: =IFERROR(__xludf.DUMMYFUNCTION("""COMPUTED_VALUE"""),45880.0) -> 45880 | W13: {=DATEDIF(T13, V13, "D")} -> 45880 | X13: =DATEDIF(T13, U13, "D") -> 45874
A14: =IFERROR(__xludf.DUMMYFUNCTION("""COMPUTED_VALUE"""),2.50805007E8) -> 250805007 | B14: =IFERROR(__xludf.DUMMYFUNCTION("""COMPUTED_VALUE"""),"John") -> John | C14: =IFERROR(__xludf.DUMMYFUNCTION("""COMPUTED_VALUE"""),"JD") -> JD | D14: =IFERROR(__xludf.DUMMYFUNCTION("""COMPUTED_VALUE"""),"Doe") -> Doe | F14: =IFERROR(__xludf.DUMMYFUNCTION("""COMPUTED_VALUE"""),45883.0) -> 45883 | G14: =IFERROR(__xludf.DUMMYFUNCTION("""COMPUTED_VALUE"""),"Decostar") -> Decostar | H14: =IFERROR(__xludf.DUMMYFUNCTION("""COMPUTED_VALUE"""),45883.0) -> 45883 | I14: =IFERROR(__xludf.DUMMYFUNCTION("""COMPUTED_VALUE"""),45874.65167400463) -> 45874.652 | J14: =IFERROR(__xludf.DUMMYFUNCTION("""COMPUTED_VALUE"""),45874.65207931713) -> 45874.652 | S14: =IFERROR(__xludf.DUMMYFUNCTION("""COMPUTED_VALUE"""),"Completed") -> Completed | U14: =IFERROR(__xludf.DUMMYFUNCTION("""COMPUTED_VALUE"""),45874.65214825231) -> 45874.652 | V14: =IFERROR(__xludf.DUMMYFUNCTION("""COMPUTED_VALUE"""),45880.0) -> 45880 | W14: {=DATEDIF(T14, V14, "D")} -> 45880 | X14: =DATEDIF(T14, U14, "D") -> 45874
A15: =IFERROR(__xludf.DUMMYFUNCTION("""COMPUTED_VALUE"""),2.50806001E8) -> 250806001 | B15: =IFERROR(__xludf.DUMMYFUNCTION("""COMPUTED_VALUE"""),"John") -> John | D15: =IFERROR(__xludf.DUMMYFUNCTION("""COMPUTED_VALUE"""),"Doe") -> Doe | F15: =IFERROR(__xludf.DUMMYFUNCTION("""COMPUTED_VALUE"""),45904.0) -> 45904 | G15: =IFERROR(__xludf.DUMMYFUNCTION("""COMPUTED_VALUE"""),"Chrysler Windsor Paintshop") -> Chrysler Windsor Paintshop | H15: =IFERROR(__xludf.DUMMYFUNCTION("""COMPUTED_VALUE"""),45904.0) -> 45904 | I15: =IFERROR(__xludf.DUMMYFUNCTION("""COMPUTED_VALUE"""),45875.433671446764) -> 45875.434 | J15: =IFERROR(__xludf.DUMMYFUNCTION("""COMPUTED_VALUE"""),45875.43422855324) -> 45875.434 | L15: =IFERROR(__xludf.DUMMYFUNCTION("""COMPUTED_VALUE"""),45875.434197939816) -> 45875.434 | S15: =IFERROR(__xludf.DUMMYFUNCTION("""COMPUTED_VALUE"""),"Completed") -> Completed | U15: =IFERROR(__xludf.DUMMYFUNCTION("""COMPUTED_VALUE"""),45875.43430746528) -> 45875.434 | V15: =IFERROR(__xludf.DUMMYFUNCTION("""COMPUTED_VALUE"""),45895.0) -> 45895 | W15: {=DATEDIF(T15, V15, "D")} -> 45895 | X15: =DATEDIF(T15, U15, "D") -> 45875
A16: =IFERROR(__xludf.DUMMYFUNCTION("""COMPUTED_VALUE"""),2.50806002E8) -> 250806002 | B16: =IFERROR(__xludf.DUMMYFUNCTION("""COMPUTED_VALUE"""),"John") -> John | C16: =IFERROR(__xludf.DUMMYFUNCTION("""COMPUTED_VALUE"""),"JD") -> JD | D16: =IFERROR(__xludf.DUMMYFUNCTION("""COMPUTED_VALUE"""),"Doe") -> Doe | F16: =IFERROR(__xludf.DUMMYFUNCTION("""COMPUTED_VALUE"""),45894.0) -> 45894 | G16: =IFERROR(__xludf.DUMMYFUNCTION("""COMPUTED_VALUE"""),"Cost Variance - RSI") -> Cost Variance - RSI | H16: =IFERROR(__xludf.DUMMYFUNCTION("""COMPUTED_VALUE"""),45894.0) -> 45894 | I16: =IFERROR(__xludf.DUMMYFUNCTION("""COMPUTED_VALUE"""),45875.45813409722) -> 45875.458 | J16: =IFERROR(__xludf.DUMMYFUNCTION("""COMPUTED_VALUE"""),45875.46517614584) -> 45875.465 | S16: =IFERROR(__xludf.DUMMYFUNCTION("""COMPUTED_VALUE"""),"Completed") -> Completed | T16: =IFERROR(__xludf.DUMMYFUNCTION("""COMPUTED_VALUE"""),45875.456749398145) -> 45875.457 | U16: =IFERROR(__xludf.DUMMYFUNCTION("""COMPUTED_VALUE"""),45875.46526244213) -> 45875.465 | V16: =IFERROR(__xludf.DUMMYFUNCTION("""COMPUTED_VALUE"""),45891.0) -> 45891 | W16: {=DATEDIF(T16, V16, "D")} -> 16 | X16: =DATEDIF(T16, U16, "D") -> 0
A17: =IFERROR(__xludf.DUMMYFUNCTION("""COMPUTED_VALUE"""),2.50806003E8) -> 250806003 | B17: =IFERROR(__xludf.DUMMYFUNCTION("""COMPUTED_VALUE"""),"John") -> John | C17: =IFERROR(__xludf.DUMMYFUNCTION("""COMPUTED_VALUE"""),"z") -> z | D17: =IFERROR(__xludf.DUMMYFUNCTION("""COMPUTED_VALUE"""),"Doe") -> Doe | E17: =IFERROR(__xludf.DUMMYFUNCTION("""COMPUTED_VALUE"""),"JZ") -> JZ | F17: =IFERROR(__xludf.DUMMYFUNCTION("""COMPUTED_VALUE"""),45896.0) -> 45896 | G17: =IFERROR(__xludf.DUMMYFUNCTION("""COMPUTED_VALUE"""),"Finance") -> Finance | H17: =IFERROR(__xludf.DUMMYFUNCTION("""COMPUTED_VALUE"""),45896.0) -> 45896 | I17: =IFERROR(__xludf.DUMMYFUNCTION("""COMPUTED_VALUE"""),45875.46891568287) -> 45875.469 | J17: =IFERROR(__xludf.DUMMYFUNCTION("""COMPUTED_VALUE"""),45875.47072511574) -> 45875.471 | L17: =IFERROR(__xludf.DUMMYFUNCTION("""COMPUTED_VALUE"""),45875.47094853009) -> 45875.471 | M17: =IFERROR(__xludf.DUMMYFUNCTION("""COMPUTED_VALUE"""),45875.470882696754) -> 45875.471 | N17: =IFERROR(__xludf.DUMMYFUNCTION("""COMPUTED_VALUE"""),45875.47084144676) -> 45875.471 | O17: =IFERROR(__xludf.DUMMYFUNCTION("""COMPUTED_VALUE"""),45875.470895810184) -> 45875.471 | P17: =IFERROR(__xludf.DUMMYFUNCTION("""COMPUTED_VALUE"""),45875.47092420139) -> 45875.471 | R17: =IFERROR(__xludf.DUMMYFUNCTION("""COMPUTED_VALUE"""),45875.47098049769) -> 45875.471 | S17: =IFERROR(__xludf.DUMMYFUNCTION("""COMPUTED_VALUE"""),"Completed") -> Completed | T17: =IFERROR(__xludf.DUMMYFUNCTION("""COMPUTED_VALUE"""),45875.468286261574) -> 45875.468 | U17: =IFERROR(__xludf.DUMMYFUNCTION("""COMPUTED_VALUE"""),45875.47081119213) -> 45875.471 | V17: =IFERROR(__xludf.DUMMYFUNCTION("""COMPUTED_VALUE"""),45894.0) -> 45894 | W17: {=DATEDIF(T17, V17, "D")} -> 19 | X17: =DATEDIF(T17, U17, "D") -> 0
A18: =IFERROR(__xludf.DUMMYFUNCTION("""COMPUTED_VALUE"""),2.50806004E8) -> 250806004 | B18: =IFERROR(__xludf.DUMMYFUNCTION("""COMPUTED_VALUE"""),"John") -> John | C18: =IFERROR(__xludf.DUMMYFUNCTION("""COMPUTED_VALUE"""),"JD") -> JD | D18: =IFERROR(__xludf.DUMMYFUNCTION("""COMPUTED_VALUE"""),"Doe") -> Doe | E18: =IFERROR(__xludf.DUMMYFUNCTION("""COMPUTED_VALUE"""),"JD") -> JD | F18: =IFERROR(__xludf.DUMMYFUNCTION("""COMPUTED_VALUE"""),45889.0) -> 45889 | G18: =IFERROR(__xludf.DUMMYFUNCTION("""COMPUTED_VALUE"""),"GM Oshawa Assembly") -> GM Oshawa Assembly | H18: =IFERROR(__xludf.DUMMYFUNCTION("""COMPUTED_VALUE"""),45889.0) -> 45889 | I18: =IFERROR(__xludf.DUMMYFUNCTION("""COMPUTED_VALUE"""),45875.502480173614) -> 45875.502 | J18: =IFERROR(__xludf.DUMMYFUNCTION("""COMPUTED_VALUE"""),45875.5027671875) -> 45875.503 | L18: =IFERROR(__xludf.DUMMYFUNCTION("""COMPUTED_VALUE"""),45875.50262621528) -> 45875.503 | P18: =IFERROR(__xludf.DUMMYFUNCTION("""COMPUTED_VALUE"""),45875.50257657407) -> 45875.503 | S18: =IFERROR(__xludf.DUMMYFUNCTION("""COMPUTED_VALUE"""),"Completed") -> Completed | T18: =IFERROR(__xludf.DUMMYFUNCTION("""COMPUTED_VALUE"""),45875.500882002314) -> 45875.501 | U18: =IFERROR(__xludf.DUMMYFUNCTION("""COMPUTED_VALUE"""),45875.504315115744) -> 45875.504 | V18: =IFERROR(__xludf.DUMMYFUNCTION("""COMPUTED_VALUE"""),45888.0) -> 45888 | W18: {=DATEDIF(T18, V18, "D")} -> 13 | X18: =DATEDIF(T18, U18, "D") -> 0
A19: =IFERROR(__xludf.DUMMYFUNCTION("""COMPUTED_VALUE"""),2.50807001E8) -> 250807001 | B19: =IFERROR(__xludf.DUMMYFUNCTION("""COMPUTED_VALUE"""),"John") -> John | C19: =IFERROR(__xludf.DUMMYFUNCTION("""COMPUTED_VALUE"""),"JD") -> JD | D19: =IFERROR(__xludf.DUMMYFUNCTION("""COMPUTED_VALUE"""),"Doe") -> Doe | E19: =IFERROR(__xludf.DUMMYFUNCTION("""COMPUTED_VALUE"""),"JD") -> JD | F19: =IFERROR(__xludf.DUMMYFUNCTION("""COMPUTED_VALUE"""),45877.0) -> 45877 | G19: =IFERROR(__xludf.DUMMYFUNCTION("""COMPUTED_VALUE"""),"Decostar Industries") -> Decostar Industries | H19: =IFERROR(__xludf.DUMMYFUNCTION("""COMPUTED_VALUE"""),45877.0) -> 45877 | I19: =IFERROR(__xludf.DUMMYFUNCTION("""COMPUTED_VALUE"""),45876.51051707176) -> 45876.511 | J19: =IFERROR(__xludf.DUMMYFUNCTION("""COMPUTED_VALUE"""),45876.51196855324) -> 45876.512 | L19: =IFERROR(__xludf.DUMMYFUNCTION("""COMPUTED_VALUE"""),45876.5120084838) -> 45876.512 | M19: =IFERROR(__xludf.DUMMYFUNCTION("""COMPUTED_VALUE"""),45876.511970023144) -> 45876.512 | N19: =IFERROR(__xludf.DUMMYFUNCTION("""COMPUTED_VALUE"""),45876.512122685184) -> 45876.512 | O19: =IFERROR(__xludf.DUMMYFUNCTION("""COMPUTED_VALUE"""),45876.51221608796) -> 45876.512 | P19: =IFERROR(__xludf.DUMMYFUNCTION("""COMPUTED_VALUE"""),45876.51217180556) -> 45876.512 | R19: =IFERROR(__xludf.DUMMYFUNCTION("""COMPUTED_VALUE"""),45876.512212800924) -> 45876.512 | S19: =IFERROR(__xludf.DUMMYFUNCTION("""COMPUTED_VALUE"""),"Completed") -> Completed | T19: =IFERROR(__xludf.DUMMYFUNCTION("""COMPUTED_VALUE"""),45876.504982488426) -> 45876.505 | U19: =IFERROR(__xludf.DUMMYFUNCTION("""COMPUTED_VALUE"""),45876.513026898145) -> 45876.513 | V19: =IFERROR(__xludf.DUMMYFUNCTION("""COMPUTED_VALUE"""),45877.0) -> 45877 | W19: {=DATEDIF(T19, V19, "D")} -> 1 | X19: =DATEDIF(T19, U19, "D") -> 0
A20: =IFERROR(__xludf.DUMMYFUNCTION("""COMPUTED_VALUE"""),2.50807002E8) -> 250807002 | B20: =IFERROR(__xludf.DUMMYFUNCTION("""COMPUTED_VALUE"""),"John") -> John | C20: =IFERROR(__xludf.DUMMYFUNCTION("""COMPUTED_VALUE"""),"JD") -> JD | D20: =IFERROR(__xludf.DUMMYFUNCTION("""COMPUTED_VALUE"""),"Doe") -> Doe | E20: =IFERROR(__xludf.DUMMYFUNCTION("""COMPUTED_VALUE"""),"JD") -> JD | F20: =IFERROR(__xludf.DUMMYFUNCTION("""COMPUTED_VALUE"""),45881.0) -> 45881 | G20: =IFERROR(__xludf.DUMMYFUNCTION("""COMPUTED_VALUE"""),"BMW Spartanburg Assembly") -> BMW Spartanburg Assembly | H20: =IFERROR(__xludf.DUMMYFUNCTION("""COMPUTED_VALUE"""),45881.0) -> 45881 | I20: =IFERROR(__xludf.DUMMYFUNCTION("""COMPUTED_VALUE"""),45876.569972881945) -> 45876.57 | J20: =IFERROR(__xludf.DUMMYFUNCTION("""COMPUTED_VALUE"""),45876.57631380787) -> 45876.576 | L20: =IFERROR(__xludf.DUMMYFUNCTION("""COMPUTED_VALUE"""),45876.577114444444) -> 45876.577 | M20: =IFERROR(__xludf.DUMMYFUNCTION("""COMPUTED_VALUE"""),45876.577088425925) -> 45876.577 | N20: =IFERROR(__xludf.DUMMYFUNCTION("""COMPUTED_VALUE"""),45876.579044363425) -> 45876.579 | O20: =IFERROR(__xludf.DUMMYFUNCTION("""COMPUTED_VALUE"""),45876.579081828706) -> 45876.579 | P20: =IFERROR(__xludf.DUMMYFUNCTION("""COMPUTED_VALUE"""),45876.57910930556) -> 45876.579 | R20: =IFERROR(__xludf.DUMMYFUNCTION("""COMPUTED_VALUE"""),45876.579145868054) -> 45876.579 | S20: =IFERROR(__xludf.DUMMYFUNCTION("""COMPUTED_VALUE"""),"Completed") -> Completed | T20: =IFERROR(__xludf.DUMMYFUNCTION("""COMPUTED_VALUE"""),45876.55894097222) -> 45876.559 | U20: =IFERROR(__xludf.DUMMYFUNCTION("""COMPUTED_VALUE"""),45876.586313541666) -> 45876.586 | V20: =IFERROR(__xludf.DUMMYFUNCTION("""COMPUTED_VALUE"""),45880.0) -> 45880 | W20: {=DATEDIF(T20, V20, "D")} -> 4 | X20: =DATEDIF(T20, U20, "D") -> 0
A21: =IFERROR(__xludf.DUMMYFUNCTION("""COMPUTED_VALUE"""),2.50808007E8) -> 250808007 | B21: =IFERROR(__xludf.DUMMYFUNCTION("""COMPUTED_VALUE"""),"John") -> John | C21: =IFERROR(__xludf.DUMMYFUNCTION("""COMPUTED_VALUE"""),"JD") -> JD | D21: =IFERROR(__xludf.DUMMYFUNCTION("""COMPUTED_VALUE"""),"Doe") -> Doe | E21: =IFERROR(__xludf.DUMMYFUNCTION("""COMPUTED_VALUE"""),"JD") -> JD | F21: =IFERROR(__xludf.DUMMYFUNCTION("""COMPUTED_VALUE"""),45896.0) -> 45896 | G21: =IFERROR(__xludf.DUMMYFUNCTION("""COMPUTED_VALUE"""),"Burns MacDonald") -> Burns MacDonald | H21: =IFERROR(__xludf.DUMMYFUNCTION("""COMPUTED_VALUE"""),45896.0) -> 45896 | I21: =IFERROR(__xludf.DUMMYFUNCTION("""COMPUTED_VALUE"""),45877.48650564815) -> 45877.487 | J21: =IFERROR(__xludf.DUMMYFUNCTION("""COMPUTED_VALUE"""),45877.48773008102) -> 45877.488 | N21: =IFERROR(__xludf.DUMMYFUNCTION("""COMPUTED_VALUE"""),45877.487574583334) -> 45877.488 | P21: =IFERROR(__xludf.DUMMYFUNCTION("""COMPUTED_VALUE"""),45877.487574583334) -> 45877.488 | S21: =IFERROR(__xludf.DUMMYFUNCTION("""COMPUTED_VALUE"""),"Completed") -> Completed | U21: =IFERROR(__xludf.DUMMYFUNCTION("""COMPUTED_VALUE"""),45877.48960327546) -> 45877.49 | V21: =IFERROR(__xludf.DUMMYFUNCTION("""COMPUTED_VALUE"""),45895.0) -> 45895 | W21: {=DATEDIF(T21, V21, "D")} -> 45895 | X21: =DATEDIF(T21, U21, "D") -> 45877
A22: =IFERROR(__xludf.DUMMYFUNCTION("""COMPUTED_VALUE"""),2.5080801E8) -> 250808010 | B22: =IFERROR(__xludf.DUMMYFUNCTION("""COMPUTED_VALUE"""),"John") -> John | C22: =IFERROR(__xludf.DUMMYFUNCTION("""COMPUTED_VALUE"""),"JD") -> JD | D22: =IFERROR(__xludf.DUMMYFUNCTION("""COMPUTED_VALUE"""),"Doe") -> Doe | E22: =IFERROR(__xludf.DUMMYFUNCTION("""COMPUTED_VALUE"""),"JD") -> JD | F22: =IFERROR(__xludf.DUMMYFUNCTION("""COMPUTED_VALUE"""),45897.0) -> 45897 | G22: =IFERROR(__xludf.DUMMYFUNCTION("""COMPUTED_VALUE"""),"Chrysler Brampton GSO") -> Chrysler Brampton GSO | H22: =IFERROR(__xludf.DUMMYFUNCTION("""COMPUTED_VALUE"""),45897.0) -> 45897 | I22: =IFERROR(__xludf.DUMMYFUNCTION("""COMPUTED_VALUE"""),45877.52985348379) -> 45877.53 | J22: =IFERROR(__xludf.DUMMYFUNCTION("""COMPUTED_VALUE"""),45877.538640729166) -> 45877.539 | S22: =IFERROR(__xludf.DUMMYFUNCTION("""COMPUTED_VALUE"""),"Completed") -> Completed | U22: =IFERROR(__xludf.DUMMYFUNCTION("""COMPUTED_VALUE"""),45877.54672288195) -> 45877.547 | V22: =IFERROR(__xludf.DUMMYFUNCTION("""COMPUTED_VALUE"""),45889.0) -> 45889 | W22: {=DATEDIF(T22, V22, "D")} -> 45889 | X22: =DATEDIF(T22, U22, "D") -> 45877
A23: =IFERROR(__xludf.DUMMYFUNCTION("""COMPUTED_VALUE"""),2.50808011E8) -> 250808011 | F23: =IFERROR(__xludf.DUMMYFUNCTION("""COMPUTED_VALUE"""),45896.0) -> 45896 | G23: =IFERROR(__xludf.DUMMYFUNCTION("""COMPUTED_VALUE"""),"Toyota Burnaston") -> Toyota Burnaston | H23: =IFERROR(__xludf.DUMMYFUNCTION("""COMPUTED_VALUE"""),45896.0) -> 45896 | I23: =IFERROR(__xludf.DUMMYFUNCTION("""COMPUTED_VALUE"""),45877.55041444444) -> 45877.55 | J23: =IFERROR(__xludf.DUMMYFUNCTION("""COMPUTED_VALUE"""),45877.55845434028) -> 45877.558 | S23: =IFERROR(__xludf.DUMMYFUNCTION("""COMPUTED_VALUE"""),"Completed") -> Completed | U23: =IFERROR(__xludf.DUMMYFUNCTION("""COMPUTED_VALUE"""),45877.558883101854) -> 45877.559 | V23: =IFERROR(__xludf.DUMMYFUNCTION("""COMPUTED_VALUE"""),45888.0) -> 45888 | W23: {=DATEDIF(T23, V23, "D")} -> 45888 | X23: =DATEDIF(T23, U23, "D") -> 45877
A24: =IFERROR(__xludf.DUMMYFUNCTION("""COMPUTED_VALUE"""),2.50811001E8) -> 250811001 | B24: =IFERROR(__xludf.DUMMYFUNCTION("""COMPUTED_VALUE"""),"John") -> John | C24: =IFERROR(__xludf.DUMMYFUNCTION("""COMPUTED_VALUE"""),"JD") -> JD | D24: =IFERROR(__xludf.DUMMYFUNCTION("""COMPUTED_VALUE"""),"Doe") -> Doe | E24: =IFERROR(__xludf.DUMMYFUNCTION("""COMPUTED_VALUE"""),"JD") -> JD | F24: =IFERROR(__xludf.DUMMYFUNCTION("""COMPUTED_VALUE"""),45888.0) -> 45888 | G24: =IFERROR(__xludf.DUMMYFUNCTION("""COMPUTED_VALUE"""),"GM Oshawa PPS") -> GM Oshawa PPS | H24: =IFERROR(__xludf.DUMMYFUNCTION("""COMPUTED_VALUE"""),45888.0) -> 45888 | I24: =IFERROR(__xludf.DUMMYFUNCTION("""COMPUTED_VALUE"""),45880.66227163194) -> 45880.662 | J24: =IFERROR(__xludf.DUMMYFUNCTION("""COMPUTED_VALUE"""),45880.66285303241) -> 45880.663 | S24: =IFERROR(__xludf.DUMMYFUNCTION("""COMPUTED_VALUE"""),"Completed") -> Completed | U24: =IFERROR(__xludf.DUMMYFUNCTION("""COMPUTED_VALUE"""),45880.66310542824) -> 45880.663 | V24: =IFERROR(__xludf.DUMMYFUNCTION("""COMPUTED_VALUE"""),45887.0) -> 45887 | W24: {=DATEDIF(T24, V24, "D")} -> 45887 | X24: =DATEDIF(T24, U24, "D") -> 45880
A25: =IFERROR(__xludf.DUMMYFUNCTION("""COMPUTED_VALUE"""),2.50811003E8) -> 250811003 | B25: =IFERROR(__xludf.DUMMYFUNCTION("""COMPUTED_VALUE"""),"Angie") -> Angie | C25: =IFERROR(__xludf.DUMMYFUNCTION("""COMPUTED_VALUE"""),"O") -> O | D25: =IFERROR(__xludf.DUMMYFUNCTION("""COMPUTED_VALUE"""),"O'Plasty") -> O'Plasty | G25: =IFERROR(__xludf.DUMMYFUNCTION("""COMPUTED_VALUE"""),"ArcelorMittal") -> ArcelorMittal | I25: =IFERROR(__xludf.DUMMYFUNCTION("""COMPUTED_VALUE"""),45880.69184714121) -> 45880.692 | J25: =IFERROR(__xludf.DUMMYFUNCTION("""COMPUTED_VALUE"""),45880.692413530094) -> 45880.692 | S25: =IFERROR(__xludf.DUMMYFUNCTION("""COMPUTED_VALUE"""),"Completed") -> Completed | U25: =IFERROR(__xludf.DUMMYFUNCTION("""COMPUTED_VALUE"""),45880.694000358795) -> 45880.694 | V25: =IFERROR(__xludf.DUMMYFUNCTION("""COMPUTED_VALUE"""),45880.0) -> 45880 | W25: {=DATEDIF(T25, V25, "D")} -> 45880 | X25: =DATEDIF(T25, U25, "D") -> 45880
A26: =IFERROR(__xludf.DUMMYFUNCTION("""COMPUTED_VALUE"""),2.50811004E8) -> 250811004 | B26: =IFERROR(__xludf.DUMMYFUNCTION("""COMPUTED_VALUE"""),"John") -> John | D26: =IFERROR(__xludf.DUMMYFUNCTION("""COMPUTED_VALUE"""),"O'Plasty") -> O'Plasty | F26: =IFERROR(__xludf.DUMMYFUNCTION("""COMPUTED_VALUE"""),45897.0) -> 45897 | G26: =IFERROR(__xludf.DUMMYFUNCTION("""COMPUTED_VALUE"""),"Chrysler Brampton") -> Chrysler Brampton | H26: =IFERROR(__xludf.DUMMYFUNCTION("""COMPUTED_VALUE"""),45897.0) -> 45897 | I26: =IFERROR(__xludf.DUMMYFUNCTION("""COMPUTED_VALUE"""),45880.70466894676) -> 45880.705 | J26: =IFERROR(__xludf.DUMMYFUNCTION("""COMPUTED_VALUE"""),45880.70676043982) -> 45880.707 | L26: =IFERROR(__xludf.DUMMYFUNCTION("""COMPUTED_VALUE"""),45880.70668800926) -> 45880.707 | S26: =IFERROR(__xludf.DUMMYFUNCTION("""COMPUTED_VALUE"""),"Completed") -> Completed | U26: =IFERROR(__xludf.DUMMYFUNCTION("""COMPUTED_VALUE"""),45881.41370305556) -> 45881.414 | V26: =IFERROR(__xludf.DUMMYFUNCTION("""COMPUTED_VALUE"""),45895.0) -> 45895 | W26: {=DATEDIF(T26, V26, "D")} -> 45895 | X26: =DATEDIF(T26, U26, "D") -> 45881
A27: =IFERROR(__xludf.DUMMYFUNCTION("""COMPUTED_VALUE"""),2.50812004E8) -> 250812004 | B27: =IFERROR(__xludf.DUMMYFUNCTION("""COMPUTED_VALUE"""),"May ") -> May | C27: =IFERROR(__xludf.DUMMYFUNCTION("""COMPUTED_VALUE"""),"B") -> B | D27: =IFERROR(__xludf.DUMMYFUNCTION("""COMPUTED_VALUE"""),"Tomorrow") -> Tomorrow | F27: =IFERROR(__xludf.DUMMYFUNCTION("""COMPUTED_VALUE"""),45884.0) -> 45884 | G27: =IFERROR(__xludf.DUMMYFUNCTION("""COMPUTED_VALUE"""),"BBI Enterprises") -> BBI Enterprises | H27: =IFERROR(__xludf.DUMMYFUNCTION("""COMPUTED_VALUE"""),45884.0) -> 45884 | I27: =IFERROR(__xludf.DUMMYFUNCTION("""COMPUTED_VALUE"""),45881.46093559028) -> 45881.461 | J27: =IFERROR(__xludf.DUMMYFUNCTION("""COMPUTED_VALUE"""),45881.46425895834) -> 45881.464 | S27: =IFERROR(__xludf.DUMMYFUNCTION("""COMPUTED_VALUE"""),"Completed") -> Completed | U27: =IFERROR(__xludf.DUMMYFUNCTION("""COMPUTED_VALUE"""),45881.46437565972) -> 45881.464 | V27: =IFERROR(__xludf.DUMMYFUNCTION("""COMPUTED_VALUE"""),45883.0) -> 45883 | W27: {=DATEDIF(T27, V27, "D")} -> 45883 | X27: =DATEDIF(T27, U27, "D") -> 45881
A28: =IFERROR(__xludf.DUMMYFUNCTION("""COMPUTED_VALUE"""),2.50812005E8) -> 250812005 | B28: =IFERROR(__xludf.DUMMYFUNCTION("""COMPUTED_VALUE"""),"Angie") -> Angie | D28: =IFERROR(__xludf.DUMMYFUNCTION("""COMPUTED_VALUE"""),"O'Plasty") -> O'Plasty | F28: =IFERROR(__xludf.DUMMYFUNCTION("""COMPUTED_VALUE"""),45888.0) -> 45888 | G28: =IFERROR(__xludf.DUMMYFUNCTION("""COMPUTED_VALUE"""),"PC Gaming") -> PC Gaming | H28: =IFERROR(__xludf.DUMMYFUNCTION("""COMPUTED_VALUE"""),45888.0) -> 45888 | I28: =IFERROR(__xludf.DUMMYFUNCTION("""COMPUTED_VALUE"""),45881.48929402778) -> 45881.489 | J28: =IFERROR(__xludf.DUMMYFUNCTION("""COMPUTED_VALUE"""),45881.49078258102) -> 45881.491 | L28: =IFERROR(__xludf.DUMMYFUNCTION("""COMPUTED_VALUE"""),45881.490887824075) -> 45881.491 | S28: =IFERROR(__xludf.DUMMYFUNCTION("""COMPUTED_VALUE"""),"Completed") -> Completed | T28: =IFERROR(__xludf.DUMMYFUNCTION("""COMPUTED_VALUE"""),45881.47328465278) -> 45881.473 | U28: =IFERROR(__xludf.DUMMYFUNCTION("""COMPUTED_VALUE"""),45881.49110421297) -> 45881.491 | V28: =IFERROR(__xludf.DUMMYFUNCTION("""COMPUTED_VALUE"""),45887.0) -> 45887 | W28: {=DATEDIF(T28, V28, "D")} -> 6 | X28: =DATEDIF(T28, U28, "D") -> 0
A29: =IFERROR(__xludf.DUMMYFUNCTION("""COMPUTED_VALUE"""),2.50812007E8) -> 250812007 | B29: =IFERROR(__xludf.DUMMYFUNCTION("""COMPUTED_VALUE"""),"John") -> John | D29: =IFERROR(__xludf.DUMMYFUNCTION("""COMPUTED_VALUE"""),"Athon") -> Athon | F29: =IFERROR(__xludf.DUMMYFUNCTION("""COMPUTED_VALUE"""),45898.0) -> 45898 | G29: =IFERROR(__xludf.DUMMYFUNCTION("""COMPUTED_VALUE"""),"Ventra Group ") -> Ventra Group | H29: =IFERROR(__xludf.DUMMYFUNCTION("""COMPUTED_VALUE"""),45898.0) -> 45898 | I29: =IFERROR(__xludf.DUMMYFUNCTION("""COMPUTED_VALUE"""),45881.52260960648) -> 45881.523 | J29: =IFERROR(__xludf.DUMMYFUNCTION("""COMPUTED_VALUE"""),45881.52437180556) -> 45881.524 | L29: =IFERROR(__xludf.DUMMYFUNCTION("""COMPUTED_VALUE"""),45881.52460265046) -> 45881.525 | N29: =IFERROR(__xludf.DUMMYFUNCTION("""COMPUTED_VALUE"""),45881.52453920139) -> 45881.525 | P29: =IFERROR(__xludf.DUMMYFUNCTION("""COMPUTED_VALUE"""),45881.52453920139) -> 45881.525 | S29: =IFERROR(__xludf.DUMMYFUNCTION("""COMPUTED_VALUE"""),"Completed") -> Completed | T29: =IFERROR(__xludf.DUMMYFUNCTION("""COMPUTED_VALUE"""),45881.514088599535) -> 45881.514 | U29: =IFERROR(__xludf.DUMMYFUNCTION("""COMPUTED_VALUE"""),45881.52821744213) -> 45881.528 | V29: =IFERROR(__xludf.DUMMYFUNCTION("""COMPUTED_VALUE"""),45897.0) -> 45897 | W29: {=DATEDIF(T29, V29, "D")} -> 16 | X29: =DATEDIF(T29, U29, "D") -> 0
A30: =IFERROR(__xludf.DUMMYFUNCTION("""COMPUTED_VALUE"""),2.50812008E8) -> 250812008 | B30: =IFERROR(__xludf.DUMMYFUNCTION("""COMPUTED_VALUE"""),"May ") -> May | C30: =IFERROR(__xludf.DUMMYFUNCTION("""COMPUTED_VALUE"""),"B") -> B | D30: =IFERROR(__xludf.DUMMYFUNCTION("""COMPUTED_VALUE"""),"Tomorrow") -> Tomorrow | E30: =IFERROR(__xludf.DUMMYFUNCTION("""COMPUTED_VALUE"""),"B") -> B | F30: =IFERROR(__xludf.DUMMYFUNCTION("""COMPUTED_VALUE"""),45895.0) -> 45895 | G30: =IFERROR(__xludf.DUMMYFUNCTION("""COMPUTED_VALUE"""),"Bunge Canada") -> Bunge Canada | H30: =IFERROR(__xludf.DUMMYFUNCTION("""COMPUTED_VALUE"""),45895.0) -> 45895 | I30: =IFERROR(__xludf.DUMMYFUNCTION("""COMPUTED_VALUE"""),45881.537617361115) -> 45881.538 | J30: =IFERROR(__xludf.DUMMYFUNCTION("""COMPUTED_VALUE"""),45881.55289924769) -> 45881.553 | K30: =IFERROR(__xludf.DUMMYFUNCTION("""COMPUTED_VALUE"""),45881.552874155095) -> 45881.553 | S30: =IFERROR(__xludf.DUMMYFUNCTION("""COMPUTED_VALUE"""),"Completed") -> Completed | T30: =IFERROR(__xludf.DUMMYFUNCTION("""COMPUTED_VALUE"""),45881.535921608796) -> 45881.536 | U30: =IFERROR(__xludf.DUMMYFUNCTION("""COMPUTED_VALUE"""),45881.55292379629) -> 45881.553 | V30: =IFERROR(__xludf.DUMMYFUNCTION("""COMPUTED_VALUE"""),45894.0) -> 45894
A31: =IFERROR(__xludf.DUMMYFUNCTION("""COMPUTED_VALUE"""),2.50826001E8) -> 250826001 | B31: =IFERROR(__xludf.DUMMYFUNCTION("""COMPUTED_VALUE"""),"John") -> John | D31: =IFERROR(__xludf.DUMMYFUNCTION("""COMPUTED_VALUE"""),"Doe") -> Doe | E31: =IFERROR(__xludf.DUMMYFUNCTION("""COMPUTED_VALUE"""),"Johnny") -> Johnny | F31: =IFERROR(__xludf.DUMMYFUNCTION("""COMPUTED_VALUE"""),45896.0) -> 45896 | G31: =IFERROR(__xludf.DUMMYFUNCTION("""COMPUTED_VALUE"""),"Geely YuYao") -> Geely YuYao | H31: =IFERROR(__xludf.DUMMYFUNCTION("""COMPUTED_VALUE"""),45896.0) -> 45896 | I31: =IFERROR(__xludf.DUMMYFUNCTION("""COMPUTED_VALUE"""),45895.4794559838) -> 45895.479 | J31: =IFERROR(__xludf.DUMMYFUNCTION("""COMPUTED_VALUE"""),45895.48259680555) -> 45895.483 | S31: =IFERROR(__xludf.DUMMYFUNCTION("""COMPUTED_VALUE"""),"Completed") -> Completed | T31: =IFERROR(__xludf.DUMMYFUNCTION("""COMPUTED_VALUE"""),45895.47522334491) -> 45895.475 | U31: =IFERROR(__xludf.DUMMYFUNCTION("""COMPUTED_VALUE"""),45895.483423784724) -> 45895.483 | V31: =IFERROR(__xludf.DUMMYFUNCTION("""COMPUTED_VALUE"""),45895.0) -> 45895
A32: =IFERROR(__xludf.DUMMYFUNCTION("""COMPUTED_VALUE"""),2.50826002E8) -> 250826002 | B32: =IFERROR(__xludf.DUMMYFUNCTION("""COMPUTED_VALUE"""),"John") -> John | D32: =IFERROR(__xludf.DUMMYFUNCTION("""COMPUTED_VALUE"""),"Doe") -> Doe | F32: =IFERROR(__xludf.DUMMYFUNCTION("""COMPUTED_VALUE"""),45897.0) -> 45897 | G32: =IFERROR(__xludf.DUMMYFUNCTION("""COMPUTED_VALUE"""),"Geely YuYao") -> Geely YuYao | H32: =IFERROR(__xludf.DUMMYFUNCTION("""COMPUTED_VALUE"""),45897.0) -> 45897 | I32: =IFERROR(__xludf.DUMMYFUNCTION("""COMPUTED_VALUE"""),45895.48109450232) -> 45895.481 | J32: =IFERROR(__xludf.DUMMYFUNCTION("""COMPUTED_VALUE"""),45895.48507277778) -> 45895.485 | N32: =IFERROR(__xludf.DUMMYFUNCTION("""COMPUTED_VALUE"""),45895.48529287037) -> 45895.485 | O32: =IFERROR(__xludf.DUMMYFUNCTION("""COMPUTED_VALUE"""),45895.4853922801) -> 45895.485 | P32: =IFERROR(__xludf.DUMMYFUNCTION("""COMPUTED_VALUE"""),45895.48529287037) -> 45895.485 | S32: =IFERROR(__xludf.DUMMYFUNCTION("""COMPUTED_VALUE"""),"Completed") -> Completed | T32: =IFERROR(__xludf.DUMMYFUNCTION("""COMPUTED_VALUE"""),45895.477966481485) -> 45895.478 | U32: =IFERROR(__xludf.DUMMYFUNCTION("""COMPUTED_VALUE"""),45895.4893078125) -> 45895.489 | V32: =IFERROR(__xludf.DUMMYFUNCTION("""COMPUTED_VALUE"""),45896.0) -> 45896
A33: =IFERROR(__xludf.DUMMYFUNCTION("""COMPUTED_VALUE"""),2.50826003E8) -> 250826003 | B33: =IFERROR(__xludf.DUMMYFUNCTION("""COMPUTED_VALUE"""),"John") -> John | C33: =IFERROR(__xludf.DUMMYFUNCTION("""COMPUTED_VALUE"""),"JD") -> JD | D33: =IFERROR(__xludf.DUMMYFUNCTION("""COMPUTED_VALUE"""),"Doe") -> Doe | E33: =IFERROR(__xludf.DUMMYFUNCTION("""COMPUTED_VALUE"""),"Johnny") -> Johnny | F33: =IFERROR(__xludf.DUMMYFUNCTION("""COMPUTED_VALUE"""),45902.0) -> 45902 | G33: =IFERROR(__xludf.DUMMYFUNCTION("""COMPUTED_VALUE"""),"Detroit Edison ") -> Detroit Edison | H33: =IFERROR(__xludf.DUMMYFUNCTION("""COMPUTED_VALUE"""),45902.0) -> 45902 | I33: =IFERROR(__xludf.DUMMYFUNCTION("""COMPUTED_VALUE"""),45895.49650013889) -> 45895.497 | J33: =IFERROR(__xludf.DUMMYFUNCTION("""COMPUTED_VALUE"""),45895.50679490741) -> 45895.507 | S33: =IFERROR(__xludf.DUMMYFUNCTION("""COMPUTED_VALUE"""),"Completed") -> Completed | T33: =IFERROR(__xludf.DUMMYFUNCTION("""COMPUTED_VALUE"""),45895.493165798616) -> 45895.493 | U33: =IFERROR(__xludf.DUMMYFUNCTION("""COMPUTED_VALUE"""),45895.50793797454) -> 45895.508 | V33: =IFERROR(__xludf.DUMMYFUNCTION("""COMPUTED_VALUE"""),45901.0) -> 45901
A34: =IFERROR(__xludf.DUMMYFUNCTION("""COMPUTED_VALUE"""),2.51125004E8) -> 251125004 | B34: =IFERROR(__xludf.DUMMYFUNCTION("""COMPUTED_VALUE"""),"DANIEL") -> DANIEL | D34: =IFERROR(__xludf.DUMMYFUNCTION("""COMPUTED_VALUE"""),"BINNS") -> BINNS | F34: =IFERROR(__xludf.DUMMYFUNCTION("""COMPUTED_VALUE"""),45986.0) -> 45986 | G34: =IFERROR(__xludf.DUMMYFUNCTION("""COMPUTED_VALUE"""),"Chrysler Brampton") -> Chrysler Brampton | H34: =IFERROR(__xludf.DUMMYFUNCTION("""COMPUTED_VALUE"""),45986.0) -> 45986 | I34: =IFERROR(__xludf.DUMMYFUNCTION("""COMPUTED_VALUE"""),45986.71939334491) -> 45986.719 | J34: =IFERROR(__xludf.DUMMYFUNCTION("""COMPUTED_VALUE"""),45986.7214671875) -> 45986.721 | S34: =IFERROR(__xludf.DUMMYFUNCTION("""COMPUTED_VALUE"""),"Completed") -> Completed | T34: =IFERROR(__xludf.DUMMYFUNCTION("""COMPUTED_VALUE"""),45986.71163521991) -> 45986.712 | U34: =IFERROR(__xludf.DUMMYFUNCTION("""COMPUTED_VALUE"""),45986.72342628472) -> 45986.723 | V34: =IFERROR(__xludf.DUMMYFUNCTION("""COMPUTED_VALUE"""),45986.0) -> 45986
